Workbook

Sheet README
A1: TSPi Team Workbook - TMA3084 Software Engineering Laboratory
A2: Faculty of Computer Science & Information Technology, UNIMAS | Semester 1, Session 2026/2027 | Workbook v3.0 (2026-10-29)
B3: WORKED SAMPLE - all names, matric numbers, emails, phone numbers and the client are fictional. The time, task and defect data is migrated from a real past team's workbooks with identities removed; the test, AI, client, GitHub and evaluation forms are illustrative, written to show what a complete workbook looks like. Do not copy the numbers - copy the habit.
B4: What this is | C4: A Team Software Process (TSP) team workbook rebuilt for TMA3084. It keeps the TSP measurement discipline - time, defects, size, earned value - and adds the forms this course actually assesses: AI-assisted coding, automated testing, GitHub workflow, client engagement and peer evaluation.
B5: Lineage | C5: The process model follows the Team Software Process introduced by Watts S. Humphrey. The original TSPi support workbook (2002, Addison-Wesley) is the ancestor of this file; every sheet here has been rewritten for this course. Forms, phases, defect types and all guidance text are original to TMA3084.
B6: What changed from the 2002 workbook | C6: NEW forms: LOGAI (AI-assisted development), LOGTEST (test cases), LOGCLIENT (client meetings), LOGGIT (GitHub activity), CCR (change requests), PEER, TEAMEVAL, ASSESS, DASHBOARD, FORM-SI. MODERNISED: phase set now covers AI generation, pull-request review, static analysis, widget test and CI/CD; defect types extended with UI/Layout, State Management, Performance, Security and AI-Generated; size measures cover screens, widgets and API endpoints alongside LOC. REMOVED: the single-week WEEK form is now a 13-week tracking table, and the PSP-style prediction intervals are dropped as the team has no historical data base.
B7: Colour convention | C7: AMBER cells are yours to fill in. GREY cells are calculated - typing over one destroys the rollup. Every drop-down is fed by the LISTS sheet.
B8: How to run it | C8: 1. Fill SETUP once, then FORM-SI with every member. 2. Agree roles in ROLES and goals in GOALS. 3. Plan each cycle in TASK and SCHEDULE. 4. Record daily in LOGT, LOGD, LOGTEST and LOGAI. 5. Hold the weekly meeting against WEEK and IRTL. 6. SUMP, SUMQ, SUMS and DASHBOARD fill themselves.
B9: One workbook per team | C9: The team keeps one shared copy in the repository (docs/tspi/). Each member records their own rows in the logs and tags them with their name, so individual contribution is traceable without separate files.
B10: Honesty clause | C10: These numbers are the evidence behind Peer/Individual and Team Evaluation. Logging work you did not do, or back-filling a term's worth of hours the night before a milestone, is academic dishonesty and the pattern is visible in DASHBOARD.
A12: Milestones
B13: Milestone | C13: Week / Due | D13: Deliverables
B14: M1 Proposal & Planning (10%) | C14: Week 5 - due 25 Oct 2026 | Proposal, SRS draft, GitHub repo, Team Charter, client approval, >=2 client meetings
B15: M2 Requirements & Design (15%) | C15: Week 9 - due 20 Nov 2026 | Revised SRS, SDD, Flutter prototype (4-5 screens), >=10 LOGAI entries, test plan (>=20 cases), >=4 client meetings
B16: M3 Implementation & Testing (35%) | C16: Week 13 - due 20 Dec 2026 | Final SDD, >=50 tests at >=60% coverage, GitHub Actions green, APK/IPA build, >=6 client meetings
B17: M4 Release & Oral Commitment (40%) | C17: Week 15 - due 02 Jan 2027 | Final report, user manual, demo video 5-10 min, presentation, client sign-off, v1.0.0 release

Sheet MANUAL
A1: How to Use This Workbook
A2: TMA3084 Software Engineering Laboratory - a step-by-step manual for the team. Read this once, together, at the launch meeting.
A4: 1. What this workbook is
B5: The short version | C5: This is a Team Software Process (TSP) workbook. TSP is a way of running a software project where the team plans its own work, measures what actually happens, and uses those measurements to plan better next time. The workbook is where the measuring happens.
B6: Why bother | C6: Three questions decide most student projects: are we going to finish on time, is the thing we are building any good, and is everyone actually contributing. Opinions on all three are usually wrong. This workbook answers them with data the team collected itself.
B7: The four things you record | C7: TIME - how long work actually took, not how long it felt. SIZE - how much you built. DEFECTS - every mistake found, and the phase where it was made. STATUS - which tasks are finished. Everything else on the summary sheets is arithmetic on those four.
B8: What it is not | C8: It is not a surveillance tool and it is not graded on neatness. Nobody is marked down for a high defect count - a team recording 40 defects is doing better engineering than an identical team recording 3, because the second team is not looking. What does get noticed is a log that is empty, or one filled in all at once the night before a milestone.
A10: 2. Before you start - conventions
B11: Convention | C11: What it means
B12: Amber cells | C12: You type here. Everything the team knows goes into an amber cell.
B13: Grey cells | C13: Calculated. Typing over one breaks the rollups that depend on it - if a grey number looks wrong, the log feeding it is wrong, so fix the log.
B14: Drop-downs | C14: Fed by the LISTS sheet. Member names come from FORM-SI, so fill FORM-SI first or every name drop-down in the workbook will be empty.
B15: Red / amber / green | C15: Applied automatically. Red is not a punishment, it is a prompt to talk about something at the next meeting.
B16: Hover for help | C16: Cells with a small red corner marker carry a note explaining what goes in them.
B17: Reference sheets | C17: PHASES and DEFECTTYPES are the standards you code against - read them in Week 1. PLANGUIDE and QUALGUIDE tell you what to aim for. None of the four should ever be edited.
B18: Charts | C18: PROJECT and CHARTS draw themselves from the logs. There is no Draw button and nothing to refresh - if a chart is empty, the log behind it is empty.
A20: 3. Stage one - the launch (do this in Week 1, and again at the start of every cycle)
A21: # | B21: Step | C21: What to do | D21: Form | E21: Who / when
A22: 1 | B22: Fill in SETUP | C22: Course details, team name, project title, client, repository URL and team size. Then check the milestone dates against the course outline and set the thresholds. Every other sheet reads its header from here, so this is the one place you type the team name. | D22: SETUP | E22: Team Leader, Week 1
A23: 2 | B23: Enter every member | C23: One row per member in FORM-SI: matric number, full name, UNIMAS email, GitHub handle. The name you type here is the name that appears in every drop-down, so agree on a spelling and do not change it later. | D23: FORM-SI | E23: All members, Week 1
A24: 3 | B24: Write the team charter | C24: The lower half of FORM-SI. Six short answers: vision, communication norms, definition of done, conflict resolution, quality standards, expected hours. Write these before you disagree about them, not after. | D24: FORM-SI | E24: Team, Week 1
A25: 4 | B25: Assign roles | C25: There are six roles and five of you, so one member holds two this cycle and nobody holds more than two. The double rotates, and nobody keeps the same role for more than two milestones running. The Role Load Check at the bottom of the sheet adds this up for you. A role is real work, not a title. | D25: ROLES | E25: Team Leader, each launch
A26: 5 | B26: Set measurable goals | C26: A goal needs a number and an owner or it is a wish. Seven starter goals are listed at the bottom of the sheet; replace them with your own. | D26: GOALS | E26: Team, each launch
A27: 6 | B27: Agree the strategy | C27: What each cycle actually delivers, what you build versus reuse, the main technical risk and who owns it. Then record the stack decisions and why - the Design rubric asks you to justify alternatives considered. | D27: STRAT | E27: Dev Manager, each launch
A28: 7 | B28: Size what you are building | C28: List the screens, modules and documents in SUMS with a planned size. Estimates will be wrong early on. Record them anyway - a wrong estimate you measured against is worth more than no estimate. | D28: SUMS | E28: Planning Manager
A29: 8 | B29: Break the work into tasks | C29: Tasks of roughly 2 to 10 hours, each with one owner, a phase, planned hours and a planned week. A task bigger than 10 hours is hiding something. | D29: TASK | E29: Planning Manager
A30: 9 | B30: Spread it across the weeks | C30: Put the hours each week in SCHEDULE. Check the Difference cell at the top: schedule hours must match task hours. If they do not, one of the two plans is fiction. | D30: SCHEDULE | E30: Planning Manager
A32: 4. Stage two - daily discipline (the habit that makes everything else work)
A33: # | B33: Step | C33: What to do | D33: Form | E33: Who / when
A34: 10 | B34: Log time as you work | C34: Start a LOGT row when you sit down, fill in the stop time when you get up. Subtract interruptions honestly. Reconstructing a week of hours from memory produces numbers that are worse than useless, because they look real. | D34: LOGT | E34: Every member, daily
A35: 11 | B35: Tag the task | C35: Put the Task ID from TASK in the Task ID column. That is what makes hours roll up against the plan. Unplanned work with no ID is fine - add the task to TASK afterwards so the plan stays honest. | D35: LOGT | E35: Every member, daily
A36: 12 | B36: Log every defect | C36: Anything wrong that you had to fix, including the ones you found yourself within a minute. The hard column is Injected in: the phase where the mistake was MADE, not where you noticed it. Getting that right is the whole point. | D36: LOGD | E36: Every member, daily
A37: 13 | B37: Log every test | C37: One row per test case with its type and status. Automated tests get a row too - LOGTEST is the evidence behind the Testing and Release rubric, not a duplicate of your test files. | D37: LOGTEST | E37: Quality & Test Manager, daily
A38: 14 | B38: Log every AI-assisted change | C38: Any time Copilot, Claude or another generator wrote code that reached the repository: what you asked for, how many lines it gave you, how many survived review, who reviewed it, and whether tests were written. The reviewer must not be you - the sheet turns that row red. | D38: LOGAI | E38: Every member, each change
A39: 15 | B39: Record client meetings | C39: Date, mode, who attended, what was decided, what actions came out and who owns them. Keep the minutes or a photo as evidence. The milestones require 2, 4 and 6 cumulative meetings - this is how you prove it. | D39: LOGCLIENT | E39: Product Owner
A41: 5. Stage three - the weekly meeting (about 30 minutes, same time every week)
A42: # | B42: Step | C42: What to do | D42: Form | E42: Who / when
A43: 16 | B43: Pull the GitHub numbers | C43: Commits, pull requests, reviews and issues closed per member, read from the repository Insights tab. These are facts - do not estimate them. | D43: LOGGIT | E43: Support Manager, weekly
A44: 17 | B44: Update task status | C44: Mark finished tasks Complete. Earned value is only credited for completed tasks; a task that is 90% done earns nothing. That is deliberate - it is what stops a plan from slipping quietly. | D44: TASK | E44: Planning Manager, weekly
A45: 18 | B45: Read the week's numbers | C45: WEEK fills itself from SCHEDULE. Look at EV variance: negative means the team has delivered less than it planned by this week, however many hours it has burned. Hours are effort; earned value is progress. | D45: WEEK | E45: Team Leader, weekly
A46: 19 | B46: Raise risks and issues | C46: A risk might happen, an issue already has. Both need a likelihood, an impact, an owner and a follow-up date. Priority is calculated; anything scoring 6 or more goes red and gets discussed. | D46: IRTL | E46: Team Leader, weekly
A47: 20 | B47: Handle change requests | C47: Once the client has agreed a baseline, changes go through CCR with an estimate and a decision - not through a quiet commit. This is also how scope creep becomes visible instead of mysterious. | D47: CCR | E47: Support Manager, as needed
A48: 21 | B48: Check the dashboard | C48: Milestone readiness, effort, quality and contribution on one screen. Anything red is the agenda for the next ten minutes. | D48: DASHBOARD | E48: Team, weekly
A49: 22 | B49: Talk about contribution | C49: The contribution panel compares each member's hours, commits, reviews and AI entries against an even share. A flag is a prompt for a conversation, not an accusation - someone may be carrying work the logs do not capture, and if so, that is worth knowing too. | D49: DASHBOARD | E49: Team, weekly
A50: 23 | B50: Write next week's commitment | C50: One line in WEEK saying what the team will have finished by the next meeting. Then check it at that meeting. This single habit does more for delivery than any tool. | D50: WEEK | E50: Team Leader, weekly
A52: 6. Stage four - closing a milestone (the postmortem)
A53: # | B53: Step | C53: What to do | D53: Form | E53: Who / when
A54: 24 | B54: Record actual sizes | C54: Go back to SUMS and fill the actual columns, plus actual SRS and SDD pages. Without actual size there is no defect density and no productivity figure. | D54: SUMS | E54: Planning Manager
A55: 25 | B55: Check the plan summary | C55: SUMP now shows where the time went, where defects were injected and where they were removed. Compare the Actual % column against your plan. The gap between them is the lesson. | D55: SUMP | E55: Planning Manager
A56: 26 | B56: Read the quality summary | C56: SUMQ is where the uncomfortable truths live: review rates that were too fast, A/FR below 2.0, process yield under 70%. Each one predicts a specific kind of pain in the next cycle. | D56: SUMQ | E56: Quality & Test Manager
A57: 27 | B57: Enter the coverage figure | C57: One manual cell on SUMQ, read from the coverage job in GitHub Actions. Do not estimate it. | D57: SUMQ | E57: Quality & Test Manager
A58: 28 | B58: Run the peer evaluation | C58: Each member rates every member including themselves, 1 to 5, across the 10 rubric categories. Self-ratings are reported separately so they cannot inflate anyone's score. Rate what people did, not whether you like them. | D58: PEER | E58: All members, each milestone
A59: 29 | B59: Run the team evaluation | C59: Ten statements about how the team works, rated 1 to 5. Then look at the spread, not just the mean - where members disagree sharply is the thing worth discussing. Agree actions at the bottom of the sheet. | D59: TEAMEVAL | E59: All members, each milestone
A60: 30 | B60: Update the assessment tracker | C60: ASSESS maps every rubric to the forms that produce its evidence. Peer and Team Evaluation fill themselves; the rest are entered by the instructor. | D60: ASSESS | E60: Team Leader
A61: 31 | B61: Look at the charts together | C61: Open CHARTS and read them as a team. The four that matter most are Cumulative Earned Value (did we deliver what we planned), Defects Removed by Phase (are we catching them early), Review Rates (did we read fast enough to miss things) and Process Yield (what reached test). A number on a sheet is arguable; a line going the wrong way for six weeks is not. | D61: CHARTS | E61: Team, each milestone
A62: 32 | B62: Agree three changes | C62: Not twenty. Pick three things the team will do differently next cycle, write them into GOALS with an owner, and check them at the next postmortem. A postmortem that changes nothing was just a meeting. | D62: GOALS | E62: Team, each milestone
A64: 7. Every form, and what it is for
B65: Form | C65: What it holds | D65: Who owns it | E65: Feeds into
B66: SETUP | C66: Course, team, client, repository, milestone plan and the thresholds that drive the dashboard traffic lights. | D66: Team Leader | E66: Every sheet header, DASHBOARD
B67: FORM-SI | C67: Member details, the team charter, and each member's planned versus actual hours with a contribution flag. | D67: All members | E67: Every name drop-down, DASHBOARD
B68: ROLES | C68: Which of the six TSP roles each member holds in each milestone, what that role owns, and a check that nobody is carrying more than two. | D68: Team Leader | E68: -
B69: GOALS | C69: Measurable team goals with a target, an owner and a review date. | D69: Team | E69: -
B70: STRAT | C70: What each cycle delivers, build-versus-reuse decisions, technical risks, and the technology stack with justification. | D70: Dev Manager | E70: Design rubric evidence
B71: TASK | C71: Every task with owner, phase, estimate, planned week, status and earned value. Actual hours arrive automatically from LOGT. | D71: Planning Manager | E71: SCHEDULE, WEEK, FORM-SI, DASHBOARD
B72: SCHEDULE | C72: Planned hours per week from Week 3 to Week 15, against actual hours and earned value. | D72: Planning Manager | E72: WEEK, DASHBOARD
B73: LOGT | C73: One row per working session: date, member, phase, task, start, stop and interruptions. The single most important sheet in the workbook. | D73: Every member | E73: TASK, SCHEDULE, SUMP, SUMQ, FORM-SI, DASHBOARD
B74: LOGD | C74: Every defect found: type, component, the phase it was injected in, the phase it was removed in, fix time, severity, and whether it came from AI-generated code. | D74: Every member | E74: SUMP, SUMQ, DASHBOARD
B75: LOGTEST | C75: Every test case with type, expected and actual result, status, tester and whether it is automated. | D75: Quality & Test Manager | E75: SUMQ, DASHBOARD
B76: LOGAI | C76: Every AI-assisted change: tool, prompt, lines generated, lines kept, reviewer, verdict and test status. Self-review is flagged red. | D76: Every member | E76: SUMP, DASHBOARD
... B99: LISTS | C99: The source lists behind every drop-down. Leave it alone unless you are adding a role or a size measure. | D99: - | E99: -
A101: 8. Worked examples
B102: Situation | C102: What you record
B103: You spend the morning writing the SRS, with a 15-minute phone call in the middle | C103: LOGT: date 20-Oct-26, member your name, milestone M1, phase REQ, task ID T01, start 09:00, stop 12:00, interrupt 15. Delta calculates as 165 minutes. Week fills in by itself.
B104: During the code review of a login screen, you find a null check that was never written | C104: LOGD: type 60 - Checking, component auth_module, injected in CODE (the mistake was made while coding), removed in CR (you found it in review), fix time 8 minutes, severity Major, from AI code No.
B105: Copilot generates a form validator; you keep about three quarters of it after review | C105: LOGAI: tool GitHub Copilot, lines generated 60, lines kept 45, reviewer a teammate's name - not yours - verdict Approved with changes, tests written Yes, commit reference PR#7, approved Yes.
B106: A test that passed last week now fails after a refactor | C106: LOGTEST: update that test's row to Fail with today's date. Then raise the defect in LOGD with injected phase CODE and removed phase UT, and link the two with the defect reference.
B107: The client asks for an extra screen three weeks before release | C107: CCR: change type Requirement, what changes and why, estimated hours, affected milestone, reviewer and decision. If approved, add the tasks to TASK so the plan reflects reality.
A109: 9. Things that go wrong
B110: Symptom | C110: Cause and fix
B111: The name drop-downs are empty | C111: FORM-SI has no names in it yet. Every member drop-down in the workbook reads column C of FORM-SI rows 9 to 14. Fill those first.
B112: A summary number has not changed after I logged work | C112: Press F9, or close and reopen the file. If it still looks wrong, check the phase or task ID you typed in the log - a typo means the row matches nothing and is silently excluded.
B113: Hours are logged but TASK shows zero actual hours | C113: The Task ID column in LOGT is blank or does not match an ID in TASK. The match is exact, so T1 and T01 are different tasks.
B114: Defect density and review rates are blank | C114: SUMS has no actual size recorded, so there is nothing to divide by. Fill the actual columns in SUMS at the end of each milestone.
B115: Someone's peer score looks far too low | C115: Check that every member filled in their own rating block. An empty block is ignored rather than counted as zero, but a block filled in for only some members will skew the average.
B116: A grey cell shows a wrong number and I want to correct it | C116: Do not type over it. Find the log row that is wrong and fix that. Overwriting a calculated cell breaks the formula permanently and every number downstream of it.
B117: We forgot to log for two weeks | C117: Reconstruct what you honestly can, mark those rows in the comments column, and say so at the weekly meeting. Inventing plausible numbers is worse than admitting a gap - the gap is recoverable, fabricated data quietly corrupts every conclusion the team draws for the rest of the project.
A119: 10. One last thing
B120: The workbook cannot make the team work well. What it can do is make it obvious, early and to everyone, when the team is not - while there is still time to do something about it. A team that logs honestly and looks at the numbers every week will finish; a team that fills this in the weekend before submission will have a very tidy record of a project that went wrong.

Sheet INDEX
A1: Index of Forms
A2: Click a form name to jump to it.
A4: Start here
B5: Form | C5: What it is for | D5: Owner | E5: When
B6: MANUAL | C6: Step-by-step manual: what to do, when, and on which form | D6: Read at launch | E6: Week 1
B7: PROJECT | C7: Project summary: headline numbers and the two charts that matter most | D7: Automatic | E7: Always
A9: Launch - do these once, at the start of each cycle
B10: Form | C10: What it is for | D10: Owner | E10: When
B11: SETUP | C11: Course, team, client, repository and the milestone plan | D11: Team Leader | E11: Week 1
B12: FORM-SI | C12: Member details, contribution rollup and the team charter | D12: All members | E12: Week 1
B13: ROLES | C13: Who holds which of the six TSP roles in each milestone | D13: Team Leader | E13: Each launch
B14: GOALS | C14: Measurable team goals with owners and review dates | D14: Team | E14: Each launch
B15: STRAT | C15: What each cycle delivers, and the stack decisions behind it | D15: Dev Manager | E15: Each launch
A17: Plan - the commitment the team makes
B18: Form | C18: What it is for | D18: Owner | E18: When
B19: TASK | C19: Task plan, estimates, ownership and earned value | D19: Planning Manager | E19: Each launch
B20: SCHEDULE | C20: Hours per week, planned against earned value | D20: Planning Manager | E20: Each launch
A22: Record - fill these as the work happens, not afterwards
B23: Form | C23: What it is for | D23: Owner | E23: When
B24: LOGT | C24: Time recording log - one row per working session | D24: All members | E24: Daily
B25: LOGD | C25: Defect recording log - every defect, wherever found | D25: All members | E25: Daily
B26: LOGTEST | C26: Test case log with status, type and coverage evidence | D26: Quality & Test Mgr | E26: Daily
B27: LOGAI | C27: AI-assisted development log with reviewer and verdict | D27: All members | E27: Every AI change
B28: LOGCLIENT | C28: Client meetings, decisions, actions and sign-off | D28: Product Owner | E28: Each meeting
B29: LOGGIT | C29: Weekly GitHub activity read from repository Insights | D29: Support Manager | E29: Weekly
A31: Track - the weekly rhythm
B32: Form | C32: What it is for | D32: Owner | E32: When
B33: WEEK | C33: Weekly status: hours, earned value, risk and commitment | D33: Team Leader | E33: Weekly
B34: IRTL | C34: Issue and risk tracking with likelihood, impact and owner | D34: Team Leader | E34: Weekly
B35: IRWEEK | C35: How the risk picture moved week by week - raised, closed, still open | D35: Team Leader | E35: Weekly
B36: RISK | C36: The top open risks from IRTL, ranked by priority | D36: Automatic | E36: Weekly
B37: CCR | C37: Change requests against an agreed baseline | D37: Support Manager | E37: As needed
A39: Summarise - these calculate themselves
B40: Form | C40: What it is for | D40: Owner | E40: When
B41: SUMS | C41: Size summary for components and documents | D41: Planning Manager | E41: Each milestone
B42: SUMP | C42: Plan summary: size, time in phase, defects injected and removed | D42: Planning Manager | E42: Each milestone
B43: SUMQ | C43: Quality summary: density, yield, review rates, test quality | D43: Quality & Test Mgr | E43: Each milestone
B44: CHARTS | C44: The fourteen TSP charts, drawn from your own logs | D44: Automatic | E44: Always
A46: Evaluate - the assessed forms
B47: Form | C47: What it is for | D47: Owner | E47: When
B48: PEER | C48: Peer and individual evaluation, 10 categories out of 50 | D48: All members | E48: Each milestone
B49: TEAMEVAL | C49: Team dynamics evaluation, 10 variables out of 50 | D49: All members | E49: Each milestone
B50: ASSESS | C50: Assessment tracker mapped to the published rubrics | D50: Team Leader | E50: Each milestone
B51: DASHBOARD | C51: Readiness, effort, quality and contribution at a glance | D51: Automatic | E51: Always
A53: Standards and guidance - read these, do not edit them
B54: Form | C54: What it is for | D54: Owner | E54: When
B55: PHASES | C55: Process phase standard: every phase code, what belongs in it | D55: - | E55: Read in Week 1
B56: DEFECTTYPES | C56: Defect type standard with a Flutter example of each | D56: - | E56: Read in Week 1
B57: PLANGUIDE | C57: Planning guidelines: effort split and the rates to plan against | D57: - | E57: Each launch
B58: QUALGUIDE | C58: Quality guidelines: what good looks like on each SUMQ measure | D58: - | E58: Each milestone
B59: QPROFPARAM | C59: The five targets behind the Quality Profile chart | D59: Quality & Test Mgr | E59: Set once
A61: Machinery - calculated, leave alone
B62: Form | C62: What it is for | D62: Owner | E62: When
B63: CHARTDATA | C63: The series every chart reads from | D63: - | E63: -
B64: LISTS | C64: Source lists behind every drop-down in the workbook | D64: - | E64: -

Sheet PROJECT
A1: Project Summary
A2: The one page to open first. Everything here is calculated from the logs.
B4: Project | C4: =SETUP!$C$11 | E4: Report date | G4: =TODAY()
B5: Team | C5: =SETUP!$C$10 | E5: Current week | G5: =CHARTDATA!$D$4
B6: Client | C6: =SETUP!$C$12 | E6: Team size | G6: =SETUP!$C$16
B7: Instructor | C7: =SETUP!$C$7 | E7: Repository | G7: =SETUP!$C$14
A9: Headline Measures
B10: Planned hours | C10: Actual hours | D10: Planned value to date | E10: Earned value to date | F10: New & changed LOC | G10: Defects removed | H10: Defects / KLOC | I10: Test cases | J10: Test pass rate
B11: =SUM(TASK!$K$8:$K$127) | C11: =SUM(LOGT!$K$7:$K$406)/60 | D11: =CHARTDATA!$G$19 | E11: =CHARTDATA!$I$19 | F11: =SUMP!$C$10 | G11: =SUMP!$C$96 | H11: =IFERROR(SUMP!$C$96/(SUMP!$C$10/1000),"") | I11: =COUNTA(LOGTEST!$A$7:$A$306) | J11: =IFERROR(COUNTIF(LOGTEST!$H$7:$H$306,"Pass")/COUNTA(LOGTEST!$H$7:$H$306),"")
A13: Earned Value and Effort
A32: Where the team stands
B33: =IF(CHARTDATA!$I$19-CHARTDATA!$G$19<-0.1,"BEHIND - earned value is more than ten points below plan. Look at TASK for work that is started but not finished, and at DASHBOARD for who is carrying the load.",IF(CHARTDATA!$I$19-CHARTDATA!$G$19<-0.02,"AT RISK - slightly behind plan. Recoverable this week if the team finishes what it started.","ON TRACK - earned value is at or ahead of plan. Keep logging; the picture is only as good as the data behind it."))

Sheet SETUP
A1: Project Setup
A2: Fill this sheet once at team launch. Every other form reads from here.
A4: Team & Project Identification
B5: Course | C5: TMA3084 Software Engineering Laboratory
B6: Semester | C6: Semester 1, Session 2026/2027
B7: Instructor | C7: Ts. Nurfauza Jali
B8: Lab Demonstrator | C8: Mr. MD. Aminul Islam Rakib
B9: Lab Group (1 or 2) | C9: 1
B10: Team Name / Number | C10: AUV
B11: Project Title | C11: SeaFresh Supplier Mobile App
B12: Client Organisation | C12: SeaFresh Seafood Trading (sample client)
B13: Client Contact & Email | C13: Encik Faizal (sample) - faizal@seafresh.example
B14: GitHub Repository URL | C14: https://github.com/tma3084-sample/auv-seafresh
B15: Project Board URL | C15: https://github.com/orgs/tma3084-sample/projects/1
B16: Team Size | C16: 5
A18: Milestone Plan
A19: ID | B19: Milestone | C19: Week | D19: Start | E19: Due | F19: Weight | G19: Status | H19: Key Deliverables
A20: M1 | B20: Proposal & Planning | C20: 5 | D20: 46314 | E20: 46320 | F20: 0.1 | G20: Complete | H20: Proposal, SRS draft, GitHub repo, Team Charter, client approval, >=2 client meetings
A21: M2 | B21: Requirements & Design | C21: 9 | D21: 46342 | E21: 46346 | F21: 0.15 | G21: Complete | H21: Revised SRS, SDD, Flutter prototype (4-5 screens), >=10 LOGAI entries, test plan (>=20 cases), >=4 client meetings
A22: M3 | B22: Implementation & Testing | C22: 13 | D22: 46370 | E22: 46376 | F22: 0.35 | G22: Complete | H22: Final SDD, >=50 tests at >=60% coverage, GitHub Actions green, APK/IPA build, >=6 client meetings
A23: M4 | B23: Release & Oral Commitment | C23: 15 | D23: 46384 | E23: 46389 | F23: 0.4 | G23: In progress | H23: Final report, user manual, demo video 5-10 min, presentation, client sign-off, v1.0.0 release
A25: Course Thresholds (used by DASHBOARD to flag a team that is behind)
A26: Threshold | B26: M1 | C26: M2 | D26: M3 | E26: M4 | H26: Notes
A27: Minimum commits (cumulative) | B27: 15 | C27: 30 | D27: 50 | E27: 70 | H27: Git history, all branches merged to develop
A28: Minimum pull requests merged | B28: 3 | C28: 8 | D28: 15 | E28: 20 | H28: Every PR needs at least one reviewer approval
A29: Minimum client meetings (cumulative) | B29: 2 | C29: 4 | D29: 6 | E29: 7 | H29: Logged in LOGCLIENT with client sign-off
A30: Minimum LOGAI entries (cumulative) | B30: 2 | C30: 10 | D30: 15 | E30: 18 | H30: Every AI-assisted change reviewed and logged
A31: Minimum test cases (cumulative) | B31: 0 | C31: 20 | D31: 50 | E31: 60 | H31: LOGTEST; unit + widget + integration
A32: Minimum code coverage | B32: 0 | C32: 0.3 | D32: 0.6 | E32: 0.6 | H32: Critical business logic; from coverage report
A33: Minimum hours per member (cumulative) | B33: 15 | C33: 40 | D33: 80 | E33: 100 | H33: LOGT; flags under-contribution

Sheet FORM-SI
A1: Form SI - Student & Team Information
A2: One row per member. Names entered here feed every drop-down in the workbook.
B4: Team | C4: =SETUP!$C$10 | E4: Project | F4: =SETUP!$C$11
B5: Repository | C5: =SETUP!$C$14 | E5: Client | F5: =SETUP!$C$12
A7: Team Members
A8: # | B8: Matric No. | C8: Full Name | D8: UNIMAS Email | E8: Phone | F8: GitHub Handle | G8: Primary Role | H8: Secondary Role | I8: Plan Hrs | J8: Actual Hrs | K8: Share of Team Hrs | L8: Flag
A9: 1 | B9: 90001 | C9: Aisyah Binti Rahman | D9: 90001@siswa.unimas.my | E9: 011-2000 0001 | F9: aisyah-r | G9: Team Leader | H9: Support Manager | I9: =IF($C9="","",SUMIFS(TASK!$K$8:$K$127,TASK!$F$8:$F$127,$C9)) | J9: =IF($C9="","",SUMIFS(LOGT!$K$7:$K$406,LOGT!$B$7:$B$406,$C9)/60) | K9: =IF(OR($C9="",$J$15=0),"",$J9/$J$15) | L9: =IF($C9="","",IF($J9=0,"NO DATA",IF($K9<0.6/MAX(1,COUNTA($C$9:$C$14)),"LOW",IF($K9>1.6/MAX(1,COUNTA($C$9:$C$14)),"HIGH","OK"))))
A10: 2 | B10: 90002 | C10: Daniel Wong Jun Hao | D10: 90002@siswa.unimas.my | E10: 011-2000 0002 | F10: danielwjh | G10: Development Manager | I10: =IF($C10="","",SUMIFS(TASK!$K$8:$K$127,TASK!$F$8:$F$127,$C10)) | J10: =IF($C10="","",SUMIFS(LOGT!$K$7:$K$406,LOGT!$B$7:$B$406,$C10)/60) | K10: =IF(OR($C10="",$J$15=0),"",$J10/$J$15) | L10: =IF($C10="","",IF($J10=0,"NO DATA",IF($K10<0.6/MAX(1,COUNTA($C$9:$C$14)),"LOW",IF($K10>1.6/MAX(1,COUNTA($C$9:$C$14)),"HIGH","OK"))))
A11: 3 | B11: 90003 | C11: Mei Ling Chong | D11: 90003@siswa.unimas.my | E11: 011-2000 0003 | F11: meiling-c | G11: Planning Manager | I11: =IF($C11="","",SUMIFS(TASK!$K$8:$K$127,TASK!$F$8:$F$127,$C11)) | J11: =IF($C11="","",SUMIFS(LOGT!$K$7:$K$406,LOGT!$B$7:$B$406,$C11)/60) | K11: =IF(OR($C11="",$J$15=0),"",$J11/$J$15) | L11: =IF($C11="","",IF($J11=0,"NO DATA",IF($K11<0.6/MAX(1,COUNTA($C$9:$C$14)),"LOW",IF($K11>1.6/MAX(1,COUNTA($C$9:$C$14)),"HIGH","OK"))))
A12: 4 | B12: 90004 | C12: Harith Bin Ismail | D12: 90004@siswa.unimas.my | E12: 011-2000 0004 | F12: harith-i | G12: Product Owner | I12: =IF($C12="","",SUMIFS(TASK!$K$8:$K$127,TASK!$F$8:$F$127,$C12)) | J12: =IF($C12="","",SUMIFS(LOGT!$K$7:$K$406,LOGT!$B$7:$B$406,$C12)/60) | K12: =IF(OR($C12="",$J$15=0),"",$J12/$J$15) | L12: =IF($C12="","",IF($J12=0,"NO DATA",IF($K12<0.6/MAX(1,COUNTA($C$9:$C$14)),"LOW",IF($K12>1.6/MAX(1,COUNTA($C$9:$C$14)),"HIGH","OK"))))
A13: 5 | B13: 90005 | C13: Priya Nair | D13: 90005@siswa.unimas.my | E13: 011-2000 0005 | F13: priyanair | G13: Quality & Test Manager | I13: =IF($C13="","",SUMIFS(TASK!$K$8:$K$127,TASK!$F$8:$F$127,$C13)) | J13: =IF($C13="","",SUMIFS(LOGT!$K$7:$K$406,LOGT!$B$7:$B$406,$C13)/60) | K13: =IF(OR($C13="",$J$15=0),"",$J13/$J$15) | L13: =IF($C13="","",IF($J13=0,"NO DATA",IF($K13<0.6/MAX(1,COUNTA($C$9:$C$14)),"LOW",IF($K13>1.6/MAX(1,COUNTA($C$9:$C$14)),"HIGH","OK"))))
A14: 6 | I14: =IF($C14="","",SUMIFS(TASK!$K$8:$K$127,TASK!$F$8:$F$127,$C14)) | J14: =IF($C14="","",SUMIFS(LOGT!$K$7:$K$406,LOGT!$B$7:$B$406,$C14)/60) | K14: =IF(OR($C14="",$J$15=0),"",$J14/$J$15) | L14: =IF($C14="","",IF($J14=0,"NO DATA",IF($K14<0.6/MAX(1,COUNTA($C$9:$C$14)),"LOW",IF($K14>1.6/MAX(1,COUNTA($C$9:$C$14)),"HIGH","OK"))))
H15: TEAM TOTAL | I15: =SUM(I9:I14) | J15: =SUM(J9:J14) | K15: =IF($J$15=0,"",1)
A17: Team Charter (agree in Week 1, revisit at every launch)
B18: Team vision | C18: Give SeaFresh's counter staff a phone app that replaces the paper order book, so an order reaches the kitchen without being re-typed.
B19: Communication norms | C19: WhatsApp group for day-to-day, GitHub Issues for anything that needs a record. Replies within 12 hours on weekdays. Stand-up every Wednesday 4pm in the lab; client meeting every second Saturday.
B20: Definition of done | C20: Merged to develop, reviewed and approved by someone other than the author, tests written and passing, CI green, and the LOGAI row filled in if a generator touched it.
B21: Conflict resolution | C21: Raise it in the Wednesday meeting first. If the team cannot settle it, the Team Leader decides and records the reason in IRTL. Nobody re-opens a settled decision without new information.
B22: Quality standards | C22: 60% coverage on business logic, zero analyzer warnings on develop, code review within 24 hours, and no AI-generated code merged without a second pair of eyes.
B23: Commitment | C23: About 10 hours per person per week. Tell the team in advance if you will be away; an unexplained silent week gets raised at the next meeting.

Sheet ROLES
A1: Role Assignment Matrix
A2: Six roles, five of you. One member doubles up each cycle and the double rotates, so everyone leads something.
A4: Team | B4: =SETUP!$C$10
A6: Roles by Milestone
A7: Role | B7: What this role owns in TMA3084 | C7: M1 | D7: M2 | E7: M3 | F7: M4
A8: Team Leader | B8: Runs the launch and the weekly meeting, keeps the team to its plan, owns the relationship with the instructor and demonstrator, reports status. | C8: Aisyah Binti Rahman | D8: Aisyah Binti Rahman | E8: Daniel Wong Jun Hao | F8: Mei Ling Chong
A9: Product Owner | B9: Owns the client relationship and the backlog. Books and chairs client meetings, turns client needs into prioritised user stories, obtains sign-off. | C9: Harith Bin Ismail | D9: Harith Bin Ismail | E9: Priya Nair | F9: Aisyah Binti Rahman
A10: Development Manager | B10: Owns the Flutter codebase and the architecture. Allocates implementation work, enforces the branching model and the pull-request review rule. | C10: Daniel Wong Jun Hao | D10: Daniel Wong Jun Hao | E10: Harith Bin Ismail | F10: Priya Nair
A11: Planning Manager | B11: Owns TASK and SCHEDULE. Produces the plan, tracks earned value weekly, raises the alarm when the team drifts off plan. | C11: Mei Ling Chong | D11: Mei Ling Chong | E11: Aisyah Binti Rahman | F11: Harith Bin Ismail
A12: Quality & Test Manager | B12: Owns SUMQ, LOGD and LOGTEST - the review, inspection and test discipline. Tracks defect density, yield and coverage, chairs inspections, owns the AI-code review rule, and reports release readiness. | C12: Priya Nair | D12: Priya Nair | E12: Mei Ling Chong | F12: Daniel Wong Jun Hao
A13: Support Manager | B13: Owns the repository, CI/CD, environments, builds and configuration control. Maintains LOGGIT and the CCR log. | C13: Aisyah Binti Rahman | D13: Mei Ling Chong | E13: Daniel Wong Jun Hao | F13: Priya Nair
A15: Role Load Check - calculated from the matrix above, do not type here
A16: Member | B16: Reading | C16: M1 | D16: M2 | E16: M3 | F16: M4
A17: =IF('FORM-SI'!$C$9="","",'FORM-SI'!$C$9) | B17: =IF($A17="","",IF(MAX($C17:$F17)>2,"Holds more than two roles in a cycle",IF(MIN($C17:$F17)=0,"Has no role in at least one cycle",IF(MAX($C17:$F17)=2,"Doubles up in at least one cycle","One role in every cycle")))) | C17: =IF($A17="","",COUNTIF(C$8:C$13,$A17)) | D17: =IF($A17="","",COUNTIF(D$8:D$13,$A17)) | E17: =IF($A17="","",COUNTIF(E$8:E$13,$A17)) | F17: =IF($A17="","",COUNTIF(F$8:F$13,$A17))
A18: =IF('FORM-SI'!$C$10="","",'FORM-SI'!$C$10) | B18: =IF($A18="","",IF(MAX($C18:$F18)>2,"Holds more than two roles in a cycle",IF(MIN($C18:$F18)=0,"Has no role in at least one cycle",IF(MAX($C18:$F18)=2,"Doubles up in at least one cycle","One role in every cycle")))) | C18: =IF($A18="","",COUNTIF(C$8:C$13,$A18)) | D18: =IF($A18="","",COUNTIF(D$8:D$13,$A18)) | E18: =IF($A18="","",COUNTIF(E$8:E$13,$A18)) | F18: =IF($A18="","",COUNTIF(F$8:F$13,$A18))
A19: =IF('FORM-SI'!$C$11="","",'FORM-SI'!$C$11) | B19: =IF($A19="","",IF(MAX($C19:$F19)>2,"Holds more than two roles in a cycle",IF(MIN($C19:$F19)=0,"Has no role in at least one cycle",IF(MAX($C19:$F19)=2,"Doubles up in at least one cycle","One role in every cycle")))) | C19: =IF($A19="","",COUNTIF(C$8:C$13,$A19)) | D19: =IF($A19="","",COUNTIF(D$8:D$13,$A19)) | E19: =IF($A19="","",COUNTIF(E$8:E$13,$A19)) | F19: =IF($A19="","",COUNTIF(F$8:F$13,$A19))
A20: =IF('FORM-SI'!$C$12="","",'FORM-SI'!$C$12) | B20: =IF($A20="","",IF(MAX($C20:$F20)>2,"Holds more than two roles in a cycle",IF(MIN($C20:$F20)=0,"Has no role in at least one cycle",IF(MAX($C20:$F20)=2,"Doubles up in at least one cycle","One role in every cycle")))) | C20: =IF($A20="","",COUNTIF(C$8:C$13,$A20)) | D20: =IF($A20="","",COUNTIF(D$8:D$13,$A20)) | E20: =IF($A20="","",COUNTIF(E$8:E$13,$A20)) | F20: =IF($A20="","",COUNTIF(F$8:F$13,$A20))
A21: =IF('FORM-SI'!$C$13="","",'FORM-SI'!$C$13) | B21: =IF($A21="","",IF(MAX($C21:$F21)>2,"Holds more than two roles in a cycle",IF(MIN($C21:$F21)=0,"Has no role in at least one cycle",IF(MAX($C21:$F21)=2,"Doubles up in at least one cycle","One role in every cycle")))) | C21: =IF($A21="","",COUNTIF(C$8:C$13,$A21)) | D21: =IF($A21="","",COUNTIF(D$8:D$13,$A21)) | E21: =IF($A21="","",COUNTIF(E$8:E$13,$A21)) | F21: =IF($A21="","",COUNTIF(F$8:F$13,$A21))
A22: =IF('FORM-SI'!$C$14="","",'FORM-SI'!$C$14) | B22: =IF($A22="","",IF(MAX($C22:$F22)>2,"Holds more than two roles in a cycle",IF(MIN($C22:$F22)=0,"Has no role in at least one cycle",IF(MAX($C22:$F22)=2,"Doubles up in at least one cycle","One role in every cycle")))) | C22: =IF($A22="","",COUNTIF(C$8:C$13,$A22)) | D22: =IF($A22="","",COUNTIF(D$8:D$13,$A22)) | E22: =IF($A22="","",COUNTIF(E$8:E$13,$A22)) | F22: =IF($A22="","",COUNTIF(F$8:F$13,$A22))
A23: Members holding two roles | B23: =IF(SETUP!$C$16="","","Should be "&MAX(0,6-SETUP!$C$16)&" with a team of "&SETUP!$C$16) | C23: =COUNTIF(C$17:C$22,2) | D23: =COUNTIF(D$17:D$22,2) | E23: =COUNTIF(E$17:E$22,2) | F23: =COUNTIF(F$17:F$22,2)
A24: Roles filled | B24: ="All 6 roles must be held in every cycle" | C24: =COUNTA(C$8:C$13) | D24: =COUNTA(D$8:D$13) | E24: =COUNTA(E$8:E$13) | F24: =COUNTA(F$8:F$13)
A26: Role Rotation Rule
A27: There are six roles and five of you, so in every cycle exactly one member holds two roles and nobody holds more than two. The double role rotates - the same member does not carry it twice in a row - and every member holds a role in every cycle. No member may hold the same role for more than two consecutive milestones. Agree the rotation at the launch meeting and record it above; a change mid-cycle goes through the CCR log with the reason stated. If your team has four members, two of you will double up; the check above works that out from the team size.

Sheet GOALS
A1: Team & Role Goals
A2: A goal that cannot be measured is a wish. Every goal needs a number and an owner.
A4: Team | B4: =SETUP!$C$10
A6: Goals
A7: # | B7: Stakeholder | C7: Goal | D7: Measure | E7: Target | F7: Actual | G7: Owner | H7: Review By
A8: 1 | B8: Client | C8: SeaFresh accepts the app and uses it for real orders | D8: Client sign-off form signed | E8: Yes by M4 | F8: Yes | G8: Harith Bin Ismail | H8: 46389
A9: 2 | B9: Client | C9: Counter staff can place an order without training | D9: Time to first successful order, new user | E9: < 3 minutes | F9: 2 min 40 s | G9: Harith Bin Ismail | H9: 46374
A10: 3 | B10: Team | C10: Finish inside the planned effort | D10: Actual hours / planned hours | E10: 0.9 - 1.1 | F10: 0.75 | G10: Mei Ling Chong | H10: 46374
A11: 4 | B11: Team | C11: Work is shared evenly across the five of us | D11: Each member's share of logged hours | E11: within +/-40% of even | F11: not met - see DASHBOARD | G11: Aisyah Binti Rahman | H11: 46344
A12: 5 | B12: Quality | C12: Catch defects before they reach test | D12: % of defects removed before unit test | E12: >= 70% | F12: 73% | G12: Priya Nair | H12: 46374
A13: 6 | B13: Quality | C13: Nothing critical reaches the client | D13: Critical defects found in acceptance test | E13: 0 | F13: 0 | G13: Priya Nair | H13: 46389
A14: 7 | B14: Process | C14: Every AI-generated change is reviewed by someone else | D14: LOGAI rows approved / total rows | E14: 100% | F14: 100% | G14: Priya Nair | H14: 46374
A15: 8 | B15: Process | C15: develop stays releasable | D15: GitHub Actions pass rate on develop | E15: >= 95% | F15: 96% | G15: Aisyah Binti Rahman | H15: 46374
A16: 9
A17: 10
A18: 11
A19: 12
A20: 13
A21: 14
A23: Suggested starting goals (replace with your own)
B24: Stakeholder | C24: Goal | D24: Measure | E24: Target
B25: Client | C25: Client accepts the delivered app | D25: Client sign-off obtained | E25: Yes by M4
B26: Team | C26: Finish within the planned effort | D26: Actual hours / planned hours | E26: 0.9 - 1.1
B27: Quality | C27: Catch defects before test | D27: % defects removed before unit test | E27: >= 70%
B28: Quality | C28: Keep the released build clean | D28: Defects found in acceptance test | E28: 0 critical
B29: Process | C29: Every AI-generated change is reviewed | D29: LOGAI entries approved / total | E29: 100%
B30: Process | C30: Keep the main branch releasable | D30: GitHub Actions pass rate on develop | E30: >= 95%
B31: Individual | C31: Contribution is evenly shared | D31: Each member's share of team hours | E31: within +/-40% of even

Sheet STRAT
A1: Development Strategy
A2: What gets built in each cycle, what is reused, and what could go wrong.
A4: Cycle Strategy
A5: # | B5: Milestone | C5: Scope delivered this cycle | D5: Build / buy / reuse decision | E5: Main technical risk | F5: Mitigation | G5: Owner
A6: 1 | B6: M1 | C6: Requirements and a clickable prototype of the order screen. No real data yet. | D6: Build the app; reuse Firebase Auth rather than writing sign-in. | E6: The client has never used a tracking app and may not recognise what we design. | F6: Show paper mock-ups at the second client meeting before writing any code. | G6: Harith Bin Ismail
A7: 2 | B7: M2 | C7: Order entry, catalogue browsing and the local database. Prototype against seeded data. | D7: Build order entry; reuse an off-the-shelf PDF package for invoices. | E7: Supplier price list changes weekly and we had assumed it was static. | F7: Model prices as dated records from the start; agreed with client at meeting 3. | G7: Daniel Wong Jun Hao
A8: 3 | B8: M3 | C8: Live catalogue sync, invoice generation, full test suite and CI. | D8: Build sync; reuse Firestore offline persistence rather than our own cache. | E8: The shop's connection drops; orders could be lost mid-entry. | F8: Offline-first write queue plus an integration test that simulates loss of connection. | G8: Harith Bin Ismail
A9: 4 | B9: M4 | C9: Release build, user manual, demo video and handover to the client. | D9: No new build; packaging and documentation only. | E9: Counter staff may not adopt it after handover. | F9: Train two staff in person at handover and leave a one-page card at the till. | G9: Aisyah Binti Rahman
A11: Technology Stack Decisions
A12: # | B12: Area | C12: Decision | D12: Why | E12: Alternative considered | F12: Decided | G12: Owner
A13: 1 | B13: Mobile framework | C13: Flutter 3.x / Dart 3 | D13: One codebase for Android and iOS; the course requires it. | E13: Native Kotlin - rejected, no iOS and no time for two codebases. | F13: 46303 | G13: Daniel Wong Jun Hao
A14: 2 | B14: State management | C14: Riverpod | D14: Compile-safe, testable, and easier to reason about than InheritedWidget. | E14: Provider - simpler but we wanted the compile-time safety. | F14: 46303 | G14: Daniel Wong Jun Hao
A15: 3 | B15: Backend / data | C15: Firebase Firestore + offline persistence | D15: The shop's connection is unreliable; offline-first is the whole point. | E15: Supabase - good, but we already had Firebase Auth. | F15: 46310 | G15: Harith Bin Ismail
A16: 4 | B16: AI capability & API | C16: Gemini API for the order-note parser | D16: Lets staff type 'two boxes tiger prawn' instead of browsing the catalogue. | E16: Rule-based parser - brittle against the way staff actually write. | F16: 46317 | G16: Priya Nair
A17: 5 | B17: Authentication | C17: Firebase Auth (email + phone) | D17: Staff share a counter device; phone sign-in is the simplest for them. | E17: Custom JWT - more work, no benefit here. | F17: 46310 | G17: Aisyah Binti Rahman
A18: 6 | B18: Testing framework | C18: flutter_test + mockito + integration_test | D18: Standard toolchain, works in CI without extra setup. | E18: None seriously considered. | F18: 46324 | G18: Mei Ling Chong
A19: 7 | B19: CI/CD | C19: GitHub Actions | D19: Free for the repo, runs analyze + test + coverage on every PR. | E19: Codemagic - nicer mobile builds, but needed a paid tier for our frequency. | F19: 46324 | G19: Aisyah Binti Rahman
A20: 8 | B20: Release channel | C20: Internal APK via GitHub Releases | D20: The client has two Android devices; no store listing needed for the pilot. | E20: Play Store internal testing - rejected, review delay would hit M4. | F20: 46366 | G20: Aisyah Binti Rahman

Sheet TASK
A1: Form TASK - Task Plan & Earned Value
A2: Break the cycle into tasks of roughly 2-10 hours. A task is done or it is not - no part marks.
A4: Team | B4: =SETUP!$C$10 | E4: Tasks | F4: =COUNTA(TASK!$A$8:$A$127) | G4: Plan hrs | H4: =SUM(TASK!$K$8:$K$127) | I4: Actual hrs | J4: =SUM(TASK!$M$8:$M$127) | L4: Complete | N4: =COUNTIF(TASK!$O$8:$O$127,"Complete") | O4: Earned value | Q4: =SUM(TASK!$Q$8:$Q$127)
A7: Task ID | B7: M/stone | C7: Phase | D7: Component | E7: Task | F7: Owner | G7: Est. size | H7: Size measure | I7: Rate /hr | J7: Est. hrs | K7: Plan hrs | L7: Plan wk | M7: Actual hrs | N7: Act. wk | O7: Status | P7: Plan value | Q7: Earned value | R7: Cum PV | S7: Cum EV
A8: T01 | B8: M1 | C8: MGMT | D8: SYSTEM | E8: Team admin, lab attendance, instructor check-ins | F8: Aisyah Binti Rahman | J8: =IF(OR(N($G8)=0,N($I8)=0),"",$G8/$I8) | K8: 7 | L8: 3 | M8: =IF($A8="","",SUMIFS(LOGT!$K$7:$K$406,LOGT!$F$7:$F$406,$A8)/60) | N8: =IFERROR(IF(N($M8)=0,"",3+INT((SUMPRODUCT(MAX((LOGT!$F$7:$F$406=$A8)*LOGT!$A$7:$A$406))-DATE(2026,10,5))/7)),"") | O8: Complete | P8: =IF(OR($A8="",SUM(TASK!$K$8:$K$127)=0),"",$K8/SUM(TASK!$K$8:$K$127)) | Q8: =IF($A8="","",IF($O8="Complete",$P8,0)) | R8: =IF($A8="","",SUM($P$8:$P8)) | S8: =IF($A8="","",SUM($Q$8:$Q8))
A9: T02 | B9: M1 | C9: STRAT | D9: SYSTEM | E9: Launch meeting, cycle strategy and stack decisions | F9: Aisyah Binti Rahman | J9: =IF(OR(N($G9)=0,N($I9)=0),"",$G9/$I9) | K9: 11 | L9: 3 | M9: =IF($A9="","",SUMIFS(LOGT!$K$7:$K$406,LOGT!$F$7:$F$406,$A9)/60) | N9: =IFERROR(IF(N($M9)=0,"",3+INT((SUMPRODUCT(MAX((LOGT!$F$7:$F$406=$A9)*LOGT!$A$7:$A$406))-DATE(2026,10,5))/7)),"") | O9: Complete | P9: =IF(OR($A9="",SUM(TASK!$K$8:$K$127)=0),"",$K9/SUM(TASK!$K$8:$K$127)) | Q9: =IF($A9="","",IF($O9="Complete",$P9,0)) | R9: =IF($A9="","",SUM($P$8:$P9)) | S9: =IF($A9="","",SUM($Q$8:$Q9))
A10: T03 | B10: M1 | C10: PLAN | D10: SYSTEM | E10: Task and schedule plan for the cycle | F10: Mei Ling Chong | J10: =IF(OR(N($G10)=0,N($I10)=0),"",$G10/$I10) | K10: 10.5 | L10: 3 | M10: =IF($A10="","",SUMIFS(LOGT!$K$7:$K$406,LOGT!$F$7:$F$406,$A10)/60) | N10: =IFERROR(IF(N($M10)=0,"",3+INT((SUMPRODUCT(MAX((LOGT!$F$7:$F$406=$A10)*LOGT!$A$7:$A$406))-DATE(2026,10,5))/7)),"") | O10: Complete | P10: =IF(OR($A10="",SUM(TASK!$K$8:$K$127)=0),"",$K10/SUM(TASK!$K$8:$K$127)) | Q10: =IF($A10="","",IF($O10="Complete",$P10,0)) | R10: =IF($A10="","",SUM($P$8:$P10)) | S10: =IF($A10="","",SUM($Q$8:$Q10))
A11: T04 | B11: M1 | C11: REQ | D11: SYSTEM | E11: Elicit requirements from SeaFresh and write the SRS | F11: Harith Bin Ismail | J11: =IF(OR(N($G11)=0,N($I11)=0),"",$G11/$I11) | K11: 7 | L11: 4 | M11: =IF($A11="","",SUMIFS(LOGT!$K$7:$K$406,LOGT!$F$7:$F$406,$A11)/60) | N11: =IFERROR(IF(N($M11)=0,"",3+INT((SUMPRODUCT(MAX((LOGT!$F$7:$F$406=$A11)*LOGT!$A$7:$A$406))-DATE(2026,10,5))/7)),"") | O11: Complete | P11: =IF(OR($A11="",SUM(TASK!$K$8:$K$127)=0),"",$K11/SUM(TASK!$K$8:$K$127)) | Q11: =IF($A11="","",IF($O11="Complete",$P11,0)) | R11: =IF($A11="","",SUM($P$8:$P11)) | S11: =IF($A11="","",SUM($Q$8:$Q11))
A12: T05 | B12: M1 | C12: STP | D12: SYSTEM | E12: System test plan | F12: Mei Ling Chong | J12: =IF(OR(N($G12)=0,N($I12)=0),"",$G12/$I12) | K12: 6 | L12: 4 | M12: =IF($A12="","",SUMIFS(LOGT!$K$7:$K$406,LOGT!$F$7:$F$406,$A12)/60) | N12: =IFERROR(IF(N($M12)=0,"",3+INT((SUMPRODUCT(MAX((LOGT!$F$7:$F$406=$A12)*LOGT!$A$7:$A$406))-DATE(2026,10,5))/7)),"") | O12: Complete | P12: =IF(OR($A12="",SUM(TASK!$K$8:$K$127)=0),"",$K12/SUM(TASK!$K$8:$K$127)) | Q12: =IF($A12="","",IF($O12="Complete",$P12,0)) | R12: =IF($A12="","",SUM($P$8:$P12)) | S12: =IF($A12="","",SUM($Q$8:$Q12))
A13: T06 | B13: M1 | C13: REQINSP | D13: SYSTEM | E13: Team inspection of the SRS | F13: Harith Bin Ismail | J13: =IF(OR(N($G13)=0,N($I13)=0),"",$G13/$I13) | K13: 11 | L13: 4 | M13: =IF($A13="","",SUMIFS(LOGT!$K$7:$K$406,LOGT!$F$7:$F$406,$A13)/60) | N13: =IFERROR(IF(N($M13)=0,"",3+INT((SUMPRODUCT(MAX((LOGT!$F$7:$F$406=$A13)*LOGT!$A$7:$A$406))-DATE(2026,10,5))/7)),"") | O13: Complete | P13: =IF(OR($A13="",SUM(TASK!$K$8:$K$127)=0),"",$K13/SUM(TASK!$K$8:$K$127)) | Q13: =IF($A13="","",IF($O13="Complete",$P13,0)) | R13: =IF($A13="","",SUM($P$8:$P13)) | S13: =IF($A13="","",SUM($Q$8:$Q13))
A14: T07 | B14: M1 | C14: HLD | D14: SYSTEM | E14: Architecture and SDD | F14: Daniel Wong Jun Hao | J14: =IF(OR(N($G14)=0,N($I14)=0),"",$G14/$I14) | K14: 9.5 | L14: 4 | M14: =IF($A14="","",SUMIFS(LOGT!$K$7:$K$406,LOGT!$F$7:$F$406,$A14)/60) | N14: =IFERROR(IF(N($M14)=0,"",3+INT((SUMPRODUCT(MAX((LOGT!$F$7:$F$406=$A14)*LOGT!$A$7:$A$406))-DATE(2026,10,5))/7)),"") | O14: Complete | P14: =IF(OR($A14="",SUM(TASK!$K$8:$K$127)=0),"",$K14/SUM(TASK!$K$8:$K$127)) | Q14: =IF($A14="","",IF($O14="Complete",$P14,0)) | R14: =IF($A14="","",SUM($P$8:$P14)) | S14: =IF($A14="","",SUM($Q$8:$Q14))
A15: T08 | B15: M1 | C15: ITP | D15: SYSTEM | E15: Integration test plan | F15: Mei Ling Chong | J15: =IF(OR(N($G15)=0,N($I15)=0),"",$G15/$I15) | K15: 6 | L15: 4 | M15: =IF($A15="","",SUMIFS(LOGT!$K$7:$K$406,LOGT!$F$7:$F$406,$A15)/60) | N15: =IFERROR(IF(N($M15)=0,"",3+INT((SUMPRODUCT(MAX((LOGT!$F$7:$F$406=$A15)*LOGT!$A$7:$A$406))-DATE(2026,10,5))/7)),"") | O15: Complete | P15: =IF(OR($A15="",SUM(TASK!$K$8:$K$127)=0),"",$K15/SUM(TASK!$K$8:$K$127)) | Q15: =IF($A15="","",IF($O15="Complete",$P15,0)) | R15: =IF($A15="","",SUM($P$8:$P15)) | S15: =IF($A15="","",SUM($Q$8:$Q15))
A16: T09 | B16: M1 | C16: HLDINSP | D16: SYSTEM | E16: Team inspection of the SDD | F16: Daniel Wong Jun Hao | J16: =IF(OR(N($G16)=0,N($I16)=0),"",$G16/$I16) | K16: 6 | L16: 4 | M16: =IF($A16="","",SUMIFS(LOGT!$K$7:$K$406,LOGT!$F$7:$F$406,$A16)/60) | N16: =IFERROR(IF(N($M16)=0,"",3+INT((SUMPRODUCT(MAX((LOGT!$F$7:$F$406=$A16)*LOGT!$A$7:$A$406))-DATE(2026,10,5))/7)),"") | O16: Complete | P16: =IF(OR($A16="",SUM(TASK!$K$8:$K$127)=0),"",$K16/SUM(TASK!$K$8:$K$127)) | Q16: =IF($A16="","",IF($O16="Complete",$P16,0)) | R16: =IF($A16="","",SUM($P$8:$P16)) | S16: =IF($A16="","",SUM($Q$8:$Q16))
A17: T10 | B17: M1 | C17: DLD | D17: UI / screens | E17: Detailed design of screens, widgets and models | F17: Priya Nair | J17: =IF(OR(N($G17)=0,N($I17)=0),"",$G17/$I17) | K17: 10.5 | L17: 5 | M17: =IF($A17="","",SUMIFS(LOGT!$K$7:$K$406,LOGT!$F$7:$F$406,$A17)/60) | N17: =IFERROR(IF(N($M17)=0,"",3+INT((SUMPRODUCT(MAX((LOGT!$F$7:$F$406=$A17)*LOGT!$A$7:$A$406))-DATE(2026,10,5))/7)),"") | O17: Complete | P17: =IF(OR($A17="",SUM(TASK!$K$8:$K$127)=0),"",$K17/SUM(TASK!$K$8:$K$127)) | Q17: =IF($A17="","",IF($O17="Complete",$P17,0)) | R17: =IF($A17="","",SUM($P$8:$P17)) | S17: =IF($A17="","",SUM($Q$8:$Q17))
A18: T11 | B18: M1 | C18: DLDR | D18: UI / screens | E18: Personal review of the detailed design | F18: Priya Nair | J18: =IF(OR(N($G18)=0,N($I18)=0),"",$G18/$I18) | K18: 12.5 | L18: 5 | M18: =IF($A18="","",SUMIFS(LOGT!$K$7:$K$406,LOGT!$F$7:$F$406,$A18)/60) | N18: =IFERROR(IF(N($M18)=0,"",3+INT((SUMPRODUCT(MAX((LOGT!$F$7:$F$406=$A18)*LOGT!$A$7:$A$406))-DATE(2026,10,5))/7)),"") | O18: Complete | P18: =IF(OR($A18="",SUM(TASK!$K$8:$K$127)=0),"",$K18/SUM(TASK!$K$8:$K$127)) | Q18: =IF($A18="","",IF($O18="Complete",$P18,0)) | R18: =IF($A18="","",SUM($P$8:$P18)) | S18: =IF($A18="","",SUM($Q$8:$Q18))
A19: T12 | B19: M1 | C19: TD | D19: UI / screens | E19: Write the test cases for this component | F19: Priya Nair | J19: =IF(OR(N($G19)=0,N($I19)=0),"",$G19/$I19) | K19: 17 | L19: 5 | M19: =IF($A19="","",SUMIFS(LOGT!$K$7:$K$406,LOGT!$F$7:$F$406,$A19)/60) | N19: =IFERROR(IF(N($M19)=0,"",3+INT((SUMPRODUCT(MAX((LOGT!$F$7:$F$406=$A19)*LOGT!$A$7:$A$406))-DATE(2026,10,5))/7)),"") | O19: Complete | P19: =IF(OR($A19="",SUM(TASK!$K$8:$K$127)=0),"",$K19/SUM(TASK!$K$8:$K$127)) | Q19: =IF($A19="","",IF($O19="Complete",$P19,0)) | R19: =IF($A19="","",SUM($P$8:$P19)) | S19: =IF($A19="","",SUM($Q$8:$Q19))
... A53: T46 | B53: M3 | C53: AIGEN | D53: Local store & sync | E53: Generate the offline write-queue scaffolding | F53: Mei Ling Chong | J53: =IF(OR(N($G53)=0,N($I53)=0),"",$G53/$I53) | K53: 8 | L53: 10 | M53: =IF($A53="","",SUMIFS(LOGT!$K$7:$K$406,LOGT!$F$7:$F$406,$A53)/60) | N53: =IFERROR(IF(N($M53)=0,"",3+INT((SUMPRODUCT(MAX((LOGT!$F$7:$F$406=$A53)*LOGT!$A$7:$A$406))-DATE(2026,10,5))/7)),"") | O53: Complete | P53: =IF(OR($A53="",SUM(TASK!$K$8:$K$127)=0),"",$K53/SUM(TASK!$K$8:$K$127)) | Q53: =IF($A53="","",IF($O53="Complete",$P53,0)) | R53: =IF($A53="","",SUM($P$8:$P53)) | S53: =IF($A53="","",SUM($Q$8:$Q53))
J54: =IF(OR(N($G54)=0,N($I54)=0),"",$G54/$I54) | M54: =IF($A54="","",SUMIFS(LOGT!$K$7:$K$406,LOGT!$F$7:$F$406,$A54)/60) | N54: =IFERROR(IF(N($M54)=0,"",3+INT((SUMPRODUCT(MAX((LOGT!$F$7:$F$406=$A54)*LOGT!$A$7:$A$406))-DATE(2026,10,5))/7)),"") | P54: =IF(OR($A54="",SUM(TASK!$K$8:$K$127)=0),"",$K54/SUM(TASK!$K$8:$K$127)) | Q54: =IF($A54="","",IF($O54="Complete",$P54,0)) | R54: =IF($A54="","",SUM($P$8:$P54)) | S54: =IF($A54="","",SUM($Q$8:$Q54))
J55: =IF(OR(N($G55)=0,N($I55)=0),"",$G55/$I55) | M55: =IF($A55="","",SUMIFS(LOGT!$K$7:$K$406,LOGT!$F$7:$F$406,$A55)/60) | N55: =IFERROR(IF(N($M55)=0,"",3+INT((SUMPRODUCT(MAX((LOGT!$F$7:$F$406=$A55)*LOGT!$A$7:$A$406))-DATE(2026,10,5))/7)),"") | P55: =IF(OR($A55="",SUM(TASK!$K$8:$K$127)=0),"",$K55/SUM(TASK!$K$8:$K$127)) | Q55: =IF($A55="","",IF($O55="Complete",$P55,0)) | R55: =IF($A55="","",SUM($P$8:$P55)) | S55: =IF($A55="","",SUM($Q$8:$Q55))
J56: =IF(OR(N($G56)=0,N($I56)=0),"",$G56/$I56) | M56: =IF($A56="","",SUMIFS(LOGT!$K$7:$K$406,LOGT!$F$7:$F$406,$A56)/60) | N56: =IFERROR(IF(N($M56)=0,"",3+INT((SUMPRODUCT(MAX((LOGT!$F$7:$F$406=$A56)*LOGT!$A$7:$A$406))-DATE(2026,10,5))/7)),"") | P56: =IF(OR($A56="",SUM(TASK!$K$8:$K$127)=0),"",$K56/SUM(TASK!$K$8:$K$127)) | Q56: =IF($A56="","",IF($O56="Complete",$P56,0)) | R56: =IF($A56="","",SUM($P$8:$P56)) | S56: =IF($A56="","",SUM($Q$8:$Q56))
J57: =IF(OR(N($G57)=0,N($I57)=0),"",$G57/$I57) | M57: =IF($A57="","",SUMIFS(LOGT!$K$7:$K$406,LOGT!$F$7:$F$406,$A57)/60) | N57: =IFERROR(IF(N($M57)=0,"",3+INT((SUMPRODUCT(MAX((LOGT!$F$7:$F$406=$A57)*LOGT!$A$7:$A$406))-DATE(2026,10,5))/7)),"") | P57: =IF(OR($A57="",SUM(TASK!$K$8:$K$127)=0),"",$K57/SUM(TASK!$K$8:$K$127)) | Q57: =IF($A57="","",IF($O57="Complete",$P57,0)) | R57: =IF($A57="","",SUM($P$8:$P57)) | S57: =IF($A57="","",SUM($Q$8:$Q57))
J58: =IF(OR(N($G58)=0,N($I58)=0),"",$G58/$I58) | M58: =IF($A58="","",SUMIFS(LOGT!$K$7:$K$406,LOGT!$F$7:$F$406,$A58)/60) | N58: =IFERROR(IF(N($M58)=0,"",3+INT((SUMPRODUCT(MAX((LOGT!$F$7:$F$406=$A58)*LOGT!$A$7:$A$406))-DATE(2026,10,5))/7)),"") | P58: =IF(OR($A58="",SUM(TASK!$K$8:$K$127)=0),"",$K58/SUM(TASK!$K$8:$K$127)) | Q58: =IF($A58="","",IF($O58="Complete",$P58,0)) | R58: =IF($A58="","",SUM($P$8:$P58)) | S58: =IF($A58="","",SUM($Q$8:$Q58))
J59: =IF(OR(N($G59)=0,N($I59)=0),"",$G59/$I59) | M59: =IF($A59="","",SUMIFS(LOGT!$K$7:$K$406,LOGT!$F$7:$F$406,$A59)/60) | N59: =IFERROR(IF(N($M59)=0,"",3+INT((SUMPRODUCT(MAX((LOGT!$F$7:$F$406=$A59)*LOGT!$A$7:$A$406))-DATE(2026,10,5))/7)),"") | P59: =IF(OR($A59="",SUM(TASK!$K$8:$K$127)=0),"",$K59/SUM(TASK!$K$8:$K$127)) | Q59: =IF($A59="","",IF($O59="Complete",$P59,0)) | R59: =IF($A59="","",SUM($P$8:$P59)) | S59: =IF($A59="","",SUM($Q$8:$Q59))
J60: =IF(OR(N($G60)=0,N($I60)=0),"",$G60/$I60) | M60: =IF($A60="","",SUMIFS(LOGT!$K$7:$K$406,LOGT!$F$7:$F$406,$A60)/60) | N60: =IFERROR(IF(N($M60)=0,"",3+INT((SUMPRODUCT(MAX((LOGT!$F$7:$F$406=$A60)*LOGT!$A$7:$A$406))-DATE(2026,10,5))/7)),"") | P60: =IF(OR($A60="",SUM(TASK!$K$8:$K$127)=0),"",$K60/SUM(TASK!$K$8:$K$127)) | Q60: =IF($A60="","",IF($O60="Complete",$P60,0)) | R60: =IF($A60="","",SUM($P$8:$P60)) | S60: =IF($A60="","",SUM($Q$8:$Q60))
J61: =IF(OR(N($G61)=0,N($I61)=0),"",$G61/$I61) | M61: =IF($A61="","",SUMIFS(LOGT!$K$7:$K$406,LOGT!$F$7:$F$406,$A61)/60) | N61: =IFERROR(IF(N($M61)=0,"",3+INT((SUMPRODUCT(MAX((LOGT!$F$7:$F$406=$A61)*LOGT!$A$7:$A$406))-DATE(2026,10,5))/7)),"") | P61: =IF(OR($A61="",SUM(TASK!$K$8:$K$127)=0),"",$K61/SUM(TASK!$K$8:$K$127)) | Q61: =IF($A61="","",IF($O61="Complete",$P61,0)) | R61: =IF($A61="","",SUM($P$8:$P61)) | S61: =IF($A61="","",SUM($Q$8:$Q61))
J62: =IF(OR(N($G62)=0,N($I62)=0),"",$G62/$I62) | M62: =IF($A62="","",SUMIFS(LOGT!$K$7:$K$406,LOGT!$F$7:$F$406,$A62)/60) | N62: =IFERROR(IF(N($M62)=0,"",3+INT((SUMPRODUCT(MAX((LOGT!$F$7:$F$406=$A62)*LOGT!$A$7:$A$406))-DATE(2026,10,5))/7)),"") | P62: =IF(OR($A62="",SUM(TASK!$K$8:$K$127)=0),"",$K62/SUM(TASK!$K$8:$K$127)) | Q62: =IF($A62="","",IF($O62="Complete",$P62,0)) | R62: =IF($A62="","",SUM($P$8:$P62)) | S62: =IF($A62="","",SUM($Q$8:$Q62))
J63: =IF(OR(N($G63)=0,N($I63)=0),"",$G63/$I63) | M63: =IF($A63="","",SUMIFS(LOGT!$K$7:$K$406,LOGT!$F$7:$F$406,$A63)/60) | N63: =IFERROR(IF(N($M63)=0,"",3+INT((SUMPRODUCT(MAX((LOGT!$F$7:$F$406=$A63)*LOGT!$A$7:$A$406))-DATE(2026,10,5))/7)),"") | P63: =IF(OR($A63="",SUM(TASK!$K$8:$K$127)=0),"",$K63/SUM(TASK!$K$8:$K$127)) | Q63: =IF($A63="","",IF($O63="Complete",$P63,0)) | R63: =IF($A63="","",SUM($P$8:$P63)) | S63: =IF($A63="","",SUM($Q$8:$Q63))
J64: =IF(OR(N($G64)=0,N($I64)=0),"",$G64/$I64) | M64: =IF($A64="","",SUMIFS(LOGT!$K$7:$K$406,LOGT!$F$7:$F$406,$A64)/60) | N64: =IFERROR(IF(N($M64)=0,"",3+INT((SUMPRODUCT(MAX((LOGT!$F$7:$F$406=$A64)*LOGT!$A$7:$A$406))-DATE(2026,10,5))/7)),"") | P64: =IF(OR($A64="",SUM(TASK!$K$8:$K$127)=0),"",$K64/SUM(TASK!$K$8:$K$127)) | Q64: =IF($A64="","",IF($O64="Complete",$P64,0)) | R64: =IF($A64="","",SUM($P$8:$P64)) | S64: =IF($A64="","",SUM($Q$8:$Q64))
J65: =IF(OR(N($G65)=0,N($I65)=0),"",$G65/$I65) | M65: =IF($A65="","",SUMIFS(LOGT!$K$7:$K$406,LOGT!$F$7:$F$406,$A65)/60) | N65: =IFERROR(IF(N($M65)=0,"",3+INT((SUMPRODUCT(MAX((LOGT!$F$7:$F$406=$A65)*LOGT!$A$7:$A$406))-DATE(2026,10,5))/7)),"") | P65: =IF(OR($A65="",SUM(TASK!$K$8:$K$127)=0),"",$K65/SUM(TASK!$K$8:$K$127)) | Q65: =IF($A65="","",IF($O65="Complete",$P65,0)) | R65: =IF($A65="","",SUM($P$8:$P65)) | S65: =IF($A65="","",SUM($Q$8:$Q65))
... J127: =IF(OR(N($G127)=0,N($I127)=0),"",$G127/$I127) | M127: =IF($A127="","",SUMIFS(LOGT!$K$7:$K$406,LOGT!$F$7:$F$406,$A127)/60) | N127: =IFERROR(IF(N($M127)=0,"",3+INT((SUMPRODUCT(MAX((LOGT!$F$7:$F$406=$A127)*LOGT!$A$7:$A$406))-DATE(2026,10,5))/7)),"") | P127: =IF(OR($A127="",SUM(TASK!$K$8:$K$127)=0),"",$K127/SUM(TASK!$K$8:$K$127)) | Q127: =IF($A127="","",IF($O127="Complete",$P127,0)) | R127: =IF($A127="","",SUM($P$8:$P127)) | S127: =IF($A127="","",SUM($Q$8:$Q127))

Sheet SCHEDULE
A1: Form SCHEDULE - Weekly Schedule & Earned Value
A2: Planned hours are what the team commits to. Earned value is what it actually delivered.
A4: Team | B4: =SETUP!$C$10 | E4: Task plan hrs | F4: =SUM(TASK!$K$8:$K$127) | G4: Schedule plan hrs | H4: =SUM(C8:C20) | I4: Difference | J4: =H4-F4
A7: Week | B7: Week starting | C7: Plan hrs | D7: Cum plan | E7: Actual hrs | F7: Cum actual | G7: Plan value | H7: Cum PV | I7: Earned value | J7: Cum EV | K7: EV vs PV | L7: Comment
A8: 3 | B8: 46300 | C8: 28.5 | D8: =SUM($C$8:$C8) | E8: =SUMIFS(LOGT!$K$7:$K$406,LOGT!$D$7:$D$406,$A8)/60 | F8: =SUM($E$8:$E8) | G8: =SUMIFS(TASK!$P$8:$P$127,TASK!$L$8:$L$127,$A8) | H8: =SUM($G$8:$G8) | I8: =SUMIFS(TASK!$Q$8:$Q$127,TASK!$N$8:$N$127,$A8) | J8: =SUM($I$8:$I8) | K8: =$J8-$H8 | L8: Launch week - plan built here
A9: 4 | B9: 46307 | C9: 45.5 | D9: =SUM($C$8:$C9) | E9: =SUMIFS(LOGT!$K$7:$K$406,LOGT!$D$7:$D$406,$A9)/60 | F9: =SUM($E$8:$E9) | G9: =SUMIFS(TASK!$P$8:$P$127,TASK!$L$8:$L$127,$A9) | H9: =SUM($G$8:$G9) | I9: =SUMIFS(TASK!$Q$8:$Q$127,TASK!$N$8:$N$127,$A9) | J9: =SUM($I$8:$I9) | K9: =$J9-$H9
A10: 5 | B10: 46314 | C10: 51.5 | D10: =SUM($C$8:$C10) | E10: =SUMIFS(LOGT!$K$7:$K$406,LOGT!$D$7:$D$406,$A10)/60 | F10: =SUM($E$8:$E10) | G10: =SUMIFS(TASK!$P$8:$P$127,TASK!$L$8:$L$127,$A10) | H10: =SUM($G$8:$G10) | I10: =SUMIFS(TASK!$Q$8:$Q$127,TASK!$N$8:$N$127,$A10) | J10: =SUM($I$8:$I10) | K10: =$J10-$H10 | L10: M1 submitted
A11: 6 | B11: 46321 | C11: 60 | D11: =SUM($C$8:$C11) | E11: =SUMIFS(LOGT!$K$7:$K$406,LOGT!$D$7:$D$406,$A11)/60 | F11: =SUM($E$8:$E11) | G11: =SUMIFS(TASK!$P$8:$P$127,TASK!$L$8:$L$127,$A11) | H11: =SUM($G$8:$G11) | I11: =SUMIFS(TASK!$Q$8:$Q$127,TASK!$N$8:$N$127,$A11) | J11: =SUM($I$8:$I11) | K11: =$J11-$H11
A12: 7 | B12: 46328 | C12: 91 | D12: =SUM($C$8:$C12) | E12: =SUMIFS(LOGT!$K$7:$K$406,LOGT!$D$7:$D$406,$A12)/60 | F12: =SUM($E$8:$E12) | G12: =SUMIFS(TASK!$P$8:$P$127,TASK!$L$8:$L$127,$A12) | H12: =SUM($G$8:$G12) | I12: =SUMIFS(TASK!$Q$8:$Q$127,TASK!$N$8:$N$127,$A12) | J12: =SUM($I$8:$I12) | K12: =$J12-$H12
A13: 8 | B13: 46335 | C13: 0 | D13: =SUM($C$8:$C13) | E13: =SUMIFS(LOGT!$K$7:$K$406,LOGT!$D$7:$D$406,$A13)/60 | F13: =SUM($E$8:$E13) | G13: =SUMIFS(TASK!$P$8:$P$127,TASK!$L$8:$L$127,$A13) | H13: =SUM($G$8:$G13) | I13: =SUMIFS(TASK!$Q$8:$Q$127,TASK!$N$8:$N$127,$A13) | J13: =SUM($I$8:$I13) | K13: =$J13-$H13 | L13: Mid-semester break, no work planned
A14: 9 | B14: 46342 | C14: 93 | D14: =SUM($C$8:$C14) | E14: =SUMIFS(LOGT!$K$7:$K$406,LOGT!$D$7:$D$406,$A14)/60 | F14: =SUM($E$8:$E14) | G14: =SUMIFS(TASK!$P$8:$P$127,TASK!$L$8:$L$127,$A14) | H14: =SUM($G$8:$G14) | I14: =SUMIFS(TASK!$Q$8:$Q$127,TASK!$N$8:$N$127,$A14) | J14: =SUM($I$8:$I14) | K14: =$J14-$H14 | L14: M2 submitted
A15: 10 | B15: 46349 | C15: 76.5 | D15: =SUM($C$8:$C15) | E15: =SUMIFS(LOGT!$K$7:$K$406,LOGT!$D$7:$D$406,$A15)/60 | F15: =SUM($E$8:$E15) | G15: =SUMIFS(TASK!$P$8:$P$127,TASK!$L$8:$L$127,$A15) | H15: =SUM($G$8:$G15) | I15: =SUMIFS(TASK!$Q$8:$Q$127,TASK!$N$8:$N$127,$A15) | J15: =SUM($I$8:$I15) | K15: =$J15-$H15
A16: 11 | B16: 46356 | C16: 38 | D16: =SUM($C$8:$C16) | E16: =SUMIFS(LOGT!$K$7:$K$406,LOGT!$D$7:$D$406,$A16)/60 | F16: =SUM($E$8:$E16) | G16: =SUMIFS(TASK!$P$8:$P$127,TASK!$L$8:$L$127,$A16) | H16: =SUM($G$8:$G16) | I16: =SUMIFS(TASK!$Q$8:$Q$127,TASK!$N$8:$N$127,$A16) | J16: =SUM($I$8:$I16) | K16: =$J16-$H16
A17: 12 | B17: 46363 | C17: 56 | D17: =SUM($C$8:$C17) | E17: =SUMIFS(LOGT!$K$7:$K$406,LOGT!$D$7:$D$406,$A17)/60 | F17: =SUM($E$8:$E17) | G17: =SUMIFS(TASK!$P$8:$P$127,TASK!$L$8:$L$127,$A17) | H17: =SUM($G$8:$G17) | I17: =SUMIFS(TASK!$Q$8:$Q$127,TASK!$N$8:$N$127,$A17) | J17: =SUM($I$8:$I17) | K17: =$J17-$H17 | L17: System test and acceptance
A18: 13 | B18: 46370 | C18: 0 | D18: =SUM($C$8:$C18) | E18: =SUMIFS(LOGT!$K$7:$K$406,LOGT!$D$7:$D$406,$A18)/60 | F18: =SUM($E$8:$E18) | G18: =SUMIFS(TASK!$P$8:$P$127,TASK!$L$8:$L$127,$A18) | H18: =SUM($G$8:$G18) | I18: =SUMIFS(TASK!$Q$8:$Q$127,TASK!$N$8:$N$127,$A18) | J18: =SUM($I$8:$I18) | K18: =$J18-$H18 | L18: M3 submitted
A19: 14 | B19: 46377 | C19: 0 | D19: =SUM($C$8:$C19) | E19: =SUMIFS(LOGT!$K$7:$K$406,LOGT!$D$7:$D$406,$A19)/60 | F19: =SUM($E$8:$E19) | G19: =SUMIFS(TASK!$P$8:$P$127,TASK!$L$8:$L$127,$A19) | H19: =SUM($G$8:$G19) | I19: =SUMIFS(TASK!$Q$8:$Q$127,TASK!$N$8:$N$127,$A19) | J19: =SUM($I$8:$I19) | K19: =$J19-$H19
A20: 15 | B20: 46384 | C20: 0 | D20: =SUM($C$8:$C20) | E20: =SUMIFS(LOGT!$K$7:$K$406,LOGT!$D$7:$D$406,$A20)/60 | F20: =SUM($E$8:$E20) | G20: =SUMIFS(TASK!$P$8:$P$127,TASK!$L$8:$L$127,$A20) | H20: =SUM($G$8:$G20) | I20: =SUMIFS(TASK!$Q$8:$Q$127,TASK!$N$8:$N$127,$A20) | J20: =SUM($I$8:$I20) | K20: =$J20-$H20 | L20: M4 - presentation and handover
B21: TOTAL | C21: =SUM(C$8:C$20) | E21: =SUM(E$8:E$20)

Sheet LOGT
A1: Form LOGT - Time Recording Log
A2: One row per working session. Delta is calculated; never type over it.
A4: Team | B4: =SETUP!$C$10 | E4: Total hours logged | G4: =SUM(LOGT!$K$7:$K$406)/60 | H4: Sessions | I4: =COUNT(LOGT!$K$7:$K$406)
A6: Date | B6: Member | C6: Milestone | D6: Week | E6: Phase | F6: Task ID | G6: Component / what you worked on | H6: Start | I6: Stop | J6: Interrupt (min) | K6: Delta (min) | L6: AI used? | M6: Comments
A7: 46300 | B7: Aisyah Binti Rahman | C7: M1 | D7: =IF($A7="","",3+INT(($A7-DATE(2026,10,5))/7)) | E7: MGMT | F7: T01 | G7: SYSTEM - Team admin, lab attendance, instructor check-ins | H7: 0.41666667 | I7: 0.49722222 | J7: 0 | K7: =IF(OR($H7="",$I7=""),"",MAX(0,ROUND(($I7-$H7)*1440,0)-N($J7))) | L7: No
A8: 46301 | B8: Aisyah Binti Rahman | C8: M1 | D8: =IF($A8="","",3+INT(($A8-DATE(2026,10,5))/7)) | E8: STRAT | F8: T02 | G8: SYSTEM - Launch meeting, cycle strategy and stack decisions | H8: 0.55763889 | I8: 0.64097222 | J8: 0 | K8: =IF(OR($H8="",$I8=""),"",MAX(0,ROUND(($I8-$H8)*1440,0)-N($J8))) | L8: No
A9: 46302 | B9: Aisyah Binti Rahman | C9: M1 | D9: =IF($A9="","",3+INT(($A9-DATE(2026,10,5))/7)) | E9: PLAN | F9: T03 | G9: SYSTEM - Task and schedule plan for the cycle | H9: 0.51041667 | I9: 0.59861111 | J9: 0 | K9: =IF(OR($H9="",$I9=""),"",MAX(0,ROUND(($I9-$H9)*1440,0)-N($J9))) | L9: No
A10: 46310 | B10: Aisyah Binti Rahman | C10: M1 | D10: =IF($A10="","",3+INT(($A10-DATE(2026,10,5))/7)) | E10: REQ | F10: T04 | G10: SYSTEM - Elicit requirements from SeaFresh and write the SRS | H10: 0.33333333 | I10: 0.36875 | J10: 0 | K10: =IF(OR($H10="",$I10=""),"",MAX(0,ROUND(($I10-$H10)*1440,0)-N($J10))) | L10: No
A11: 46311 | B11: Aisyah Binti Rahman | C11: M1 | D11: =IF($A11="","",3+INT(($A11-DATE(2026,10,5))/7)) | E11: REQINSP | F11: T06 | G11: SYSTEM - Team inspection of the SRS | H11: 0.46527778 | I11: 0.53472222 | J11: 0 | K11: =IF(OR($H11="",$I11=""),"",MAX(0,ROUND(($I11-$H11)*1440,0)-N($J11))) | L11: No
A12: 46312 | B12: Aisyah Binti Rahman | C12: M1 | D12: =IF($A12="","",3+INT(($A12-DATE(2026,10,5))/7)) | E12: HLD | F12: T07 | G12: SYSTEM - Architecture and SDD | H12: 0.41666667 | I12: 0.45486111 | J12: 0 | K12: =IF(OR($H12="",$I12=""),"",MAX(0,ROUND(($I12-$H12)*1440,0)-N($J12))) | L12: No
A13: 46307 | B13: Aisyah Binti Rahman | C13: M1 | D13: =IF($A13="","",3+INT(($A13-DATE(2026,10,5))/7)) | E13: HLDINSP | F13: T09 | G13: SYSTEM - Team inspection of the SDD | H13: 0.375 | I13: 0.40833333 | J13: 0 | K13: =IF(OR($H13="",$I13=""),"",MAX(0,ROUND(($I13-$H13)*1440,0)-N($J13))) | L13: No
A14: 46315 | B14: Aisyah Binti Rahman | C14: M1 | D14: =IF($A14="","",3+INT(($A14-DATE(2026,10,5))/7)) | E14: DLDR | F14: T11 | G14: UI / screens - Personal review of the detailed design | H14: 0.59027778 | I14: 0.67361111 | J14: 0 | K14: =IF(OR($H14="",$I14=""),"",MAX(0,ROUND(($I14-$H14)*1440,0)-N($J14))) | L14: No
A15: 46316 | B15: Aisyah Binti Rahman | C15: M1 | D15: =IF($A15="","",3+INT(($A15-DATE(2026,10,5))/7)) | E15: TD | F15: T12 | G15: UI / screens - Write the test cases for this component | H15: 0.625 | I15: 0.70625 | J15: 0 | K15: =IF(OR($H15="",$I15=""),"",MAX(0,ROUND(($I15-$H15)*1440,0)-N($J15))) | L15: No
A16: 46317 | B16: Aisyah Binti Rahman | C16: M1 | D16: =IF($A16="","",3+INT(($A16-DATE(2026,10,5))/7)) | E16: DLDINSP | F16: T13 | G16: UI / screens - Team inspection of the detailed design | H16: 0.40625 | I16: 0.44097222 | J16: 0 | K16: =IF(OR($H16="",$I16=""),"",MAX(0,ROUND(($I16-$H16)*1440,0)-N($J16))) | L16: No
A17: 46325 | B17: Aisyah Binti Rahman | C17: M2 | D17: =IF($A17="","",3+INT(($A17-DATE(2026,10,5))/7)) | E17: CR | F17: T15 | G17: UI / screens - Pull-request review by a teammate | H17: 0.58333333 | I17: 0.66388889 | J17: 0 | K17: =IF(OR($H17="",$I17=""),"",MAX(0,ROUND(($I17-$H17)*1440,0)-N($J17))) | L17: No
A18: 46326 | B18: Aisyah Binti Rahman | C18: M2 | D18: =IF($A18="","",3+INT(($A18-DATE(2026,10,5))/7)) | E18: CODEINSP | F18: T17 | G18: UI / screens - Team code inspection | H18: 0.375 | I18: 0.44930556 | J18: 0 | K18: =IF(OR($H18="",$I18=""),"",MAX(0,ROUND(($I18-$H18)*1440,0)-N($J18))) | L18: No
... A31: 46300 | B31: Daniel Wong Jun Hao | C31: M1 | D31: =IF($A31="","",3+INT(($A31-DATE(2026,10,5))/7)) | E31: STRAT | F31: T02 | G31: SYSTEM - Launch meeting, cycle strategy and stack decisions | H31: 0.42013889 | I31: 0.46180556 | J31: 0 | K31: =IF(OR($H31="",$I31=""),"",MAX(0,ROUND(($I31-$H31)*1440,0)-N($J31))) | L31: No
A32: 46301 | B32: Daniel Wong Jun Hao | C32: M1 | D32: =IF($A32="","",3+INT(($A32-DATE(2026,10,5))/7)) | E32: PLAN | F32: T03 | G32: SYSTEM - Task and schedule plan for the cycle | H32: 0.39930556 | I32: 0.47222222 | J32: 15 | K32: =IF(OR($H32="",$I32=""),"",MAX(0,ROUND(($I32-$H32)*1440,0)-N($J32))) | L32: No | M32: eat breakfast
A33: 46309 | B33: Daniel Wong Jun Hao | C33: M1 | D33: =IF($A33="","",3+INT(($A33-DATE(2026,10,5))/7)) | E33: REQ | F33: T04 | G33: SYSTEM - Elicit requirements from SeaFresh and write the SRS | H33: 0.48611111 | I33: 0.56944444 | J33: 0 | K33: =IF(OR($H33="",$I33=""),"",MAX(0,ROUND(($I33-$H33)*1440,0)-N($J33))) | L33: No
A34: 46310 | B34: Daniel Wong Jun Hao | C34: M1 | D34: =IF($A34="","",3+INT(($A34-DATE(2026,10,5))/7)) | E34: STP | F34: T05 | G34: SYSTEM - System test plan | H34: 0.63194444 | I34: 0.74861111 | J34: 0 | K34: =IF(OR($H34="",$I34=""),"",MAX(0,ROUND(($I34-$H34)*1440,0)-N($J34))) | L34: No
A35: 46311 | B35: Daniel Wong Jun Hao | C35: M1 | D35: =IF($A35="","",3+INT(($A35-DATE(2026,10,5))/7)) | E35: REQINSP | F35: T06 | G35: SYSTEM - Team inspection of the SRS | H35: 0.59722222 | I35: 0.66388889 | J35: 0 | K35: =IF(OR($H35="",$I35=""),"",MAX(0,ROUND(($I35-$H35)*1440,0)-N($J35))) | L35: No
A36: 46312 | B36: Daniel Wong Jun Hao | C36: M1 | D36: =IF($A36="","",3+INT(($A36-DATE(2026,10,5))/7)) | E36: HLD | F36: T07 | G36: SYSTEM - Architecture and SDD | H36: 0.66388889 | I36: 0.74722222 | J36: 0 | K36: =IF(OR($H36="",$I36=""),"",MAX(0,ROUND(($I36-$H36)*1440,0)-N($J36))) | L36: No
A37: 46307 | B37: Daniel Wong Jun Hao | C37: M1 | D37: =IF($A37="","",3+INT(($A37-DATE(2026,10,5))/7)) | E37: ITP | F37: T08 | G37: SYSTEM - Integration test plan | H37: 0.71180556 | I37: 0.8125 | J37: 25 | K37: =IF(OR($H37="",$I37=""),"",MAX(0,ROUND(($I37-$H37)*1440,0)-N($J37))) | L37: No | M37: friend call
A38: 46308 | B38: Daniel Wong Jun Hao | C38: M1 | D38: =IF($A38="","",3+INT(($A38-DATE(2026,10,5))/7)) | E38: HLDINSP | F38: T09 | G38: SYSTEM - Team inspection of the SDD | H38: 0.8125 | I38: 0.85416667 | J38: 0 | K38: =IF(OR($H38="",$I38=""),"",MAX(0,ROUND(($I38-$H38)*1440,0)-N($J38))) | L38: No
A39: 46316 | B39: Daniel Wong Jun Hao | C39: M1 | D39: =IF($A39="","",3+INT(($A39-DATE(2026,10,5))/7)) | E39: DLD | F39: T10 | G39: UI / screens - Detailed design of screens, widgets and models | H39: 0.77777778 | I39: 0.88611111 | J39: 0 | K39: =IF(OR($H39="",$I39=""),"",MAX(0,ROUND(($I39-$H39)*1440,0)-N($J39))) | L39: No
A40: 46317 | B40: Daniel Wong Jun Hao | C40: M1 | D40: =IF($A40="","",3+INT(($A40-DATE(2026,10,5))/7)) | E40: DLDR | F40: T11 | G40: UI / screens - Personal review of the detailed design | H40: 0.88611111 | I40: 0.96944444 | J40: 0 | K40: =IF(OR($H40="",$I40=""),"",MAX(0,ROUND(($I40-$H40)*1440,0)-N($J40))) | L40: No
A41: 46318 | B41: Daniel Wong Jun Hao | C41: M1 | D41: =IF($A41="","",3+INT(($A41-DATE(2026,10,5))/7)) | E41: TD | F41: T12 | G41: UI / screens - Write the test cases for this component | H41: 0.47916667 | I41: 0.54166667 | J41: 0 | K41: =IF(OR($H41="",$I41=""),"",MAX(0,ROUND(($I41-$H41)*1440,0)-N($J41))) | L41: No
A42: 46319 | B42: Daniel Wong Jun Hao | C42: M1 | D42: =IF($A42="","",3+INT(($A42-DATE(2026,10,5))/7)) | E42: DLDINSP | F42: T13 | G42: UI / screens - Team inspection of the detailed design | H42: 0.66319444 | I42: 0.70486111 | J42: 0 | K42: =IF(OR($H42="",$I42=""),"",MAX(0,ROUND(($I42-$H42)*1440,0)-N($J42))) | L42: No
A43: 46321 | B43: Daniel Wong Jun Hao | C43: M2 | D43: =IF($A43="","",3+INT(($A43-DATE(2026,10,5))/7)) | E43: CODE | F43: T14 | G43: UI / screens - Implement in Dart / Flutter | H43: 0.81944444 | I43: 0.90694444 | J43: 0 | K43: =IF(OR($H43="",$I43=""),"",MAX(0,ROUND(($I43-$H43)*1440,0)-N($J43))) | L43: No
A44: 46322 | B44: Daniel Wong Jun Hao | C44: M2 | D44: =IF($A44="","",3+INT(($A44-DATE(2026,10,5))/7)) | E44: CR | F44: T15 | G44: UI / screens - Pull-request review by a teammate | H44: 0.61111111 | I44: 0.65277778 | J44: 0 | K44: =IF(OR($H44="",$I44=""),"",MAX(0,ROUND(($I44-$H44)*1440,0)-N($J44))) | L44: No
A45: 46323 | B45: Daniel Wong Jun Hao | C45: M2 | D45: =IF($A45="","",3+INT(($A45-DATE(2026,10,5))/7)) | E45: BUILD | F45: T16 | G45: UI / screens - flutter analyze and build, fix what it reports | H45: 0.71527778 | I45: 0.78194444 | J45: 0 | K45: =IF(OR($H45="",$I45=""),"",MAX(0,ROUND(($I45-$H45)*1440,0)-N($J45))) | L45: No
A46: 46324 | B46: Daniel Wong Jun Hao | C46: M2 | D46: =IF($A46="","",3+INT(($A46-DATE(2026,10,5))/7)) | E46: CODEINSP | F46: T17 | G46: UI / screens - Team code inspection | H46: 0.51041667 | I46: 0.59375 | J46: 0 | K46: =IF(OR($H46="",$I46=""),"",MAX(0,ROUND(($I46-$H46)*1440,0)-N($J46))) | L46: No
A47: 46300 | B47: Mei Ling Chong | C47: M1 | D47: =IF($A47="","",3+INT(($A47-DATE(2026,10,5))/7)) | E47: MGMT | F47: T01 | G47: SYSTEM - Team admin, lab attendance, instructor check-ins | H47: 0.64583333 | I47: 0.72916667 | J47: 0 | K47: =IF(OR($H47="",$I47=""),"",MAX(0,ROUND(($I47-$H47)*1440,0)-N($J47))) | L47: No
A48: 46301 | B48: Mei Ling Chong | C48: M1 | D48: =IF($A48="","",3+INT(($A48-DATE(2026,10,5))/7)) | E48: STRAT | F48: T02 | G48: SYSTEM - Launch meeting, cycle strategy and stack decisions | H48: 0.59027778 | I48: 0.67291667 | J48: 0 | K48: =IF(OR($H48="",$I48=""),"",MAX(0,ROUND(($I48-$H48)*1440,0)-N($J48))) | L48: No
A49: 46302 | B49: Mei Ling Chong | C49: M1 | D49: =IF($A49="","",3+INT(($A49-DATE(2026,10,5))/7)) | E49: PLAN | F49: T03 | G49: SYSTEM - Task and schedule plan for the cycle | H49: 0.41666667 | I49: 0.50902778 | J49: 0 | K49: =IF(OR($H49="",$I49=""),"",MAX(0,ROUND(($I49-$H49)*1440,0)-N($J49))) | L49: No
A50: 46310 | B50: Mei Ling Chong | C50: M1 | D50: =IF($A50="","",3+INT(($A50-DATE(2026,10,5))/7)) | E50: STP | F50: T05 | G50: SYSTEM - System test plan | H50: 0.59375 | I50: 0.66666667 | J50: 0 | K50: =IF(OR($H50="",$I50=""),"",MAX(0,ROUND(($I50-$H50)*1440,0)-N($J50))) | L50: No
A51: 46311 | B51: Mei Ling Chong | C51: M1 | D51: =IF($A51="","",3+INT(($A51-DATE(2026,10,5))/7)) | E51: REQINSP | F51: T06 | G51: SYSTEM - Team inspection of the SRS | H51: 0.3125 | I51: 0.41180556 | J51: 30 | K51: =IF(OR($H51="",$I51=""),"",MAX(0,ROUND(($I51-$H51)*1440,0)-N($J51))) | L51: No | M51: breakfast
A52: 46312 | B52: Mei Ling Chong | C52: M1 | D52: =IF($A52="","",3+INT(($A52-DATE(2026,10,5))/7)) | E52: HLD | F52: T07 | G52: SYSTEM - Architecture and SDD | H52: 0.85416667 | I52: 0.89305556 | J52: 0 | K52: =IF(OR($H52="",$I52=""),"",MAX(0,ROUND(($I52-$H52)*1440,0)-N($J52))) | L52: No
A53: 46307 | B53: Mei Ling Chong | C53: M1 | D53: =IF($A53="","",3+INT(($A53-DATE(2026,10,5))/7)) | E53: ITP | F53: T08 | G53: SYSTEM - Integration test plan | H53: 0.625 | I53: 0.72430556 | J53: 20 | K53: =IF(OR($H53="",$I53=""),"",MAX(0,ROUND(($I53-$H53)*1440,0)-N($J53))) | L53: No | M53: solve other matters
A54: 46315 | B54: Mei Ling Chong | C54: M1 | D54: =IF($A54="","",3+INT(($A54-DATE(2026,10,5))/7)) | E54: DLDR | F54: T11 | G54: UI / screens - Personal review of the detailed design | H54: 0.66666667 | I54: 0.70833333 | J54: 0 | K54: =IF(OR($H54="",$I54=""),"",MAX(0,ROUND(($I54-$H54)*1440,0)-N($J54))) | L54: No
A55: 46316 | B55: Mei Ling Chong | C55: M1 | D55: =IF($A55="","",3+INT(($A55-DATE(2026,10,5))/7)) | E55: TD | F55: T12 | G55: UI / screens - Write the test cases for this component | H55: 0.66666667 | I55: 0.83333333 | J55: 60 | K55: =IF(OR($H55="",$I55=""),"",MAX(0,ROUND(($I55-$H55)*1440,0)-N($J55))) | L55: No | M55: dinner
A56: 46317 | B56: Mei Ling Chong | C56: M1 | D56: =IF($A56="","",3+INT(($A56-DATE(2026,10,5))/7)) | E56: DLDINSP | F56: T13 | G56: UI / screens - Team inspection of the detailed design | H56: 0.58333333 | I56: 0.66041667 | J56: 0 | K56: =IF(OR($H56="",$I56=""),"",MAX(0,ROUND(($I56-$H56)*1440,0)-N($J56))) | L56: No
A57: 46325 | B57: Mei Ling Chong | C57: M2 | D57: =IF($A57="","",3+INT(($A57-DATE(2026,10,5))/7)) | E57: CODE | F57: T14 | G57: UI / screens - Implement in Dart / Flutter | H57: 0.44791667 | I57: 0.58333333 | J57: 30 | K57: =IF(OR($H57="",$I57=""),"",MAX(0,ROUND(($I57-$H57)*1440,0)-N($J57))) | L57: No | M57: lunch
A58: 46326 | B58: Mei Ling Chong | C58: M2 | D58: =IF($A58="","",3+INT(($A58-DATE(2026,10,5))/7)) | E58: CR | F58: T15 | G58: UI / screens - Pull-request review by a teammate | H58: 0.79166667 | I58: 0.91666667 | J58: 0 | K58: =IF(OR($H58="",$I58=""),"",MAX(0,ROUND(($I58-$H58)*1440,0)-N($J58))) | L58: No
A59: 46321 | B59: Mei Ling Chong | C59: M2 | D59: =IF($A59="","",3+INT(($A59-DATE(2026,10,5))/7)) | E59: CODEINSP | F59: T17 | G59: UI / screens - Team code inspection | H59: 0.77083333 | I59: 0.85069444 | J59: 0 | K59: =IF(OR($H59="",$I59=""),"",MAX(0,ROUND(($I59-$H59)*1440,0)-N($J59))) | L59: No
A60: 46329 | B60: Mei Ling Chong | C60: M2 | D60: =IF($A60="","",3+INT(($A60-DATE(2026,10,5))/7)) | E60: UT | F60: T18 | G60: UI / screens - Unit tests for this component | H60: 0.66666667 | I60: 0.91180556 | J60: 120 | K60: =IF(OR($H60="",$I60=""),"",MAX(0,ROUND(($I60-$H60)*1440,0)-N($J60))) | L60: No | M60: rest, dinner
A61: 46330 | B61: Mei Ling Chong | C61: M2 | D61: =IF($A61="","",3+INT(($A61-DATE(2026,10,5))/7)) | E61: DLDR | F61: T20 | G61: Order & catalogue service - Personal review of the detailed design | H61: 0.80555556 | I61: 0.95486111 | J61: 0 | K61: =IF(OR($H61="",$I61=""),"",MAX(0,ROUND(($I61-$H61)*1440,0)-N($J61))) | L61: No
A62: 46331 | B62: Mei Ling Chong | C62: M2 | D62: =IF($A62="","",3+INT(($A62-DATE(2026,10,5))/7)) | E62: TD | F62: T21 | G62: Order & catalogue service - Write the test cases for this component | H62: 0.41666667 | I62: 0.57986111 | J62: 0 | K62: =IF(OR($H62="",$I62=""),"",MAX(0,ROUND(($I62-$H62)*1440,0)-N($J62))) | L62: No
A63: 46332 | B63: Mei Ling Chong | C63: M2 | D63: =IF($A63="","",3+INT(($A63-DATE(2026,10,5))/7)) | E63: DLDINSP | F63: T22 | G63: Order & catalogue service - Team inspection of the detailed design | H63: 0.625 | I63: 0.72916667 | J63: 0 | K63: =IF(OR($H63="",$I63=""),"",MAX(0,ROUND(($I63-$H63)*1440,0)-N($J63))) | L63: No
A64: 46347 | B64: Mei Ling Chong | C64: M2 | D64: =IF($A64="","",3+INT(($A64-DATE(2026,10,5))/7)) | E64: CR | F64: T24 | G64: Order & catalogue service - Pull-request review by a teammate | H64: 0.45833333 | I64: 0.61805556 | J64: 60 | K64: =IF(OR($H64="",$I64=""),"",MAX(0,ROUND(($I64-$H64)*1440,0)-N($J64))) | L64: No | M64: lunch
A65: 46342 | B65: Mei Ling Chong | C65: M2 | D65: =IF($A65="","",3+INT(($A65-DATE(2026,10,5))/7)) | E65: BUILD | F65: T25 | G65: Order & catalogue service - flutter analyze and build, fix what it rep | H65: 0.70833333 | I65: 0.82291667 | J65: 0 | K65: =IF(OR($H65="",$I65=""),"",MAX(0,ROUND(($I65-$H65)*1440,0)-N($J65))) | L65: No
A66: 46343 | B66: Mei Ling Chong | C66: M2 | D66: =IF($A66="","",3+INT(($A66-DATE(2026,10,5))/7)) | E66: CODEINSP | F66: T26 | G66: Order & catalogue service - Team code inspection | H66: 0.83333333 | I66: 0.97916667 | J66: 0 | K66: =IF(OR($H66="",$I66=""),"",MAX(0,ROUND(($I66-$H66)*1440,0)-N($J66))) | L66: No
A67: 46344 | B67: Mei Ling Chong | C67: M2 | D67: =IF($A67="","",3+INT(($A67-DATE(2026,10,5))/7)) | E67: UT | F67: T27 | G67: Order & catalogue service - Unit tests for this component | H67: 0.4375 | I67: 0.60416667 | J67: 0 | K67: =IF(OR($H67="",$I67=""),"",MAX(0,ROUND(($I67-$H67)*1440,0)-N($J67))) | L67: No
A68: 46345 | B68: Mei Ling Chong | C68: M2 | D68: =IF($A68="","",3+INT(($A68-DATE(2026,10,5))/7)) | E68: DLD | F68: T28 | G68: Local store & sync - Detailed design of screens, widgets and models | H68: 0.41666667 | I68: 0.5 | J68: 0 | K68: =IF(OR($H68="",$I68=""),"",MAX(0,ROUND(($I68-$H68)*1440,0)-N($J68))) | L68: No
A69: 46346 | B69: Mei Ling Chong | C69: M2 | D69: =IF($A69="","",3+INT(($A69-DATE(2026,10,5))/7)) | E69: DLDR | F69: T29 | G69: Local store & sync - Personal review of the detailed design | H69: 0.60416667 | I69: 0.75 | J69: 30 | K69: =IF(OR($H69="",$I69=""),"",MAX(0,ROUND(($I69-$H69)*1440,0)-N($J69))) | L69: No | M69: break
A70: 46354 | B70: Mei Ling Chong | C70: M3 | D70: =IF($A70="","",3+INT(($A70-DATE(2026,10,5))/7)) | E70: TD | F70: T30 | G70: Local store & sync - Write the test cases for this component | H70: 0.79513889 | I70: 0.91666667 | J70: 0 | K70: =IF(OR($H70="",$I70=""),"",MAX(0,ROUND(($I70-$H70)*1440,0)-N($J70))) | L70: No
A71: 46349 | B71: Mei Ling Chong | C71: M3 | D71: =IF($A71="","",3+INT(($A71-DATE(2026,10,5))/7)) | E71: DLDINSP | F71: T31 | G71: Local store & sync - Team inspection of the detailed design | H71: 0.45833333 | I71: 0.54513889 | J71: 0 | K71: =IF(OR($H71="",$I71=""),"",MAX(0,ROUND(($I71-$H71)*1440,0)-N($J71))) | L71: No
A72: 46350 | B72: Mei Ling Chong | C72: M3 | D72: =IF($A72="","",3+INT(($A72-DATE(2026,10,5))/7)) | E72: CODE | F72: T32 | G72: Local store & sync - Implement in Dart / Flutter | H72: 0.79166667 | I72: 0.91666667 | J72: 0 | K72: =IF(OR($H72="",$I72=""),"",MAX(0,ROUND(($I72-$H72)*1440,0)-N($J72))) | L72: No
A73: 46351 | B73: Mei Ling Chong | C73: M3 | D73: =IF($A73="","",3+INT(($A73-DATE(2026,10,5))/7)) | E73: CR | F73: T33 | G73: Local store & sync - Pull-request review by a teammate | H73: 0.625 | I73: 0.71527778 | J73: 0 | K73: =IF(OR($H73="",$I73=""),"",MAX(0,ROUND(($I73-$H73)*1440,0)-N($J73))) | L73: No
A74: 46352 | B74: Mei Ling Chong | C74: M3 | D74: =IF($A74="","",3+INT(($A74-DATE(2026,10,5))/7)) | E74: BUILD | F74: T34 | G74: Local store & sync - flutter analyze and build, fix what it reports | H74: 0.875 | I74: 0.95486111 | J74: 0 | K74: =IF(OR($H74="",$I74=""),"",MAX(0,ROUND(($I74-$H74)*1440,0)-N($J74))) | L74: No
A75: 46360 | B75: Mei Ling Chong | C75: M3 | D75: =IF($A75="","",3+INT(($A75-DATE(2026,10,5))/7)) | E75: CODEINSP | F75: T35 | G75: Local store & sync - Team code inspection | H75: 0.67361111 | I75: 0.75694444 | J75: 0 | K75: =IF(OR($H75="",$I75=""),"",MAX(0,ROUND(($I75-$H75)*1440,0)-N($J75))) | L75: No
A76: 46361 | B76: Mei Ling Chong | C76: M3 | D76: =IF($A76="","",3+INT(($A76-DATE(2026,10,5))/7)) | E76: UT | F76: T36 | G76: Local store & sync - Unit tests for this component | H76: 0.66666667 | I76: 0.91666667 | J76: 120 | K76: =IF(OR($H76="",$I76=""),"",MAX(0,ROUND(($I76-$H76)*1440,0)-N($J76))) | L76: No | M76: rest, dinner
A77: 46356 | B77: Mei Ling Chong | C77: M3 | D77: =IF($A77="","",3+INT(($A77-DATE(2026,10,5))/7)) | E77: IT | F77: T37 | G77: SYSTEM - Build and integration test across components | H77: 0.75 | I77: 0.83333333 | J77: 0 | K77: =IF(OR($H77="",$I77=""),"",MAX(0,ROUND(($I77-$H77)*1440,0)-N($J77))) | L77: No
A78: 46364 | B78: Mei Ling Chong | C78: M3 | D78: =IF($A78="","",3+INT(($A78-DATE(2026,10,5))/7)) | E78: ST | F78: T38 | G78: SYSTEM - System test against the SRS | H78: 0.625 | I78: 0.91666667 | J78: 120 | K78: =IF(OR($H78="",$I78=""),"",MAX(0,ROUND(($I78-$H78)*1440,0)-N($J78))) | L78: No | M78: dinner, family meeting
A79: 46365 | B79: Mei Ling Chong | C79: M3 | D79: =IF($A79="","",3+INT(($A79-DATE(2026,10,5))/7)) | E79: DOC | F79: T39 | G79: SYSTEM - User manual and final report | H79: 0.41666667 | I79: 0.625 | J79: 60 | K79: =IF(OR($H79="",$I79=""),"",MAX(0,ROUND(($I79-$H79)*1440,0)-N($J79))) | L79: No | M79: lunch
A80: 46366 | B80: Mei Ling Chong | C80: M3 | D80: =IF($A80="","",3+INT(($A80-DATE(2026,10,5))/7)) | E80: PM | F80: T40 | G80: SYSTEM - Postmortem: review the data and agree three changes | H80: 0.58333333 | I80: 0.66666667 | J80: 0 | K80: =IF(OR($H80="",$I80=""),"",MAX(0,ROUND(($I80-$H80)*1440,0)-N($J80))) | L80: No
A81: 46300 | B81: Harith Bin Ismail | C81: M1 | D81: =IF($A81="","",3+INT(($A81-DATE(2026,10,5))/7)) | E81: MGMT | F81: T01 | G81: SYSTEM - Team admin, lab attendance, instructor check-ins | H81: 0.75 | I81: 0.79166667 | J81: 0 | K81: =IF(OR($H81="",$I81=""),"",MAX(0,ROUND(($I81-$H81)*1440,0)-N($J81))) | L81: No
A82: 46301 | B82: Harith Bin Ismail | C82: M1 | D82: =IF($A82="","",3+INT(($A82-DATE(2026,10,5))/7)) | E82: STRAT | F82: T02 | G82: SYSTEM - Launch meeting, cycle strategy and stack decisions | H82: 0.79166667 | I82: 0.875 | J82: 0 | K82: =IF(OR($H82="",$I82=""),"",MAX(0,ROUND(($I82-$H82)*1440,0)-N($J82))) | L82: No
A83: 46302 | B83: Harith Bin Ismail | C83: M1 | D83: =IF($A83="","",3+INT(($A83-DATE(2026,10,5))/7)) | E83: PLAN | F83: T03 | G83: SYSTEM - Task and schedule plan for the cycle | H83: 0.79166667 | I83: 0.875 | J83: 0 | K83: =IF(OR($H83="",$I83=""),"",MAX(0,ROUND(($I83-$H83)*1440,0)-N($J83))) | L83: No
A84: 46310 | B84: Harith Bin Ismail | C84: M1 | D84: =IF($A84="","",3+INT(($A84-DATE(2026,10,5))/7)) | E84: REQ | F84: T04 | G84: SYSTEM - Elicit requirements from SeaFresh and write the SRS | H84: 0.625 | I84: 0.75 | J84: 0 | K84: =IF(OR($H84="",$I84=""),"",MAX(0,ROUND(($I84-$H84)*1440,0)-N($J84))) | L84: No
A85: 46311 | B85: Harith Bin Ismail | C85: M1 | D85: =IF($A85="","",3+INT(($A85-DATE(2026,10,5))/7)) | E85: STP | F85: T05 | G85: SYSTEM - System test plan | H85: 0.79166667 | I85: 0.83333333 | J85: 0 | K85: =IF(OR($H85="",$I85=""),"",MAX(0,ROUND(($I85-$H85)*1440,0)-N($J85))) | L85: No
A86: 46312 | B86: Harith Bin Ismail | C86: M1 | D86: =IF($A86="","",3+INT(($A86-DATE(2026,10,5))/7)) | E86: REQINSP | F86: T06 | G86: SYSTEM - Team inspection of the SRS | H86: 0.70833333 | I86: 0.8125 | J86: 0 | K86: =IF(OR($H86="",$I86=""),"",MAX(0,ROUND(($I86-$H86)*1440,0)-N($J86))) | L86: No
A87: 46307 | B87: Harith Bin Ismail | C87: M1 | D87: =IF($A87="","",3+INT(($A87-DATE(2026,10,5))/7)) | E87: HLD | F87: T07 | G87: SYSTEM - Architecture and SDD | H87: 0.54166667 | I87: 0.6875 | J87: 0 | K87: =IF(OR($H87="",$I87=""),"",MAX(0,ROUND(($I87-$H87)*1440,0)-N($J87))) | L87: No
A88: 46308 | B88: Harith Bin Ismail | C88: M1 | D88: =IF($A88="","",3+INT(($A88-DATE(2026,10,5))/7)) | E88: ITP | F88: T08 | G88: SYSTEM - Integration test plan | H88: 0.41666667 | I88: 0.5 | J88: 0 | K88: =IF(OR($H88="",$I88=""),"",MAX(0,ROUND(($I88-$H88)*1440,0)-N($J88))) | L88: No
A89: 46309 | B89: Harith Bin Ismail | C89: M1 | D89: =IF($A89="","",3+INT(($A89-DATE(2026,10,5))/7)) | E89: HLDINSP | F89: T09 | G89: SYSTEM - Team inspection of the SDD | H89: 0.45833333 | I89: 0.54166667 | J89: 0 | K89: =IF(OR($H89="",$I89=""),"",MAX(0,ROUND(($I89-$H89)*1440,0)-N($J89))) | L89: No
A90: 46317 | B90: Harith Bin Ismail | C90: M1 | D90: =IF($A90="","",3+INT(($A90-DATE(2026,10,5))/7)) | E90: DLD | F90: T10 | G90: UI / screens - Detailed design of screens, widgets and models | H90: 0.58333333 | I90: 0.875 | J90: 0 | K90: =IF(OR($H90="",$I90=""),"",MAX(0,ROUND(($I90-$H90)*1440,0)-N($J90))) | L90: No
A91: 46318 | B91: Harith Bin Ismail | C91: M1 | D91: =IF($A91="","",3+INT(($A91-DATE(2026,10,5))/7)) | E91: DLDR | F91: T11 | G91: UI / screens - Personal review of the detailed design | H91: 0.375 | I91: 0.58333333 | J91: 0 | K91: =IF(OR($H91="",$I91=""),"",MAX(0,ROUND(($I91-$H91)*1440,0)-N($J91))) | L91: No
... A93: 46314 | B93: Harith Bin Ismail | C93: M1 | D93: =IF($A93="","",3+INT(($A93-DATE(2026,10,5))/7)) | E93: DLDINSP | F93: T13 | G93: UI / screens - Team inspection of the detailed design | H93: 0.45833333 | I93: 0.66666667 | J93: 0 | K93: =IF(OR($H93="",$I93=""),"",MAX(0,ROUND(($I93-$H93)*1440,0)-N($J93))) | L93: No
A94: 46322 | B94: Harith Bin Ismail | C94: M2 | D94: =IF($A94="","",3+INT(($A94-DATE(2026,10,5))/7)) | E94: CODE | F94: T14 | G94: UI / screens - Implement in Dart / Flutter | H94: 0.58333333 | I94: 0 | J94: 80 | K94: =IF(OR($H94="",$I94=""),"",MAX(0,ROUND(($I94-$H94)*1440,0)-N($J94))) | L94: No | M94: dinner
A95: 46323 | B95: Harith Bin Ismail | C95: M2 | D95: =IF($A95="","",3+INT(($A95-DATE(2026,10,5))/7)) | E95: CODE | F95: T14 | G95: UI / screens - Implement in Dart / Flutter | H95: 0.64583333 | I95: 0.97916667 | J95: 80 | K95: =IF(OR($H95="",$I95=""),"",MAX(0,ROUND(($I95-$H95)*1440,0)-N($J95))) | L95: No | M95: dinner and rest
A96: 46324 | B96: Harith Bin Ismail | C96: M2 | D96: =IF($A96="","",3+INT(($A96-DATE(2026,10,5))/7)) | E96: CR | F96: T15 | G96: UI / screens - Pull-request review by a teammate | H96: 0.70833333 | I96: 0.91666667 | J96: 0 | K96: =IF(OR($H96="",$I96=""),"",MAX(0,ROUND(($I96-$H96)*1440,0)-N($J96))) | L96: No
A97: 46325 | B97: Harith Bin Ismail | C97: M2 | D97: =IF($A97="","",3+INT(($A97-DATE(2026,10,5))/7)) | E97: BUILD | F97: T16 | G97: UI / screens - flutter analyze and build, fix what it reports | H97: 0.60416667 | I97: 0.70833333 | J97: 0 | K97: =IF(OR($H97="",$I97=""),"",MAX(0,ROUND(($I97-$H97)*1440,0)-N($J97))) | L97: No
A98: 46326 | B98: Harith Bin Ismail | C98: M2 | D98: =IF($A98="","",3+INT(($A98-DATE(2026,10,5))/7)) | E98: CODEINSP | F98: T17 | G98: UI / screens - Team code inspection | H98: 0.54166667 | I98: 0.83333333 | J98: 40 | K98: =IF(OR($H98="",$I98=""),"",MAX(0,ROUND(($I98-$H98)*1440,0)-N($J98))) | L98: No | M98: lunch
A99: 46321 | B99: Harith Bin Ismail | C99: M2 | D99: =IF($A99="","",3+INT(($A99-DATE(2026,10,5))/7)) | E99: UT | F99: T18 | G99: UI / screens - Unit tests for this component | H99: 0.45833333 | I99: 0.66666667 | J99: 0 | K99: =IF(OR($H99="",$I99=""),"",MAX(0,ROUND(($I99-$H99)*1440,0)-N($J99))) | L99: No
A100: 46329 | B100: Harith Bin Ismail | C100: M2 | D100: =IF($A100="","",3+INT(($A100-DATE(2026,10,5))/7)) | E100: DLD | F100: T19 | G100: Order & catalogue service - Detailed design of screens, widgets and mo | H100: 0.70833333 | I100: 0.875 | J100: 0 | K100: =IF(OR($H100="",$I100=""),"",MAX(0,ROUND(($I100-$H100)*1440,0)-N($J100))) | L100: No
A101: 46330 | B101: Harith Bin Ismail | C101: M2 | D101: =IF($A101="","",3+INT(($A101-DATE(2026,10,5))/7)) | E101: DLDR | F101: T20 | G101: Order & catalogue service - Personal review of the detailed design | H101: 0.79166667 | I101: 0.91666667 | J101: 0 | K101: =IF(OR($H101="",$I101=""),"",MAX(0,ROUND(($I101-$H101)*1440,0)-N($J101))) | L101: No
A102: 46331 | B102: Harith Bin Ismail | C102: M2 | D102: =IF($A102="","",3+INT(($A102-DATE(2026,10,5))/7)) | E102: TD | F102: T21 | G102: Order & catalogue service - Write the test cases for this component | H102: 0.54166667 | I102: 0.66666667 | J102: 0 | K102: =IF(OR($H102="",$I102=""),"",MAX(0,ROUND(($I102-$H102)*1440,0)-N($J102))) | L102: No
A103: 46332 | B103: Harith Bin Ismail | C103: M2 | D103: =IF($A103="","",3+INT(($A103-DATE(2026,10,5))/7)) | E103: DLDINSP | F103: T22 | G103: Order & catalogue service - Team inspection of the detailed design | H103: 0.41666667 | I103: 0.625 | J103: 0 | K103: =IF(OR($H103="",$I103=""),"",MAX(0,ROUND(($I103-$H103)*1440,0)-N($J103))) | L103: No
A104: 46333 | B104: Harith Bin Ismail | C104: M2 | D104: =IF($A104="","",3+INT(($A104-DATE(2026,10,5))/7)) | E104: CODE | F104: T23 | G104: Order & catalogue service - Implement in Dart / Flutter | H104: 0.41666667 | I104: 0.58333333 | J104: 0 | K104: =IF(OR($H104="",$I104=""),"",MAX(0,ROUND(($I104-$H104)*1440,0)-N($J104))) | L104: No
A105: 46342 | B105: Harith Bin Ismail | C105: M2 | D105: =IF($A105="","",3+INT(($A105-DATE(2026,10,5))/7)) | E105: CR | F105: T24 | G105: Order & catalogue service - Pull-request review by a teammate | H105: 0.625 | I105: 0.83333333 | J105: 60 | K105: =IF(OR($H105="",$I105=""),"",MAX(0,ROUND(($I105-$H105)*1440,0)-N($J105))) | L105: No | M105: dinner
A106: 46343 | B106: Harith Bin Ismail | C106: M2 | D106: =IF($A106="","",3+INT(($A106-DATE(2026,10,5))/7)) | E106: BUILD | F106: T25 | G106: Order & catalogue service - flutter analyze and build, fix what it rep | H106: 0.41666667 | I106: 0.66666667 | J106: 60 | K106: =IF(OR($H106="",$I106=""),"",MAX(0,ROUND(($I106-$H106)*1440,0)-N($J106))) | L106: No | M106: lunch
A107: 46344 | B107: Harith Bin Ismail | C107: M2 | D107: =IF($A107="","",3+INT(($A107-DATE(2026,10,5))/7)) | E107: CODEINSP | F107: T26 | G107: Order & catalogue service - Team code inspection | H107: 0.79166667 | I107: 0.91666667 | J107: 0 | K107: =IF(OR($H107="",$I107=""),"",MAX(0,ROUND(($I107-$H107)*1440,0)-N($J107))) | L107: No
A108: 46345 | B108: Harith Bin Ismail | C108: M2 | D108: =IF($A108="","",3+INT(($A108-DATE(2026,10,5))/7)) | E108: UT | F108: T27 | G108: Order & catalogue service - Unit tests for this component | H108: 0.58333333 | I108: 0.6875 | J108: 0 | K108: =IF(OR($H108="",$I108=""),"",MAX(0,ROUND(($I108-$H108)*1440,0)-N($J108))) | L108: No
A109: 46346 | B109: Harith Bin Ismail | C109: M2 | D109: =IF($A109="","",3+INT(($A109-DATE(2026,10,5))/7)) | E109: DLD | F109: T28 | G109: Local store & sync - Detailed design of screens, widgets and models | H109: 0.70833333 | I109: 0.83333333 | J109: 0 | K109: =IF(OR($H109="",$I109=""),"",MAX(0,ROUND(($I109-$H109)*1440,0)-N($J109))) | L109: No
A110: 46347 | B110: Harith Bin Ismail | C110: M2 | D110: =IF($A110="","",3+INT(($A110-DATE(2026,10,5))/7)) | E110: DLDR | F110: T29 | G110: Local store & sync - Personal review of the detailed design | H110: 0.54166667 | I110: 0.75 | J110: 0 | K110: =IF(OR($H110="",$I110=""),"",MAX(0,ROUND(($I110-$H110)*1440,0)-N($J110))) | L110: No
A111: 46349 | B111: Harith Bin Ismail | C111: M3 | D111: =IF($A111="","",3+INT(($A111-DATE(2026,10,5))/7)) | E111: TD | F111: T30 | G111: Local store & sync - Write the test cases for this component | H111: 0.375 | I111: 0.58333333 | J111: 60 | K111: =IF(OR($H111="",$I111=""),"",MAX(0,ROUND(($I111-$H111)*1440,0)-N($J111))) | L111: No | M111: lunch
A112: 46350 | B112: Harith Bin Ismail | C112: M3 | D112: =IF($A112="","",3+INT(($A112-DATE(2026,10,5))/7)) | E112: DLDINSP | F112: T31 | G112: Local store & sync - Team inspection of the detailed design | H112: 0.41666667 | I112: 0.54166667 | J112: 0 | K112: =IF(OR($H112="",$I112=""),"",MAX(0,ROUND(($I112-$H112)*1440,0)-N($J112))) | L112: No
A113: 46351 | B113: Harith Bin Ismail | C113: M3 | D113: =IF($A113="","",3+INT(($A113-DATE(2026,10,5))/7)) | E113: CODE | F113: T32 | G113: Local store & sync - Implement in Dart / Flutter | H113: 0.70833333 | I113: 0.91666667 | J113: 80 | K113: =IF(OR($H113="",$I113=""),"",MAX(0,ROUND(($I113-$H113)*1440,0)-N($J113))) | L113: No | M113: dinner and rest
A114: 46352 | B114: Harith Bin Ismail | C114: M3 | D114: =IF($A114="","",3+INT(($A114-DATE(2026,10,5))/7)) | E114: CR | F114: T33 | G114: Local store & sync - Pull-request review by a teammate | H114: 0.54166667 | I114: 0.66666667 | J114: 0 | K114: =IF(OR($H114="",$I114=""),"",MAX(0,ROUND(($I114-$H114)*1440,0)-N($J114))) | L114: No
A115: 46353 | B115: Harith Bin Ismail | C115: M3 | D115: =IF($A115="","",3+INT(($A115-DATE(2026,10,5))/7)) | E115: BUILD | F115: T34 | G115: Local store & sync - flutter analyze and build, fix what it reports | H115: 0.41666667 | I115: 0.5 | J115: 0 | K115: =IF(OR($H115="",$I115=""),"",MAX(0,ROUND(($I115-$H115)*1440,0)-N($J115))) | L115: No
...

Sheet LOGD
A1: Form LOGD - Defect Recording Log
A2: Every defect found, wherever it was found. A defect caught in review still counts.
A4: Team | B4: =SETUP!$C$10 | E4: Defects recorded | G4: =COUNTA(LOGD!$B$7:$B$306) | H4: Total fix time (hrs) | J4: =SUM(LOGD!$I$7:$I$306)/60
A6: Date | B6: Defect ID | C6: Found by | D6: Milestone | E6: Type | F6: Component | G6: Injected in | H6: Removed in | I6: Fix time (min) | J6: Fix reference | K6: Severity | L6: From AI code? | M6: Description & root cause
A7: 46364 | B7: D001 | C7: Daniel Wong Jun Hao | D7: M3 | E7: 10 - Documentation | F7: HLD | G7: HLD | H7: HLDINSP | I7: 30 | J7: PR | K7: Minor | L7: No | M7: Proposal correction on system artefacts
A8: 46316 | B8: D002 | C8: Mei Ling Chong | D8: M1 | E8: 10 - Documentation | F8: SRS | G8: HLDINSP | H8: HLDINSP | I8: 30 | J8: PR | K8: Minor | L8: No | M8: fix the error found in diagram
A9: 46331 | B9: D003 | C9: Mei Ling Chong | D9: M2 | E9: 50 - Interface | F9: UI / screens | G9: CODEINSP | H9: UT | I9: 60 | J9: PR | K9: Major | L9: No | M9: fix the bug in shopping cart page
A10: 46325 | B10: D004 | C10: Harith Bin Ismail | D10: M2 | E10: 50 - Interface | F10: UI / screens | G10: CODE | H10: CODE | I10: 120 | J10: PR | K10: Major | L10: No | M10: Fix the front-end code for better layout
A11: 46328 | B11: D005 | C11: Harith Bin Ismail | D11: M2 | E11: 80 - Function | F11: Order & catalogue service | G11: CODE | H11: CODE | I11: 80 | J11: PR | K11: Major | L11: No | M11: Fix shopping cart and invoice part
A12: 46315 | B12: D006 | C12: Priya Nair | D12: M1 | E12: 10 - Documentation | F12: SRS | G12: PLAN | H12: REQINSP | I12: 14 | J12: PR | K12: Minor | L12: No | M12: Misunderstanding on the phrase "Joy buyers" in non-functional requirements
A13: 46344 | B13: D007 | C13: Priya Nair | D13: M2 | E13: 80 - Function | F13: Order & catalogue service | G13: CODE | H13: CODEINSP | I13: 30 | J13: PR | K13: Minor | L13: No | M13: Fixed back-end code for user profile for "Edit" function, and any other functions that need fixing
A14: 46345 | B14: D008 | C14: Priya Nair | D14: M2 | E14: 80 - Function | F14: Order & catalogue service | G14: CODE | H14: CODEINSP | I14: 30 | J14: PR | K14: Minor | L14: No | M14: Fixed back-end code for password hashing in "Add Admin" function and "Edit Profile" at Admin side
A15: 46314 | B15: D009 | C15: Harith Bin Ismail | D15: M1 | E15: 10 - Documentation | F15: SYSTEM | G15: REQ | H15: REQINSP | I15: 20 | J15: PR#20 | K15: Minor | L15: No | M15: Order cancellation rule stated twice, in two different ways
A16: 46315 | B16: D010 | C16: Harith Bin Ismail | D16: M1 | E16: 60 - Checking | F16: SYSTEM | G16: REQ | H16: REQINSP | I16: 35 | J16: PR#21 | K16: Major | L16: No | M16: No requirement for what happens when a price changes mid-order
A17: 46316 | B17: D011 | C17: Aisyah Binti Rahman | D17: M1 | E17: 10 - Documentation | F17: SYSTEM | G17: REQ | H17: REQINSP | I17: 15 | J17: PR#22 | K17: Minor | L17: No | M17: Glossary missing 'catch of the day', used throughout section 3
A18: 46317 | B18: D012 | C18: Mei Ling Chong | D18: M1 | E18: 80 - Function | F18: SYSTEM | G18: REQ | H18: REQINSP | I18: 45 | J18: PR#23 | K18: Major | L18: No | M18: Quantity units unspecified - kg or box? Client meant box
... A59: 46365 | B59: D053 | C59: Harith Bin Ismail | D59: M3 | E59: 110 - UI / Layout | F59: UI / screens | G59: CODE | H59: UAT | I59: 15 | J59: PR#64 | K59: Cosmetic | L59: No | M59: Counter staff found the font too small at the till

Sheet LOGTEST
A1: Form LOGTEST - Test Case Log
A2: The evidence behind the Testing & Release rubric. Automated tests still get a row.
A4: Team | B4: =SETUP!$C$10 | E4: Cases | F4: =COUNTA(LOGTEST!$A$7:$A$306) | G4: Passed | H4: =COUNTIF(LOGTEST!$H$7:$H$306,"Pass") | I4: Pass rate | J4: =IF(COUNTA(LOGTEST!$H$7:$H$306)=0,"",COUNTIF(LOGTEST!$H$7:$H$306,"Pass")/COUNTA(LOGTEST!$H$7:$H$306)) | K4: Automated | L4: =COUNTIF(LOGTEST!$L$7:$L$306,"Yes")
A6: Date run | B6: Test ID | C6: Module / Screen | D6: What is being tested | E6: Type | F6: Expected result | G6: Actual result | H6: Status | I6: Milestone | J6: Tester | K6: Defect ref (LOGD) | L6: Automated?
A7: 46342 | B7: TC001 | C7: Order entry screen | D7: Order total sums line amounts correctly | E7: Unit | F7: Total equals sum of line amounts | G7: As expected | H7: Pass | I7: M2 | J7: Aisyah Binti Rahman | L7: Yes
A8: 46343 | B8: TC002 | C8: Catalogue screen | D8: Order total recalculates when a quantity changes | E8: Unit | F8: Total updates immediately | G8: As expected | H8: Pass | I8: M2 | J8: Daniel Wong Jun Hao | L8: Yes
A9: 46344 | B9: TC003 | C9: Invoice & history | D9: Zero-quantity line is rejected | E9: Unit | F9: Validation error shown, line not added | G9: As expected | H9: Pass | I9: M2 | J9: Mei Ling Chong | L9: Yes
A10: 46345 | B10: TC004 | C10: Order & catalogue service | D10: Negative quantity is rejected | E10: Unit | F10: Validation error shown | G10: As expected | H10: Pass | I10: M2 | J10: Harith Bin Ismail | L10: Yes
A11: 46346 | B11: TC005 | C11: Local store & sync | D11: Discount applied after tax | E11: Unit | F11: Invoice total matches the worked example | G11: As expected | H11: Pass | I11: M2 | J11: Priya Nair | L11: Yes
A12: 46347 | B12: TC006 | C12: Shared widgets & theme | D12: Price at order time is used, not latest price | E12: Unit | F12: Historic price returned | G12: As expected | H12: Pass | I12: M2 | J12: Aisyah Binti Rahman | L12: Yes
A13: 46342 | B13: TC007 | C13: Order entry screen | D13: Rounding applied once, on the invoice total | E13: Unit | F13: Total matches to two decimals | G13: As expected | H13: Pass | I13: M2 | J13: Daniel Wong Jun Hao | L13: Yes
A14: 46343 | B14: TC008 | C14: Catalogue screen | D14: Invoice number unique across devices | E14: Unit | F14: No duplicate for 1000 generated ids | G14: As expected | H14: Pass | I14: M2 | J14: Mei Ling Chong | L14: Yes
A15: 46344 | B15: TC009 | C15: Invoice & history | D15: Empty order cannot be submitted | E15: Unit | F15: Submit rejected with a message | G15: As expected | H15: Pass | I15: M2 | J15: Harith Bin Ismail | L15: Yes
A16: 46345 | B16: TC010 | C16: Order & catalogue service | D16: Catalogue filter returns matching items only | E16: Unit | F16: Filtered list matches the query | G16: As expected | H16: Pass | I16: M2 | J16: Priya Nair | L16: Yes
A17: 46346 | B17: TC011 | C17: Local store & sync | D17: Catalogue sorts by name | E17: Unit | F17: Alphabetical order | G17: As expected | H17: Pass | I17: M2 | J17: Aisyah Binti Rahman | L17: Yes
A18: 46347 | B18: TC012 | C18: Shared widgets & theme | D18: Order note parser reads a Malay quantity phrase | E18: Unit | F18: Two lines parsed correctly | G18: As expected | H18: Pass | I18: M2 | J18: Daniel Wong Jun Hao | L18: Yes
... A40: 46359 | B40: TC034 | C40: Order & catalogue service | D40: Removing a line updates the displayed total | E40: Widget | F40: Total decreases correctly | G40: As expected | H40: Pass | I40: M3 | J40: Harith Bin Ismail | L40: Yes
A41: 46360 | B41: TC035 | C41: Local store & sync | D41: Catalogue list scrolls past three hundred items | E41: Widget | F41: No frame drops reported | G41: Still failing - defect raised, fix in progress | H41: Fail | I41: M3 | J41: Priya Nair | K41: PR#64 | L41: Yes
A42: 46361 | B42: TC036 | C42: Shared widgets & theme | D42: Catalogue filter clears when the screen reopens | E42: Widget | F42: Filter field empty | G42: As expected | H42: Pass | I42: M3 | J42: Aisyah Binti Rahman | L42: Yes
A43: 46356 | B43: TC037 | C43: Order entry screen | D43: Long item names do not overflow on a small screen | E43: Widget | F43: No overflow warning | G43: As expected | H43: Pass | I43: M3 | J43: Daniel Wong Jun Hao | L43: Yes
A44: 46357 | B44: TC038 | C44: Catalogue screen | D44: Invoice screen shows the order lines | E44: Widget | F44: All lines visible | G44: As expected | H44: Pass | I44: M3 | J44: Mei Ling Chong | L44: Yes
A45: 46358 | B45: TC039 | C45: Invoice & history | D45: History screen shows the most recent order first | E45: Widget | F45: Order matches expectation | G45: As expected | H45: Pass | I45: M3 | J45: Harith Bin Ismail | L45: Yes
A46: 46359 | B46: TC040 | C46: Order & catalogue service | D46: Offline banner appears when connection is lost | E46: Widget | F46: Banner visible | G46: As expected | H46: Pass | I46: M3 | J46: Priya Nair | L46: Yes
A47: 46360 | B47: TC041 | C47: Local store & sync | D47: Offline banner disappears on reconnect | E47: Widget | F47: Banner removed | G47: As expected | H47: Pass | I47: M3 | J47: Aisyah Binti Rahman | L47: Yes
A48: 46361 | B48: TC042 | C48: Shared widgets & theme | D48: Error dialog is dismissable | E48: Widget | F48: Dialog closes on tap | G48: As expected | H48: Pass | I48: M3 | J48: Daniel Wong Jun Hao | L48: Yes
A49: 46356 | B49: TC043 | C49: Order entry screen | D49: Theme applies the brand colour to the app bar | E49: Widget | F49: Colour matches the design system | G49: As expected | H49: Pass | I49: M3 | J49: Mei Ling Chong | L49: Yes
A50: 46357 | B50: TC044 | C50: Catalogue screen | D50: Font size is readable at the counter device setting | E50: Widget | F50: Text scales as configured | G50: As expected | H50: Pass | I50: M3 | J50: Harith Bin Ismail | L50: Yes
A51: 46358 | B51: TC045 | C51: Invoice & history | D51: Sign-in screen validates the phone format | E51: Widget | F51: Inline error shown | G51: As expected | H51: Pass | I51: M3 | J51: Priya Nair | L51: Yes
A52: 46359 | B52: TC046 | C52: Order & catalogue service | D52: Low-stock badge renders on the catalogue tile | E52: Widget | F52: Badge visible | G52: As expected | H52: Pass | I52: M3 | J52: Aisyah Binti Rahman | L52: Yes
A53: 46367 | B53: TC047 | C53: Local store & sync | D53: Place an order end to end while online | E53: Integration | F53: Order appears in history | G53: As expected | H53: Pass | I53: M3 | J53: Daniel Wong Jun Hao | L53: Yes
A54: 46368 | B54: TC048 | C54: Shared widgets & theme | D54: Place an order offline, then reconnect | E54: Integration | F54: Order syncs once, no duplicate | G54: Still failing - defect raised, fix in progress | H54: Fail | I54: M3 | J54: Mei Ling Chong | K54: PR#77 | L54: Yes
A55: 46363 | B55: TC049 | C55: Order entry screen | D55: Generate and open an invoice PDF | E55: Integration | F55: PDF opens with correct totals | G55: As expected | H55: Pass | I55: M3 | J55: Harith Bin Ismail | L55: Yes
A56: 46364 | B56: TC050 | C56: Catalogue screen | D56: Sign in, place an order, sign out | E56: Integration | F56: Session cleared, order retained | G56: As expected | H56: Pass | I56: M3 | J56: Priya Nair | L56: Yes
A57: 46365 | B57: TC051 | C57: Invoice & history | D57: Catalogue updates propagate to an open screen | E57: Integration | F57: List refreshes without restart | G57: As expected | H57: Pass | I57: M3 | J57: Aisyah Binti Rahman | L57: Yes
A58: 46366 | B58: TC052 | C58: Order & catalogue service | D58: Connection flaps repeatedly during a sync | E58: Integration | F58: Queue drains exactly once | G58: As expected | H58: Pass | I58: M3 | J58: Daniel Wong Jun Hao | L58: Yes
A59: 46367 | B59: TC053 | C59: Local store & sync | D59: Counter staff place a real order unaided | E59: Acceptance | F59: Order completed in under 3 minutes | G59: As expected | H59: Pass | I59: M3 | J59: Mei Ling Chong | L59: No
A60: 46368 | B60: TC054 | C60: Shared widgets & theme | D60: Counter staff find yesterday's order | E60: Acceptance | F60: Order located without help | G60: As expected | H60: Pass | I60: M3 | J60: Harith Bin Ismail | L60: No

Sheet LOGAI
A1: Form LOGAI - AI-Assisted Development Log
A2: Every change where a generator wrote code that reached the repository. No entry, no merge.
A4: Team | B4: =SETUP!$C$10 | D4: Entries | E4: =COUNTA(LOGAI!$A$7:$A$256) | F4: Approved | G4: =COUNTIF(LOGAI!$P$7:$P$256,"Yes") | H4: Lines generated | I4: =SUM(LOGAI!$H$7:$H$256) | K4: Lines kept after review | M4: =SUM(LOGAI!$I$7:$I$256) | N4: Keep rate | P4: =IF(SUM(LOGAI!$H$7:$H$256)=0,"",SUM(LOGAI!$I$7:$I$256)/SUM(LOGAI!$H$7:$H$256))
A6: Date | B6: Member | C6: Milestone | D6: File / module | E6: Feature or behaviour | F6: AI tool | G6: Prompt (summarised) | H6: Lines gen. | I6: Lines kept | J6: Keep % | K6: Reviewer | L6: Review verdict | M6: Tests written? | N6: Test status | O6: Commit / PR ref | P6: Approved?
A7: 46322 | B7: Priya Nair | C7: M2 | D7: order_form.dart | E7: Form validation for quantity and item fields | F7: GitHub Copilot | G7: Validate quantity is a positive integer and item is selected; return a message per field | H7: 60 | I7: 45 | J7: =IF(N($H7)=0,"",$I7/$H7) | K7: Daniel Wong Jun Hao | L7: Approved with changes | M7: Yes | N7: Pass | O7: PR#21 | P7: Yes
A8: 46323 | B8: Priya Nair | C8: M2 | D8: catalogue_list.dart | E8: ListView.builder with lazy loading | F8: GitHub Copilot | G8: Build a lazy list of catalogue items with a low-stock badge | H8: 40 | I8: 34 | J8: =IF(N($H8)=0,"",$I8/$H8) | K8: Mei Ling Chong | L8: Approved | M8: Yes | N8: Pass | O8: PR#22 | P8: Yes
A9: 46331 | B9: Aisyah Binti Rahman | C9: M2 | D9: .github/workflows/ci.yml | E9: GitHub Actions workflow | F9: Claude | G9: Workflow that runs flutter analyze, flutter test and uploads a coverage report | H9: 55 | I9: 50 | J9: =IF(N($H9)=0,"",$I9/$H9) | K9: Mei Ling Chong | L9: Approved with changes | M9: No | N9: Not run | O9: PR#23 | P9: Yes
A10: 46332 | B10: Daniel Wong Jun Hao | C10: M2 | D10: price_repository.dart | E10: Dated price lookup | F10: GitHub Copilot | G10: Return the price effective on a given date from a list of dated price records | H10: 45 | I10: 28 | J10: =IF(N($H10)=0,"",$I10/$H10) | K10: Harith Bin Ismail | L10: Changes requested | M10: Yes | N10: Pass | O10: PR#24 | P10: Yes
A11: 46333 | B11: Daniel Wong Jun Hao | C11: M2 | D11: note_parser.dart | E11: Gemini order-note parser wrapper | F11: Google Gemini | G11: Parse a free-text order note into item and quantity pairs; handle Malay and English | H11: 90 | I11: 62 | J11: =IF(N($H11)=0,"",$I11/$H11) | K11: Priya Nair | L11: Approved with changes | M11: Yes | N11: Pass | O11: PR#25 | P11: Yes
A12: 46342 | B12: Priya Nair | C12: M2 | D12: invoice_view.dart | E12: Invoice layout widget | F12: GitHub Copilot | G12: Lay out order lines, subtotal, tax and total in a printable column | H12: 50 | I12: 41 | J12: =IF(N($H12)=0,"",$I12/$H12) | K12: Mei Ling Chong | L12: Approved | M12: Yes | N12: Pass | O12: PR#26 | P12: Yes
A13: 46343 | B13: Mei Ling Chong | C13: M2 | D13: write_queue.dart | E13: Offline write-queue scaffolding | F13: Claude | G13: A queue that persists pending writes and drains them once when connectivity returns | H13: 75 | I13: 58 | J13: =IF(N($H13)=0,"",$I13/$H13) | K13: Daniel Wong Jun Hao | L13: Approved with changes | M13: Yes | N13: Pass | O13: PR#27 | P13: Yes
A14: 46344 | B14: Mei Ling Chong | C14: M2 | D14: app_theme.dart | E14: Material 3 theme from the brand colours | F14: GitHub Copilot | G14: Build a Material 3 ColorScheme from a seed colour and define text styles | H14: 35 | I14: 33 | J14: =IF(N($H14)=0,"",$I14/$H14) | K14: Priya Nair | L14: Approved | M14: No | N14: Not run | O14: PR#28 | P14: Yes
A15: 46345 | B15: Harith Bin Ismail | C15: M2 | D15: invoice_number.dart | E15: Device-safe invoice numbering | F15: Claude | G15: Generate invoice numbers unique across devices without a central server | H15: 40 | I15: 30 | J15: =IF(N($H15)=0,"",$I15/$H15) | K15: Aisyah Binti Rahman | L15: Approved with changes | M15: Yes | N15: Pass | O15: PR#29 | P15: Yes
A16: 46346 | B16: Priya Nair | C16: M2 | D16: order_form.dart | E16: Double-submit guard | F16: GitHub Copilot | G16: Prevent a second submit while the first is still in flight | H16: 20 | I16: 18 | J16: =IF(N($H16)=0,"",$I16/$H16) | K16: Mei Ling Chong | L16: Approved | M16: Yes | N16: Pass | O16: PR#30 | P16: Yes
A17: 46354 | B17: Mei Ling Chong | C17: M3 | D17: sync_service.dart | E17: Retry with exponential backoff | F17: GitHub Copilot | G17: Retry a failed sync with exponential backoff and a maximum attempt count | H17: 45 | I17: 36 | J17: =IF(N($H17)=0,"",$I17/$H17) | K17: Daniel Wong Jun Hao | L17: Approved | M17: Yes | N17: Pass | O17: PR#31 | P17: Yes
A18: 46356 | B18: Daniel Wong Jun Hao | C18: M3 | D18: stock_rules.dart | E18: Low-stock threshold rules | F18: GitHub Copilot | G18: Flag an item as low stock based on a per-item threshold | H18: 25 | I18: 22 | J18: =IF(N($H18)=0,"",$I18/$H18) | K18: Harith Bin Ismail | L18: Approved | M18: Yes | N18: Pass | O18: PR#32 | P18: Yes
... A22: 46367 | B22: Priya Nair | C22: M3 | D22: catalogue_list.dart | E22: Performance fix for long lists | F22: GitHub Copilot | G22: Reduce rebuilds in a long list by adding keys and a const item widget | H22: 30 | I22: 26 | J22: =IF(N($H22)=0,"",$I22/$H22) | K22: Daniel Wong Jun Hao | L22: Approved | M22: Yes | N22: Pass | O22: PR#36 | P22: Yes
J23: =IF(N($H23)=0,"",$I23/$H23)
J24: =IF(N($H24)=0,"",$I24/$H24)
J25: =IF(N($H25)=0,"",$I25/$H25)
J26: =IF(N($H26)=0,"",$I26/$H26)
J27: =IF(N($H27)=0,"",$I27/$H27)
J28: =IF(N($H28)=0,"",$I28/$H28)
J29: =IF(N($H29)=0,"",$I29/$H29)
J30: =IF(N($H30)=0,"",$I30/$H30)
J31: =IF(N($H31)=0,"",$I31/$H31)
J32: =IF(N($H32)=0,"",$I32/$H32)
J33: =IF(N($H33)=0,"",$I33/$H33)
J34: =IF(N($H34)=0,"",$I34/$H34)
... J256: =IF(N($H256)=0,"",$I256/$H256)

Sheet LOGCLIENT
A1: Form LOGCLIENT - Client Engagement Log
A2: Proof of the client relationship. M1 needs 2 meetings, M2 needs 4, M3 needs 6 - cumulative.
A4: Client | B4: =SETUP!$C$12 | F4: Meetings held | G4: =COUNTA(LOGCLIENT!$A$7:$A$46) | H4: Face-to-face | I4: =COUNTIF(LOGCLIENT!$C$7:$C$46,"Face-to-face") | J4: Total hours | K4: =SUM(LOGCLIENT!$D$7:$D$46)
A6: Date | B6: Milestone | C6: Mode | D6: Hours | E6: Team attendees | F6: Client attendees | G6: Purpose / agenda | H6: Decisions made | I6: Action items & owners | J6: Evidence (minutes / photo link) | K6: Client sign-off?
A7: 46305 | B7: M1 | C7: Face-to-face | D7: 1.5 | E7: All five | F7: Encik Faizal, counter supervisor | G7: First visit: watch how orders are taken on paper today | H7: Scope limited to ordering and invoicing; stock control is out of scope for this semester | I7: Harith to draft the user stories by Friday; Aisyah to send the project brief | J7: Photos + notes in docs/meetings/m01.md | K7: No
A8: 46319 | B8: M1 | C8: Face-to-face | D8: 2 | E8: Harith, Aisyah, Priya | F8: Encik Faizal | G8: Walk through the paper mock-ups of the order screen | H8: Order lines must allow a free-text note; quantity is by box, not kg | I8: Priya to redraw the order screen; Mei Ling to update the SRS | J8: Signed mock-up sheets, photographed | K8: Yes
A9: 46333 | B9: M2 | C9: Online (Zoom/Meet) | D9: 1 | E9: Harith, Daniel | F9: Encik Faizal | G9: Review the SRS section on pricing | H9: Prices change weekly - the app must keep the price at order time | I9: Daniel to change the data model to dated prices; raise a CCR | J9: docs/meetings/m03.md | K9: No
A10: 46347 | B10: M2 | C10: Face-to-face | D10: 2 | E10: All five | F10: Encik Faizal, two counter staff | G10: Demonstrate the prototype on a real device | H10: Staff asked for a bigger font; confirmed the offline requirement is real, the shop loses signal daily | I10: Priya to raise the font issue; Mei Ling to prioritise the offline queue | J10: Video of the session | K10: Yes
A11: 46361 | B11: M3 | C11: Face-to-face | D11: 1.5 | E11: Harith, Mei Ling, Daniel | F11: Encik Faizal | G11: Review invoice layout and the order history screen | H11: Invoice must show the shop name and SSM number; history only needs 30 days | I11: Harith to update the invoice template | J11: docs/meetings/m05.md | K11: No
A12: 46368 | B12: M3 | C12: Face-to-face | D12: 2.5 | E12: All five | F12: Encik Faizal, two counter staff | G12: Acceptance test: staff place real orders unaided | H12: Accepted with one cosmetic change (font size at the till) | I12: Priya to ship the font fix before handover | J12: Signed acceptance sheet | K12: Yes
A13: 46389 | B13: M4 | C13: Face-to-face | D13: 2 | E13: All five | F13: Encik Faizal, two counter staff | G13: Handover: install the release build, train two staff, leave the quick card | H13: Client signed off; agreed to a follow-up call in two weeks | I13: Aisyah to send the repository link and the manual | J13: Signed handover form | K13: Yes

Sheet LOGGIT
A1: Form LOGGIT - GitHub Activity Log
A2: Recorded weekly from the repository's Insights tab. These are facts, not estimates.
A4: Repository | C4: =SETUP!$C$14 | F4: Commits | G4: =SUM(LOGGIT!$D$7:$D$86) | H4: PRs merged | I4: =SUM(LOGGIT!$F$7:$F$86) | J4: Reviews | K4: =SUM(LOGGIT!$G$7:$G$86)
A6: Week | B6: Milestone | C6: Member | D6: Commits | E6: PRs opened | F6: PRs merged | G6: Reviews given | H6: Issues closed | I6: Lines + | J6: Lines - | K6: CI green? | L6: Notes
A7: 3 | B7: M1 | C7: Aisyah Binti Rahman | D7: 1 | E7: 0 | F7: 0 | G7: 0 | H7: 0 | I7: 42 | J7: 11 | K7: Yes
A8: 3 | B8: M1 | C8: Daniel Wong Jun Hao | D8: 1 | E8: 0 | F8: 0 | G8: 0 | H8: 0 | I8: 42 | J8: 11 | K8: Yes
A9: 3 | B9: M1 | C9: Mei Ling Chong | D9: 2 | E9: 0 | F9: 0 | G9: 1 | H9: 0 | I9: 84 | J9: 22 | K9: Yes
A10: 3 | B10: M1 | C10: Harith Bin Ismail | D10: 3 | E10: 1 | F10: 1 | G10: 1 | H10: 1 | I10: 126 | J10: 33 | K10: Yes
A11: 3 | B11: M1 | C11: Priya Nair | D11: 1 | E11: 0 | F11: 0 | G11: 0 | H11: 0 | I11: 42 | J11: 11 | K11: Yes
A12: 4 | B12: M1 | C12: Aisyah Binti Rahman | D12: 1 | E12: 0 | F12: 0 | G12: 0 | H12: 0 | I12: 42 | J12: 11 | K12: Yes
A13: 4 | B13: M1 | C13: Daniel Wong Jun Hao | D13: 1 | E13: 0 | F13: 0 | G13: 0 | H13: 0 | I13: 42 | J13: 11 | K13: Yes
A14: 4 | B14: M1 | C14: Mei Ling Chong | D14: 2 | E14: 0 | F14: 0 | G14: 1 | H14: 0 | I14: 84 | J14: 22 | K14: Yes
A15: 4 | B15: M1 | C15: Harith Bin Ismail | D15: 4 | E15: 1 | F15: 1 | G15: 1 | H15: 1 | I15: 168 | J15: 44 | K15: Yes
A16: 4 | B16: M1 | C16: Priya Nair | D16: 1 | E16: 0 | F16: 0 | G16: 0 | H16: 0 | I16: 42 | J16: 11 | K16: Yes
A17: 5 | B17: M1 | C17: Aisyah Binti Rahman | D17: 1 | E17: 0 | F17: 0 | G17: 0 | H17: 0 | I17: 42 | J17: 11 | K17: Yes
A18: 5 | B18: M1 | C18: Daniel Wong Jun Hao | D18: 1 | E18: 0 | F18: 0 | G18: 0 | H18: 0 | I18: 42 | J18: 11 | K18: Yes
... A31: 7 | B31: M2 | C31: Priya Nair | D31: 2 | E31: 0 | F31: 0 | G31: 1 | H31: 0 | I31: 84 | J31: 22 | K31: Yes
A32: 9 | B32: M2 | C32: Aisyah Binti Rahman | D32: 2 | E32: 0 | F32: 0 | G32: 1 | H32: 0 | I32: 84 | J32: 22 | K32: No | L32: CI red for two days - intl version conflict, fixed in PR#27
A33: 9 | B33: M2 | C33: Daniel Wong Jun Hao | D33: 1 | E33: 0 | F33: 0 | G33: 0 | H33: 0 | I33: 42 | J33: 11 | K33: No
A34: 9 | B34: M2 | C34: Mei Ling Chong | D34: 4 | E34: 1 | F34: 1 | G34: 1 | H34: 1 | I34: 168 | J34: 44 | K34: No
A35: 9 | B35: M2 | C35: Harith Bin Ismail | D35: 7 | E35: 2 | F35: 1 | G35: 2 | H35: 2 | I35: 294 | J35: 77 | K35: No
A36: 9 | B36: M2 | C36: Priya Nair | D36: 2 | E36: 0 | F36: 0 | G36: 1 | H36: 0 | I36: 84 | J36: 22 | K36: No
A37: 10 | B37: M3 | C37: Aisyah Binti Rahman | D37: 2 | E37: 0 | F37: 0 | G37: 1 | H37: 0 | I37: 84 | J37: 22 | K37: Yes
A38: 10 | B38: M3 | C38: Daniel Wong Jun Hao | D38: 1 | E38: 0 | F38: 0 | G38: 0 | H38: 0 | I38: 42 | J38: 11 | K38: Yes
A39: 10 | B39: M3 | C39: Mei Ling Chong | D39: 4 | E39: 1 | F39: 1 | G39: 1 | H39: 1 | I39: 168 | J39: 44 | K39: Yes
A40: 10 | B40: M3 | C40: Harith Bin Ismail | D40: 7 | E40: 2 | F40: 1 | G40: 2 | H40: 2 | I40: 294 | J40: 77 | K40: Yes
A41: 10 | B41: M3 | C41: Priya Nair | D41: 2 | E41: 0 | F41: 0 | G41: 1 | H41: 0 | I41: 84 | J41: 22 | K41: Yes
A42: 11 | B42: M3 | C42: Aisyah Binti Rahman | D42: 2 | E42: 0 | F42: 0 | G42: 1 | H42: 0 | I42: 84 | J42: 22 | K42: Yes
A43: 11 | B43: M3 | C43: Daniel Wong Jun Hao | D43: 1 | E43: 0 | F43: 0 | G43: 0 | H43: 0 | I43: 42 | J43: 11 | K43: Yes
A44: 11 | B44: M3 | C44: Mei Ling Chong | D44: 4 | E44: 1 | F44: 1 | G44: 1 | H44: 1 | I44: 168 | J44: 44 | K44: Yes
... A51: 12 | B51: M3 | C51: Priya Nair | D51: 1 | E51: 0 | F51: 0 | G51: 0 | H51: 0 | I51: 42 | J51: 11 | K51: Yes

Sheet WEEK
A1: Form WEEK - Weekly Status Report
A2: Filled in at the weekly team meeting. This is the record the instructor and demonstrator read.
A4: Team | B4: =SETUP!$C$10 | F4: Meetings held | G4: =COUNTIF(D8:D20,"Yes")
A7: Week | B7: Week starting | C7: M/stone | D7: Met? | E7: Present | F7: Plan hrs | G7: Actual hrs | H7: Act/Plan | I7: Cum PV | J7: Cum EV | K7: EV variance | L7: Status | M7: Biggest risk or issue this week | N7: Commitment for next week
A8: 3 | B8: 46300 | C8: M1 | D8: Yes | E8: 5 | F8: =SCHEDULE!$C$8 | G8: =SCHEDULE!$E$8 | H8: =IF(N($F8)=0,"",$G8/$F8) | I8: =SCHEDULE!$H$8 | J8: =SCHEDULE!$J$8 | K8: =SCHEDULE!$K$8 | L8: =IF($A8>MAX(IF(LOGT!$D$7:$D$406<>"",LOGT!$D$7:$D$406)),"",IF($K8<-0.1,"BEHIND",IF($K8<-0.02,"AT RISK","ON TRACK"))) | M8: Client not yet confirmed - no signed approval form | N8: Submit the client approval form and open the repo
A9: 4 | B9: 46307 | C9: M1 | D9: Yes | E9: 5 | F9: =SCHEDULE!$C$9 | G9: =SCHEDULE!$E$9 | H9: =IF(N($F9)=0,"",$G9/$F9) | I9: =SCHEDULE!$H$9 | J9: =SCHEDULE!$J$9 | K9: =SCHEDULE!$K$9 | L9: =IF($A9>MAX(IF(LOGT!$D$7:$D$406<>"",LOGT!$D$7:$D$406)),"",IF($K9<-0.1,"BEHIND",IF($K9<-0.02,"AT RISK","ON TRACK"))) | M9: Requirements still vague on pricing | N9: Finish the SRS draft and book the mock-up review
A10: 5 | B10: 46314 | C10: M1 | D10: Yes | E10: 5 | F10: =SCHEDULE!$C$10 | G10: =SCHEDULE!$E$10 | H10: =IF(N($F10)=0,"",$G10/$F10) | I10: =SCHEDULE!$H$10 | J10: =SCHEDULE!$J$10 | K10: =SCHEDULE!$K$10 | L10: =IF($A10>MAX(IF(LOGT!$D$7:$D$406<>"",LOGT!$D$7:$D$406)),"",IF($K10<-0.1,"BEHIND",IF($K10<-0.02,"AT RISK","ON TRACK"))) | M10: M1 due Saturday; SRS inspection not scheduled yet | N10: Submit M1: proposal, SRS, charter, repo
A11: 6 | B11: 46321 | C11: M2 | D11: Yes | E11: 4 | F11: =SCHEDULE!$C$11 | G11: =SCHEDULE!$E$11 | H11: =IF(N($F11)=0,"",$G11/$F11) | I11: =SCHEDULE!$H$11 | J11: =SCHEDULE!$J$11 | K11: =SCHEDULE!$K$11 | L11: =IF($A11>MAX(IF(LOGT!$D$7:$D$406<>"",LOGT!$D$7:$D$406)),"",IF($K11<-0.1,"BEHIND",IF($K11<-0.02,"AT RISK","ON TRACK"))) | M11: Daniel missed two sessions - no commits this week | N11: Daniel to pick up the price repository and report Wednesday
A12: 7 | B12: 46328 | C12: M2 | D12: Yes | E12: 5 | F12: =SCHEDULE!$C$12 | G12: =SCHEDULE!$E$12 | H12: =IF(N($F12)=0,"",$G12/$F12) | I12: =SCHEDULE!$H$12 | J12: =SCHEDULE!$J$12 | K12: =SCHEDULE!$K$12 | L12: =IF($A12>MAX(IF(LOGT!$D$7:$D$406<>"",LOGT!$D$7:$D$406)),"",IF($K12<-0.1,"BEHIND",IF($K12<-0.02,"AT RISK","ON TRACK"))) | M12: Dated-price change may not fit before M2 | N12: Finish the order screen and the catalogue service
A13: 8 | B13: 46335 | C13: M2 | D13: No | E13: 0 | F13: =SCHEDULE!$C$13 | G13: =SCHEDULE!$E$13 | H13: =IF(N($F13)=0,"",$G13/$F13) | I13: =SCHEDULE!$H$13 | J13: =SCHEDULE!$J$13 | K13: =SCHEDULE!$K$13 | L13: =IF($A13>MAX(IF(LOGT!$D$7:$D$406<>"",LOGT!$D$7:$D$406)),"",IF($K13<-0.1,"BEHIND",IF($K13<-0.02,"AT RISK","ON TRACK"))) | M13: Mid-semester break - no work planned | N13: Resume Wednesday of week 9
A14: 9 | B14: 46342 | C14: M2 | D14: Yes | E14: 5 | F14: =SCHEDULE!$C$14 | G14: =SCHEDULE!$E$14 | H14: =IF(N($F14)=0,"",$G14/$F14) | I14: =SCHEDULE!$H$14 | J14: =SCHEDULE!$J$14 | K14: =SCHEDULE!$K$14 | L14: =IF($A14>MAX(IF(LOGT!$D$7:$D$406<>"",LOGT!$D$7:$D$406)),"",IF($K14<-0.1,"BEHIND",IF($K14<-0.02,"AT RISK","ON TRACK"))) | M14: CI red for two days; contribution is very uneven | N14: Submit M2; Aisyah to fix CI; raise contribution at the meeting
A15: 10 | B15: 46349 | C15: M3 | D15: Yes | E15: 5 | F15: =SCHEDULE!$C$15 | G15: =SCHEDULE!$E$15 | H15: =IF(N($F15)=0,"",$G15/$F15) | I15: =SCHEDULE!$H$15 | J15: =SCHEDULE!$J$15 | K15: =SCHEDULE!$K$15 | L15: =IF($A15>MAX(IF(LOGT!$D$7:$D$406<>"",LOGT!$D$7:$D$406)),"",IF($K15<-0.1,"BEHIND",IF($K15<-0.02,"AT RISK","ON TRACK"))) | M15: Harith is carrying far too much of the work | N15: Redistribute the sync tasks; Mei Ling takes the widget tests
A16: 11 | B16: 46356 | C16: M3 | D16: Yes | E16: 5 | F16: =SCHEDULE!$C$16 | G16: =SCHEDULE!$E$16 | H16: =IF(N($F16)=0,"",$G16/$F16) | I16: =SCHEDULE!$H$16 | J16: =SCHEDULE!$J$16 | K16: =SCHEDULE!$K$16 | L16: =IF($A16>MAX(IF(LOGT!$D$7:$D$406<>"",LOGT!$D$7:$D$406)),"",IF($K16<-0.1,"BEHIND",IF($K16<-0.02,"AT RISK","ON TRACK"))) | M16: Coverage at 58%, below the 60% floor | N16: Add tests for the write queue and the price repository
A17: 12 | B17: 46363 | C17: M3 | D17: Yes | E17: 5 | F17: =SCHEDULE!$C$17 | G17: =SCHEDULE!$E$17 | H17: =IF(N($F17)=0,"",$G17/$F17) | I17: =SCHEDULE!$H$17 | J17: =SCHEDULE!$J$17 | K17: =SCHEDULE!$K$17 | L17: =IF($A17>MAX(IF(LOGT!$D$7:$D$406<>"",LOGT!$D$7:$D$406)),"",IF($K17<-0.1,"BEHIND",IF($K17<-0.02,"AT RISK","ON TRACK"))) | M17: Acceptance test revealed a font size issue | N17: Fix the font, finish system test, prepare M3
A18: 13 | B18: 46370 | C18: M3 | D18: Yes | E18: 5 | F18: =SCHEDULE!$C$18 | G18: =SCHEDULE!$E$18 | H18: =IF(N($F18)=0,"",$G18/$F18) | I18: =SCHEDULE!$H$18 | J18: =SCHEDULE!$J$18 | K18: =SCHEDULE!$K$18 | L18: =IF($A18>MAX(IF(LOGT!$D$7:$D$406<>"",LOGT!$D$7:$D$406)),"",IF($K18<-0.1,"BEHIND",IF($K18<-0.02,"AT RISK","ON TRACK"))) | M18: None - M3 submitted on time | N18: Start the final report and the demo video
A19: 14 | B19: 46377 | C19: M4 | D19: Yes | E19: 5 | F19: =SCHEDULE!$C$19 | G19: =SCHEDULE!$E$19 | H19: =IF(N($F19)=0,"",$G19/$F19) | I19: =SCHEDULE!$H$19 | J19: =SCHEDULE!$J$19 | K19: =SCHEDULE!$K$19 | L19: =IF($A19>MAX(IF(LOGT!$D$7:$D$406<>"",LOGT!$D$7:$D$406)),"",IF($K19<-0.1,"BEHIND",IF($K19<-0.02,"AT RISK","ON TRACK"))) | M19: Demo video not started | N19: Record the demo and rehearse the presentation
A20: 15 | B20: 46384 | C20: M4 | D20: Yes | E20: 5 | F20: =SCHEDULE!$C$20 | G20: =SCHEDULE!$E$20 | H20: =IF(N($F20)=0,"",$G20/$F20) | I20: =SCHEDULE!$H$20 | J20: =SCHEDULE!$J$20 | K20: =SCHEDULE!$K$20 | L20: =IF($A20>MAX(IF(LOGT!$D$7:$D$406<>"",LOGT!$D$7:$D$406)),"",IF($K20<-0.1,"BEHIND",IF($K20<-0.02,"AT RISK","ON TRACK"))) | M20: None - handover complete | N20: Submit M4 and close the repository at v1.0.0

Sheet IRTL
A1: Form IRTL - Issue & Risk Tracking Log
A2: A risk might happen; an issue already has. Both need an owner and a date, or they are just worry.
A4: Team | B4: =SETUP!$C$10 | E4: Open | F4: =COUNTIFS(L7:L46,"<>Complete",A7:A46,"<>") | G4: High priority | H4: =COUNTIFS(H7:H46,">=6",L7:L46,"<>Complete")
A6: ID | B6: Date raised | C6: Type | D6: Scope | E6: Description | F6: Likelihood | G6: Impact | H6: Priority | I6: Owner | J6: Mitigation / action taken | K6: Follow-up | L6: Status | M6: Date closed
A7: R01 | B7: 46302 | C7: Risk | D7: Client | E7: SeaFresh may not sign the client approval form in time | F7: Medium | G7: High | H7: =IF(OR($F7="",$G7=""),"",(IF($F7="High",3,IF($F7="Medium",2,1)))*(IF($G7="High",3,IF($G7="Medium",2,1)))) | I7: Harith Bin Ismail | J7: Visited the shop twice in week 3; form signed on 10 Oct | K7: 46316 | L7: Complete | M7: 46318
A8: R02 | B8: 46309 | C8: Risk | D8: Technical | E8: The shop loses signal daily; orders could be lost mid-entry | F8: High | G8: High | H8: =IF(OR($F8="",$G8=""),"",(IF($F8="High",3,IF($F8="Medium",2,1)))*(IF($G8="High",3,IF($G8="Medium",2,1)))) | I8: Mei Ling Chong | J8: Offline-first write queue built in M2; integration test simulates loss of connection | K8: 46358 | L8: Complete | M8: 46360
A9: I01 | B9: 46323 | C9: Issue | D9: Team | E9: Daniel logged no hours and no commits in week 6 | F9: High | G9: Medium | H9: =IF(OR($F9="",$G9=""),"",(IF($F9="High",3,IF($F9="Medium",2,1)))*(IF($G9="High",3,IF($G9="Medium",2,1)))) | I9: Aisyah Binti Rahman | J9: Raised at the week 6 meeting; Daniel took the price repository and reported weekly after | K9: 46344 | L9: Complete | M9: 46346
A10: I02 | B10: 46330 | C10: Issue | D10: Client | E10: Prices change weekly - the data model assumed they were static | F10: High | G10: High | H10: =IF(OR($F10="",$G10=""),"",(IF($F10="High",3,IF($F10="Medium",2,1)))*(IF($G10="High",3,IF($G10="Medium",2,1)))) | I10: Daniel Wong Jun Hao | J10: CCR-02 raised and approved; model changed to dated price records | K10: 46344 | L10: Complete | M10: 46346
A11: R03 | B11: 46344 | C11: Risk | D11: Technical | E11: Gemini API cost and latency unknown at the shop's connection speed | F11: Medium | G11: Medium | H11: =IF(OR($F11="",$G11=""),"",(IF($F11="High",3,IF($F11="Medium",2,1)))*(IF($G11="High",3,IF($G11="Medium",2,1)))) | I11: Priya Nair | J11: Measured over a week; parser made optional with a manual fallback | K11: 46358 | L11: Complete | M11: 46360
A12: I03 | B12: 46344 | C12: Issue | D12: Team | E12: Work is very unevenly shared - one member has logged 45% of all hours | F12: High | G12: High | H12: =IF(OR($F12="",$G12=""),"",(IF($F12="High",3,IF($F12="Medium",2,1)))*(IF($G12="High",3,IF($G12="Medium",2,1)))) | I12: Aisyah Binti Rahman | J12: Tasks redistributed in week 10; still uneven at M3, reported honestly in the peer evaluation | K12: 46372 | L12: In progress
A13: I04 | B13: 46344 | C13: Issue | D13: Technical | E13: CI red for two days after an intl version conflict | F13: Medium | G13: Medium | H13: =IF(OR($F13="",$G13=""),"",(IF($F13="High",3,IF($F13="Medium",2,1)))*(IF($G13="High",3,IF($G13="Medium",2,1)))) | I13: Aisyah Binti Rahman | J13: Dependency pinned; a weekly dependency check added to the workflow | K13: 46351 | L13: Complete | M13: 46353
A14: R04 | B14: 46358 | C14: Risk | D14: Project | E14: Coverage below the 60% floor with two weeks to M3 | F14: Medium | G14: High | H14: =IF(OR($F14="",$G14=""),"",(IF($F14="High",3,IF($F14="Medium",2,1)))*(IF($G14="High",3,IF($G14="Medium",2,1)))) | I14: Mei Ling Chong | J14: Mei Ling took the widget tests; coverage reached 64% by week 12 | K14: 46365 | L14: Complete | M14: 46367
A15: R05 | B15: 46372 | C15: Risk | D15: Client | E15: Counter staff may not adopt the app after handover | F15: Medium | G15: High | H15: =IF(OR($F15="",$G15=""),"",(IF($F15="High",3,IF($F15="Medium",2,1)))*(IF($G15="High",3,IF($G15="Medium",2,1)))) | I15: Harith Bin Ismail | J15: Two staff trained in person at handover; one-page card left at the till | K15: 46386 | L15: Complete | M15: 46388
H16: =IF(OR($F16="",$G16=""),"",(IF($F16="High",3,IF($F16="Medium",2,1)))*(IF($G16="High",3,IF($G16="Medium",2,1))))
H17: =IF(OR($F17="",$G17=""),"",(IF($F17="High",3,IF($F17="Medium",2,1)))*(IF($G17="High",3,IF($G17="Medium",2,1))))
H18: =IF(OR($F18="",$G18=""),"",(IF($F18="High",3,IF($F18="Medium",2,1)))*(IF($G18="High",3,IF($G18="Medium",2,1))))
H19: =IF(OR($F19="",$G19=""),"",(IF($F19="High",3,IF($F19="Medium",2,1)))*(IF($G19="High",3,IF($G19="Medium",2,1))))
H20: =IF(OR($F20="",$G20=""),"",(IF($F20="High",3,IF($F20="Medium",2,1)))*(IF($G20="High",3,IF($G20="Medium",2,1))))
H21: =IF(OR($F21="",$G21=""),"",(IF($F21="High",3,IF($F21="Medium",2,1)))*(IF($G21="High",3,IF($G21="Medium",2,1))))
H22: =IF(OR($F22="",$G22=""),"",(IF($F22="High",3,IF($F22="Medium",2,1)))*(IF($G22="High",3,IF($G22="Medium",2,1))))
H23: =IF(OR($F23="",$G23=""),"",(IF($F23="High",3,IF($F23="Medium",2,1)))*(IF($G23="High",3,IF($G23="Medium",2,1))))
H24: =IF(OR($F24="",$G24=""),"",(IF($F24="High",3,IF($F24="Medium",2,1)))*(IF($G24="High",3,IF($G24="Medium",2,1))))
H25: =IF(OR($F25="",$G25=""),"",(IF($F25="High",3,IF($F25="Medium",2,1)))*(IF($G25="High",3,IF($G25="Medium",2,1))))
H26: =IF(OR($F26="",$G26=""),"",(IF($F26="High",3,IF($F26="Medium",2,1)))*(IF($G26="High",3,IF($G26="Medium",2,1))))
H27: =IF(OR($F27="",$G27=""),"",(IF($F27="High",3,IF($F27="Medium",2,1)))*(IF($G27="High",3,IF($G27="Medium",2,1))))
... H46: =IF(OR($F46="",$G46=""),"",(IF($F46="High",3,IF($F46="Medium",2,1)))*(IF($G46="High",3,IF($G46="Medium",2,1))))

Sheet IRWEEK
A1: Issue & Risk Week Summary
A2: How the risk picture moved each week. Calculated from IRTL - the comment column is yours.
A5: Week | B5: Week starting | C5: Raised | D5: Closed | E5: Open at end | F5: High priority open | G5: Risks open | H5: Issues open | I5: What the team did about it this week
A6: 3 | B6: 46300 | C6: =COUNTIFS(IRTL!$B$7:$B$46,">="&$B6,IRTL!$B$7:$B$46,"<="&$B6+6) | D6: =COUNTIFS(IRTL!$M$7:$M$46,">="&$B6,IRTL!$M$7:$M$46,"<="&$B6+6) | E6: =COUNTIFS(IRTL!$B$7:$B$46,"<="&$B6+6)-COUNTIFS(IRTL!$M$7:$M$46,"<="&$B6+6,IRTL!$M$7:$M$46,"<>") | F6: =COUNTIFS(IRTL!$B$7:$B$46,"<="&$B6+6,IRTL!$H$7:$H$46,">=6")-COUNTIFS(IRTL!$M$7:$M$46,"<="&$B6+6,IRTL!$M$7:$M$46,"<>",IRTL!$H$7:$H$46,">=6") | G6: =COUNTIFS(IRTL!$B$7:$B$46,"<="&$B6+6,IRTL!$C$7:$C$46,"Risk")-COUNTIFS(IRTL!$M$7:$M$46,"<="&$B6+6,IRTL!$M$7:$M$46,"<>",IRTL!$C$7:$C$46,"Risk") | H6: =COUNTIFS(IRTL!$B$7:$B$46,"<="&$B6+6,IRTL!$C$7:$C$46,"Issue")-COUNTIFS(IRTL!$M$7:$M$46,"<="&$B6+6,IRTL!$M$7:$M$46,"<>",IRTL!$C$7:$C$46,"Issue")
A7: 4 | B7: 46307 | C7: =COUNTIFS(IRTL!$B$7:$B$46,">="&$B7,IRTL!$B$7:$B$46,"<="&$B7+6) | D7: =COUNTIFS(IRTL!$M$7:$M$46,">="&$B7,IRTL!$M$7:$M$46,"<="&$B7+6) | E7: =COUNTIFS(IRTL!$B$7:$B$46,"<="&$B7+6)-COUNTIFS(IRTL!$M$7:$M$46,"<="&$B7+6,IRTL!$M$7:$M$46,"<>") | F7: =COUNTIFS(IRTL!$B$7:$B$46,"<="&$B7+6,IRTL!$H$7:$H$46,">=6")-COUNTIFS(IRTL!$M$7:$M$46,"<="&$B7+6,IRTL!$M$7:$M$46,"<>",IRTL!$H$7:$H$46,">=6") | G7: =COUNTIFS(IRTL!$B$7:$B$46,"<="&$B7+6,IRTL!$C$7:$C$46,"Risk")-COUNTIFS(IRTL!$M$7:$M$46,"<="&$B7+6,IRTL!$M$7:$M$46,"<>",IRTL!$C$7:$C$46,"Risk") | H7: =COUNTIFS(IRTL!$B$7:$B$46,"<="&$B7+6,IRTL!$C$7:$C$46,"Issue")-COUNTIFS(IRTL!$M$7:$M$46,"<="&$B7+6,IRTL!$M$7:$M$46,"<>",IRTL!$C$7:$C$46,"Issue")
A8: 5 | B8: 46314 | C8: =COUNTIFS(IRTL!$B$7:$B$46,">="&$B8,IRTL!$B$7:$B$46,"<="&$B8+6) | D8: =COUNTIFS(IRTL!$M$7:$M$46,">="&$B8,IRTL!$M$7:$M$46,"<="&$B8+6) | E8: =COUNTIFS(IRTL!$B$7:$B$46,"<="&$B8+6)-COUNTIFS(IRTL!$M$7:$M$46,"<="&$B8+6,IRTL!$M$7:$M$46,"<>") | F8: =COUNTIFS(IRTL!$B$7:$B$46,"<="&$B8+6,IRTL!$H$7:$H$46,">=6")-COUNTIFS(IRTL!$M$7:$M$46,"<="&$B8+6,IRTL!$M$7:$M$46,"<>",IRTL!$H$7:$H$46,">=6") | G8: =COUNTIFS(IRTL!$B$7:$B$46,"<="&$B8+6,IRTL!$C$7:$C$46,"Risk")-COUNTIFS(IRTL!$M$7:$M$46,"<="&$B8+6,IRTL!$M$7:$M$46,"<>",IRTL!$C$7:$C$46,"Risk") | H8: =COUNTIFS(IRTL!$B$7:$B$46,"<="&$B8+6,IRTL!$C$7:$C$46,"Issue")-COUNTIFS(IRTL!$M$7:$M$46,"<="&$B8+6,IRTL!$M$7:$M$46,"<>",IRTL!$C$7:$C$46,"Issue")
A9: 6 | B9: 46321 | C9: =COUNTIFS(IRTL!$B$7:$B$46,">="&$B9,IRTL!$B$7:$B$46,"<="&$B9+6) | D9: =COUNTIFS(IRTL!$M$7:$M$46,">="&$B9,IRTL!$M$7:$M$46,"<="&$B9+6) | E9: =COUNTIFS(IRTL!$B$7:$B$46,"<="&$B9+6)-COUNTIFS(IRTL!$M$7:$M$46,"<="&$B9+6,IRTL!$M$7:$M$46,"<>") | F9: =COUNTIFS(IRTL!$B$7:$B$46,"<="&$B9+6,IRTL!$H$7:$H$46,">=6")-COUNTIFS(IRTL!$M$7:$M$46,"<="&$B9+6,IRTL!$M$7:$M$46,"<>",IRTL!$H$7:$H$46,">=6") | G9: =COUNTIFS(IRTL!$B$7:$B$46,"<="&$B9+6,IRTL!$C$7:$C$46,"Risk")-COUNTIFS(IRTL!$M$7:$M$46,"<="&$B9+6,IRTL!$M$7:$M$46,"<>",IRTL!$C$7:$C$46,"Risk") | H9: =COUNTIFS(IRTL!$B$7:$B$46,"<="&$B9+6,IRTL!$C$7:$C$46,"Issue")-COUNTIFS(IRTL!$M$7:$M$46,"<="&$B9+6,IRTL!$M$7:$M$46,"<>",IRTL!$C$7:$C$46,"Issue")
A10: 7 | B10: 46328 | C10: =COUNTIFS(IRTL!$B$7:$B$46,">="&$B10,IRTL!$B$7:$B$46,"<="&$B10+6) | D10: =COUNTIFS(IRTL!$M$7:$M$46,">="&$B10,IRTL!$M$7:$M$46,"<="&$B10+6) | E10: =COUNTIFS(IRTL!$B$7:$B$46,"<="&$B10+6)-COUNTIFS(IRTL!$M$7:$M$46,"<="&$B10+6,IRTL!$M$7:$M$46,"<>") | F10: =COUNTIFS(IRTL!$B$7:$B$46,"<="&$B10+6,IRTL!$H$7:$H$46,">=6")-COUNTIFS(IRTL!$M$7:$M$46,"<="&$B10+6,IRTL!$M$7:$M$46,"<>",IRTL!$H$7:$H$46,">=6") | G10: =COUNTIFS(IRTL!$B$7:$B$46,"<="&$B10+6,IRTL!$C$7:$C$46,"Risk")-COUNTIFS(IRTL!$M$7:$M$46,"<="&$B10+6,IRTL!$M$7:$M$46,"<>",IRTL!$C$7:$C$46,"Risk") | H10: =COUNTIFS(IRTL!$B$7:$B$46,"<="&$B10+6,IRTL!$C$7:$C$46,"Issue")-COUNTIFS(IRTL!$M$7:$M$46,"<="&$B10+6,IRTL!$M$7:$M$46,"<>",IRTL!$C$7:$C$46,"Issue")
A11: 8 | B11: 46335 | C11: =COUNTIFS(IRTL!$B$7:$B$46,">="&$B11,IRTL!$B$7:$B$46,"<="&$B11+6) | D11: =COUNTIFS(IRTL!$M$7:$M$46,">="&$B11,IRTL!$M$7:$M$46,"<="&$B11+6) | E11: =COUNTIFS(IRTL!$B$7:$B$46,"<="&$B11+6)-COUNTIFS(IRTL!$M$7:$M$46,"<="&$B11+6,IRTL!$M$7:$M$46,"<>") | F11: =COUNTIFS(IRTL!$B$7:$B$46,"<="&$B11+6,IRTL!$H$7:$H$46,">=6")-COUNTIFS(IRTL!$M$7:$M$46,"<="&$B11+6,IRTL!$M$7:$M$46,"<>",IRTL!$H$7:$H$46,">=6") | G11: =COUNTIFS(IRTL!$B$7:$B$46,"<="&$B11+6,IRTL!$C$7:$C$46,"Risk")-COUNTIFS(IRTL!$M$7:$M$46,"<="&$B11+6,IRTL!$M$7:$M$46,"<>",IRTL!$C$7:$C$46,"Risk") | H11: =COUNTIFS(IRTL!$B$7:$B$46,"<="&$B11+6,IRTL!$C$7:$C$46,"Issue")-COUNTIFS(IRTL!$M$7:$M$46,"<="&$B11+6,IRTL!$M$7:$M$46,"<>",IRTL!$C$7:$C$46,"Issue")
A12: 9 | B12: 46342 | C12: =COUNTIFS(IRTL!$B$7:$B$46,">="&$B12,IRTL!$B$7:$B$46,"<="&$B12+6) | D12: =COUNTIFS(IRTL!$M$7:$M$46,">="&$B12,IRTL!$M$7:$M$46,"<="&$B12+6) | E12: =COUNTIFS(IRTL!$B$7:$B$46,"<="&$B12+6)-COUNTIFS(IRTL!$M$7:$M$46,"<="&$B12+6,IRTL!$M$7:$M$46,"<>") | F12: =COUNTIFS(IRTL!$B$7:$B$46,"<="&$B12+6,IRTL!$H$7:$H$46,">=6")-COUNTIFS(IRTL!$M$7:$M$46,"<="&$B12+6,IRTL!$M$7:$M$46,"<>",IRTL!$H$7:$H$46,">=6") | G12: =COUNTIFS(IRTL!$B$7:$B$46,"<="&$B12+6,IRTL!$C$7:$C$46,"Risk")-COUNTIFS(IRTL!$M$7:$M$46,"<="&$B12+6,IRTL!$M$7:$M$46,"<>",IRTL!$C$7:$C$46,"Risk") | H12: =COUNTIFS(IRTL!$B$7:$B$46,"<="&$B12+6,IRTL!$C$7:$C$46,"Issue")-COUNTIFS(IRTL!$M$7:$M$46,"<="&$B12+6,IRTL!$M$7:$M$46,"<>",IRTL!$C$7:$C$46,"Issue")
A13: 10 | B13: 46349 | C13: =COUNTIFS(IRTL!$B$7:$B$46,">="&$B13,IRTL!$B$7:$B$46,"<="&$B13+6) | D13: =COUNTIFS(IRTL!$M$7:$M$46,">="&$B13,IRTL!$M$7:$M$46,"<="&$B13+6) | E13: =COUNTIFS(IRTL!$B$7:$B$46,"<="&$B13+6)-COUNTIFS(IRTL!$M$7:$M$46,"<="&$B13+6,IRTL!$M$7:$M$46,"<>") | F13: =COUNTIFS(IRTL!$B$7:$B$46,"<="&$B13+6,IRTL!$H$7:$H$46,">=6")-COUNTIFS(IRTL!$M$7:$M$46,"<="&$B13+6,IRTL!$M$7:$M$46,"<>",IRTL!$H$7:$H$46,">=6") | G13: =COUNTIFS(IRTL!$B$7:$B$46,"<="&$B13+6,IRTL!$C$7:$C$46,"Risk")-COUNTIFS(IRTL!$M$7:$M$46,"<="&$B13+6,IRTL!$M$7:$M$46,"<>",IRTL!$C$7:$C$46,"Risk") | H13: =COUNTIFS(IRTL!$B$7:$B$46,"<="&$B13+6,IRTL!$C$7:$C$46,"Issue")-COUNTIFS(IRTL!$M$7:$M$46,"<="&$B13+6,IRTL!$M$7:$M$46,"<>",IRTL!$C$7:$C$46,"Issue")
A14: 11 | B14: 46356 | C14: =COUNTIFS(IRTL!$B$7:$B$46,">="&$B14,IRTL!$B$7:$B$46,"<="&$B14+6) | D14: =COUNTIFS(IRTL!$M$7:$M$46,">="&$B14,IRTL!$M$7:$M$46,"<="&$B14+6) | E14: =COUNTIFS(IRTL!$B$7:$B$46,"<="&$B14+6)-COUNTIFS(IRTL!$M$7:$M$46,"<="&$B14+6,IRTL!$M$7:$M$46,"<>") | F14: =COUNTIFS(IRTL!$B$7:$B$46,"<="&$B14+6,IRTL!$H$7:$H$46,">=6")-COUNTIFS(IRTL!$M$7:$M$46,"<="&$B14+6,IRTL!$M$7:$M$46,"<>",IRTL!$H$7:$H$46,">=6") | G14: =COUNTIFS(IRTL!$B$7:$B$46,"<="&$B14+6,IRTL!$C$7:$C$46,"Risk")-COUNTIFS(IRTL!$M$7:$M$46,"<="&$B14+6,IRTL!$M$7:$M$46,"<>",IRTL!$C$7:$C$46,"Risk") | H14: =COUNTIFS(IRTL!$B$7:$B$46,"<="&$B14+6,IRTL!$C$7:$C$46,"Issue")-COUNTIFS(IRTL!$M$7:$M$46,"<="&$B14+6,IRTL!$M$7:$M$46,"<>",IRTL!$C$7:$C$46,"Issue")
A15: 12 | B15: 46363 | C15: =COUNTIFS(IRTL!$B$7:$B$46,">="&$B15,IRTL!$B$7:$B$46,"<="&$B15+6) | D15: =COUNTIFS(IRTL!$M$7:$M$46,">="&$B15,IRTL!$M$7:$M$46,"<="&$B15+6) | E15: =COUNTIFS(IRTL!$B$7:$B$46,"<="&$B15+6)-COUNTIFS(IRTL!$M$7:$M$46,"<="&$B15+6,IRTL!$M$7:$M$46,"<>") | F15: =COUNTIFS(IRTL!$B$7:$B$46,"<="&$B15+6,IRTL!$H$7:$H$46,">=6")-COUNTIFS(IRTL!$M$7:$M$46,"<="&$B15+6,IRTL!$M$7:$M$46,"<>",IRTL!$H$7:$H$46,">=6") | G15: =COUNTIFS(IRTL!$B$7:$B$46,"<="&$B15+6,IRTL!$C$7:$C$46,"Risk")-COUNTIFS(IRTL!$M$7:$M$46,"<="&$B15+6,IRTL!$M$7:$M$46,"<>",IRTL!$C$7:$C$46,"Risk") | H15: =COUNTIFS(IRTL!$B$7:$B$46,"<="&$B15+6,IRTL!$C$7:$C$46,"Issue")-COUNTIFS(IRTL!$M$7:$M$46,"<="&$B15+6,IRTL!$M$7:$M$46,"<>",IRTL!$C$7:$C$46,"Issue")
A16: 13 | B16: 46370 | C16: =COUNTIFS(IRTL!$B$7:$B$46,">="&$B16,IRTL!$B$7:$B$46,"<="&$B16+6) | D16: =COUNTIFS(IRTL!$M$7:$M$46,">="&$B16,IRTL!$M$7:$M$46,"<="&$B16+6) | E16: =COUNTIFS(IRTL!$B$7:$B$46,"<="&$B16+6)-COUNTIFS(IRTL!$M$7:$M$46,"<="&$B16+6,IRTL!$M$7:$M$46,"<>") | F16: =COUNTIFS(IRTL!$B$7:$B$46,"<="&$B16+6,IRTL!$H$7:$H$46,">=6")-COUNTIFS(IRTL!$M$7:$M$46,"<="&$B16+6,IRTL!$M$7:$M$46,"<>",IRTL!$H$7:$H$46,">=6") | G16: =COUNTIFS(IRTL!$B$7:$B$46,"<="&$B16+6,IRTL!$C$7:$C$46,"Risk")-COUNTIFS(IRTL!$M$7:$M$46,"<="&$B16+6,IRTL!$M$7:$M$46,"<>",IRTL!$C$7:$C$46,"Risk") | H16: =COUNTIFS(IRTL!$B$7:$B$46,"<="&$B16+6,IRTL!$C$7:$C$46,"Issue")-COUNTIFS(IRTL!$M$7:$M$46,"<="&$B16+6,IRTL!$M$7:$M$46,"<>",IRTL!$C$7:$C$46,"Issue")
A17: 14 | B17: 46377 | C17: =COUNTIFS(IRTL!$B$7:$B$46,">="&$B17,IRTL!$B$7:$B$46,"<="&$B17+6) | D17: =COUNTIFS(IRTL!$M$7:$M$46,">="&$B17,IRTL!$M$7:$M$46,"<="&$B17+6) | E17: =COUNTIFS(IRTL!$B$7:$B$46,"<="&$B17+6)-COUNTIFS(IRTL!$M$7:$M$46,"<="&$B17+6,IRTL!$M$7:$M$46,"<>") | F17: =COUNTIFS(IRTL!$B$7:$B$46,"<="&$B17+6,IRTL!$H$7:$H$46,">=6")-COUNTIFS(IRTL!$M$7:$M$46,"<="&$B17+6,IRTL!$M$7:$M$46,"<>",IRTL!$H$7:$H$46,">=6") | G17: =COUNTIFS(IRTL!$B$7:$B$46,"<="&$B17+6,IRTL!$C$7:$C$46,"Risk")-COUNTIFS(IRTL!$M$7:$M$46,"<="&$B17+6,IRTL!$M$7:$M$46,"<>",IRTL!$C$7:$C$46,"Risk") | H17: =COUNTIFS(IRTL!$B$7:$B$46,"<="&$B17+6,IRTL!$C$7:$C$46,"Issue")-COUNTIFS(IRTL!$M$7:$M$46,"<="&$B17+6,IRTL!$M$7:$M$46,"<>",IRTL!$C$7:$C$46,"Issue")
A18: 15 | B18: 46384 | C18: =COUNTIFS(IRTL!$B$7:$B$46,">="&$B18,IRTL!$B$7:$B$46,"<="&$B18+6) | D18: =COUNTIFS(IRTL!$M$7:$M$46,">="&$B18,IRTL!$M$7:$M$46,"<="&$B18+6) | E18: =COUNTIFS(IRTL!$B$7:$B$46,"<="&$B18+6)-COUNTIFS(IRTL!$M$7:$M$46,"<="&$B18+6,IRTL!$M$7:$M$46,"<>") | F18: =COUNTIFS(IRTL!$B$7:$B$46,"<="&$B18+6,IRTL!$H$7:$H$46,">=6")-COUNTIFS(IRTL!$M$7:$M$46,"<="&$B18+6,IRTL!$M$7:$M$46,"<>",IRTL!$H$7:$H$46,">=6") | G18: =COUNTIFS(IRTL!$B$7:$B$46,"<="&$B18+6,IRTL!$C$7:$C$46,"Risk")-COUNTIFS(IRTL!$M$7:$M$46,"<="&$B18+6,IRTL!$M$7:$M$46,"<>",IRTL!$C$7:$C$46,"Risk") | H18: =COUNTIFS(IRTL!$B$7:$B$46,"<="&$B18+6,IRTL!$C$7:$C$46,"Issue")-COUNTIFS(IRTL!$M$7:$M$46,"<="&$B18+6,IRTL!$M$7:$M$46,"<>",IRTL!$C$7:$C$46,"Issue")
A20: Reading this sheet
A21: Watch the Open at end column across the weeks, not any single number. A count that climbs steadily means the team is raising risks faster than it resolves them - which is still better than a column of zeros, because a project with no recorded risks is a project where nobody is looking for them.

Sheet RISK
A1: Top Risk Register
A2: The highest-priority open items from IRTL, ranked. Read this at every weekly meeting.
A4: Open items | B4: =COUNTIFS(IRTL!$A$7:$A$46,"<>",IRTL!$L$7:$L$46,"<>Complete") | C4: High priority (6 or more) | F4: =COUNTIFS(IRTL!$H$7:$H$46,">=6",IRTL!$L$7:$L$46,"<>Complete")
A6: Rank | B6: ID | C6: Risk or issue | D6: Likelihood | E6: Impact | F6: Priority | G6: Owner | H6: Follow-up | I6: Status | J6: Mitigation in hand
A7: 1 | B7: =IFERROR(IF(LARGE(IRTL!$H$7:$H$46*(IRTL!$L$7:$L$46<>"Complete")*(IRTL!$A$7:$A$46<>"")-ROW(IRTL!$A$7:$A$46)/100000,$A7)<=0,"",INDEX(IRTL!$A$7:$A$46,MATCH(LARGE(IRTL!$H$7:$H$46*(IRTL!$L$7:$L$46<>"Complete")*(IRTL!$A$7:$A$46<>"")-ROW(IRTL!$A$7:$A$46)/100000,$A7),IRTL!$H$7:$H$46*(IRTL!$L$7:$L$46<>"Complete")*(IRTL!$A$7:$A$46<>"")-ROW(IRTL!$A$7:$A$46)/100000,0))),"") | C7: =IFERROR(IF(LARGE(IRTL!$H$7:$H$46*(IRTL!$L$7:$L$46<>"Complete")*(IRTL!$A$7:$A$46<>"")-ROW(IRTL!$A$7:$A$46)/100000,$A7)<=0,"",INDEX(IRTL!$E$7:$E$46,MATCH(LARGE(IRTL!$H$7:$H$46*(IRTL!$L$7:$L$46<>"Complete")*(IRTL!$A$7:$A$46<>"")-ROW(IRTL!$A$7:$A$46)/100000,$A7),IRTL!$H$7:$H$46*(IRTL!$L$7:$L$46<>"Complete")*(IRTL!$A$7:$A$46<>"")-ROW(IRTL!$A$7:$A$46)/100000,0))),"") | D7: =IFERROR(IF(LARGE(IRTL!$H$7:$H$46*(IRTL!$L$7:$L$46<>"Complete")*(IRTL!$A$7:$A$46<>"")-ROW(IRTL!$A$7:$A$46)/100000,$A7)<=0,"",INDEX(IRTL!$F$7:$F$46,MATCH(LARGE(IRTL!$H$7:$H$46*(IRTL!$L$7:$L$46<>"Complete")*(IRTL!$A$7:$A$46<>"")-ROW(IRTL!$A$7:$A$46)/100000,$A7),IRTL!$H$7:$H$46*(IRTL!$L$7:$L$46<>"Complete")*(IRTL!$A$7:$A$46<>"")-ROW(IRTL!$A$7:$A$46)/100000,0))),"") | E7: =IFERROR(IF(LARGE(IRTL!$H$7:$H$46*(IRTL!$L$7:$L$46<>"Complete")*(IRTL!$A$7:$A$46<>"")-ROW(IRTL!$A$7:$A$46)/100000,$A7)<=0,"",INDEX(IRTL!$G$7:$G$46,MATCH(LARGE(IRTL!$H$7:$H$46*(IRTL!$L$7:$L$46<>"Complete")*(IRTL!$A$7:$A$46<>"")-ROW(IRTL!$A$7:$A$46)/100000,$A7),IRTL!$H$7:$H$46*(IRTL!$L$7:$L$46<>"Complete")*(IRTL!$A$7:$A$46<>"")-ROW(IRTL!$A$7:$A$46)/100000,0))),"") | F7: =IFERROR(IF(LARGE(IRTL!$H$7:$H$46*(IRTL!$L$7:$L$46<>"Complete")*(IRTL!$A$7:$A$46<>"")-ROW(IRTL!$A$7:$A$46)/100000,$A7)<=0,"",INDEX(IRTL!$H$7:$H$46,MATCH(LARGE(IRTL!$H$7:$H$46*(IRTL!$L$7:$L$46<>"Complete")*(IRTL!$A$7:$A$46<>"")-ROW(IRTL!$A$7:$A$46)/100000,$A7),IRTL!$H$7:$H$46*(IRTL!$L$7:$L$46<>"Complete")*(IRTL!$A$7:$A$46<>"")-ROW(IRTL!$A$7:$A$46)/100000,0))),"") | G7: =IFERROR(IF(LARGE(IRTL!$H$7:$H$46*(IRTL!$L$7:$L$46<>"Complete")*(IRTL!$A$7:$A$46<>"")-ROW(IRTL!$A$7:$A$46)/100000,$A7)<=0,"",INDEX(IRTL!$I$7:$I$46,MATCH(LARGE(IRTL!$H$7:$H$46*(IRTL!$L$7:$L$46<>"Complete")*(IRTL!$A$7:$A$46<>"")-ROW(IRTL!$A$7:$A$46)/100000,$A7),IRTL!$H$7:$H$46*(IRTL!$L$7:$L$46<>"Complete")*(IRTL!$A$7:$A$46<>"")-ROW(IRTL!$A$7:$A$46)/100000,0))),"") | H7: =IFERROR(IF(LARGE(IRTL!$H$7:$H$46*(IRTL!$L$7:$L$46<>"Complete")*(IRTL!$A$7:$A$46<>"")-ROW(IRTL!$A$7:$A$46)/100000,$A7)<=0,"",INDEX(IRTL!$K$7:$K$46,MATCH(LARGE(IRTL!$H$7:$H$46*(IRTL!$L$7:$L$46<>"Complete")*(IRTL!$A$7:$A$46<>"")-ROW(IRTL!$A$7:$A$46)/100000,$A7),IRTL!$H$7:$H$46*(IRTL!$L$7:$L$46<>"Complete")*(IRTL!$A$7:$A$46<>"")-ROW(IRTL!$A$7:$A$46)/100000,0))),"") | I7: =IFERROR(IF(LARGE(IRTL!$H$7:$H$46*(IRTL!$L$7:$L$46<>"Complete")*(IRTL!$A$7:$A$46<>"")-ROW(IRTL!$A$7:$A$46)/100000,$A7)<=0,"",INDEX(IRTL!$L$7:$L$46,MATCH(LARGE(IRTL!$H$7:$H$46*(IRTL!$L$7:$L$46<>"Complete")*(IRTL!$A$7:$A$46<>"")-ROW(IRTL!$A$7:$A$46)/100000,$A7),IRTL!$H$7:$H$46*(IRTL!$L$7:$L$46<>"Complete")*(IRTL!$A$7:$A$46<>"")-ROW(IRTL!$A$7:$A$46)/100000,0))),"") | J7: =IFERROR(IF(LARGE(IRTL!$H$7:$H$46*(IRTL!$L$7:$L$46<>"Complete")*(IRTL!$A$7:$A$46<>"")-ROW(IRTL!$A$7:$A$46)/100000,$A7)<=0,"",INDEX(IRTL!$J$7:$J$46,MATCH(LARGE(IRTL!$H$7:$H$46*(IRTL!$L$7:$L$46<>"Complete")*(IRTL!$A$7:$A$46<>"")-ROW(IRTL!$A$7:$A$46)/100000,$A7),IRTL!$H$7:$H$46*(IRTL!$L$7:$L$46<>"Complete")*(IRTL!$A$7:$A$46<>"")-ROW(IRTL!$A$7:$A$46)/100000,0))),"")
A8: 2 | B8: =IFERROR(IF(LARGE(IRTL!$H$7:$H$46*(IRTL!$L$7:$L$46<>"Complete")*(IRTL!$A$7:$A$46<>"")-ROW(IRTL!$A$7:$A$46)/100000,$A8)<=0,"",INDEX(IRTL!$A$7:$A$46,MATCH(LARGE(IRTL!$H$7:$H$46*(IRTL!$L$7:$L$46<>"Complete")*(IRTL!$A$7:$A$46<>"")-ROW(IRTL!$A$7:$A$46)/100000,$A8),IRTL!$H$7:$H$46*(IRTL!$L$7:$L$46<>"Complete")*(IRTL!$A$7:$A$46<>"")-ROW(IRTL!$A$7:$A$46)/100000,0))),"") | C8: =IFERROR(IF(LARGE(IRTL!$H$7:$H$46*(IRTL!$L$7:$L$46<>"Complete")*(IRTL!$A$7:$A$46<>"")-ROW(IRTL!$A$7:$A$46)/100000,$A8)<=0,"",INDEX(IRTL!$E$7:$E$46,MATCH(LARGE(IRTL!$H$7:$H$46*(IRTL!$L$7:$L$46<>"Complete")*(IRTL!$A$7:$A$46<>"")-ROW(IRTL!$A$7:$A$46)/100000,$A8),IRTL!$H$7:$H$46*(IRTL!$L$7:$L$46<>"Complete")*(IRTL!$A$7:$A$46<>"")-ROW(IRTL!$A$7:$A$46)/100000,0))),"") | D8: =IFERROR(IF(LARGE(IRTL!$H$7:$H$46*(IRTL!$L$7:$L$46<>"Complete")*(IRTL!$A$7:$A$46<>"")-ROW(IRTL!$A$7:$A$46)/100000,$A8)<=0,"",INDEX(IRTL!$F$7:$F$46,MATCH(LARGE(IRTL!$H$7:$H$46*(IRTL!$L$7:$L$46<>"Complete")*(IRTL!$A$7:$A$46<>"")-ROW(IRTL!$A$7:$A$46)/100000,$A8),IRTL!$H$7:$H$46*(IRTL!$L$7:$L$46<>"Complete")*(IRTL!$A$7:$A$46<>"")-ROW(IRTL!$A$7:$A$46)/100000,0))),"") | E8: =IFERROR(IF(LARGE(IRTL!$H$7:$H$46*(IRTL!$L$7:$L$46<>"Complete")*(IRTL!$A$7:$A$46<>"")-ROW(IRTL!$A$7:$A$46)/100000,$A8)<=0,"",INDEX(IRTL!$G$7:$G$46,MATCH(LARGE(IRTL!$H$7:$H$46*(IRTL!$L$7:$L$46<>"Complete")*(IRTL!$A$7:$A$46<>"")-ROW(IRTL!$A$7:$A$46)/100000,$A8),IRTL!$H$7:$H$46*(IRTL!$L$7:$L$46<>"Complete")*(IRTL!$A$7:$A$46<>"")-ROW(IRTL!$A$7:$A$46)/100000,0))),"") | F8: =IFERROR(IF(LARGE(IRTL!$H$7:$H$46*(IRTL!$L$7:$L$46<>"Complete")*(IRTL!$A$7:$A$46<>"")-ROW(IRTL!$A$7:$A$46)/100000,$A8)<=0,"",INDEX(IRTL!$H$7:$H$46,MATCH(LARGE(IRTL!$H$7:$H$46*(IRTL!$L$7:$L$46<>"Complete")*(IRTL!$A$7:$A$46<>"")-ROW(IRTL!$A$7:$A$46)/100000,$A8),IRTL!$H$7:$H$46*(IRTL!$L$7:$L$46<>"Complete")*(IRTL!$A$7:$A$46<>"")-ROW(IRTL!$A$7:$A$46)/100000,0))),"") | G8: =IFERROR(IF(LARGE(IRTL!$H$7:$H$46*(IRTL!$L$7:$L$46<>"Complete")*(IRTL!$A$7:$A$46<>"")-ROW(IRTL!$A$7:$A$46)/100000,$A8)<=0,"",INDEX(IRTL!$I$7:$I$46,MATCH(LARGE(IRTL!$H$7:$H$46*(IRTL!$L$7:$L$46<>"Complete")*(IRTL!$A$7:$A$46<>"")-ROW(IRTL!$A$7:$A$46)/100000,$A8),IRTL!$H$7:$H$46*(IRTL!$L$7:$L$46<>"Complete")*(IRTL!$A$7:$A$46<>"")-ROW(IRTL!$A$7:$A$46)/100000,0))),"") | H8: =IFERROR(IF(LARGE(IRTL!$H$7:$H$46*(IRTL!$L$7:$L$46<>"Complete")*(IRTL!$A$7:$A$46<>"")-ROW(IRTL!$A$7:$A$46)/100000,$A8)<=0,"",INDEX(IRTL!$K$7:$K$46,MATCH(LARGE(IRTL!$H$7:$H$46*(IRTL!$L$7:$L$46<>"Complete")*(IRTL!$A$7:$A$46<>"")-ROW(IRTL!$A$7:$A$46)/100000,$A8),IRTL!$H$7:$H$46*(IRTL!$L$7:$L$46<>"Complete")*(IRTL!$A$7:$A$46<>"")-ROW(IRTL!$A$7:$A$46)/100000,0))),"") | I8: =IFERROR(IF(LARGE(IRTL!$H$7:$H$46*(IRTL!$L$7:$L$46<>"Complete")*(IRTL!$A$7:$A$46<>"")-ROW(IRTL!$A$7:$A$46)/100000,$A8)<=0,"",INDEX(IRTL!$L$7:$L$46,MATCH(LARGE(IRTL!$H$7:$H$46*(IRTL!$L$7:$L$46<>"Complete")*(IRTL!$A$7:$A$46<>"")-ROW(IRTL!$A$7:$A$46)/100000,$A8),IRTL!$H$7:$H$46*(IRTL!$L$7:$L$46<>"Complete")*(IRTL!$A$7:$A$46<>"")-ROW(IRTL!$A$7:$A$46)/100000,0))),"") | J8: =IFERROR(IF(LARGE(IRTL!$H$7:$H$46*(IRTL!$L$7:$L$46<>"Complete")*(IRTL!$A$7:$A$46<>"")-ROW(IRTL!$A$7:$A$46)/100000,$A8)<=0,"",INDEX(IRTL!$J$7:$J$46,MATCH(LARGE(IRTL!$H$7:$H$46*(IRTL!$L$7:$L$46<>"Complete")*(IRTL!$A$7:$A$46<>"")-ROW(IRTL!$A$7:$A$46)/100000,$A8),IRTL!$H$7:$H$46*(IRTL!$L$7:$L$46<>"Complete")*(IRTL!$A$7:$A$46<>"")-ROW(IRTL!$A$7:$A$46)/100000,0))),"")
A9: 3 | B9: =IFERROR(IF(LARGE(IRTL!$H$7:$H$46*(IRTL!$L$7:$L$46<>"Complete")*(IRTL!$A$7:$A$46<>"")-ROW(IRTL!$A$7:$A$46)/100000,$A9)<=0,"",INDEX(IRTL!$A$7:$A$46,MATCH(LARGE(IRTL!$H$7:$H$46*(IRTL!$L$7:$L$46<>"Complete")*(IRTL!$A$7:$A$46<>"")-ROW(IRTL!$A$7:$A$46)/100000,$A9),IRTL!$H$7:$H$46*(IRTL!$L$7:$L$46<>"Complete")*(IRTL!$A$7:$A$46<>"")-ROW(IRTL!$A$7:$A$46)/100000,0))),"") | C9: =IFERROR(IF(LARGE(IRTL!$H$7:$H$46*(IRTL!$L$7:$L$46<>"Complete")*(IRTL!$A$7:$A$46<>"")-ROW(IRTL!$A$7:$A$46)/100000,$A9)<=0,"",INDEX(IRTL!$E$7:$E$46,MATCH(LARGE(IRTL!$H$7:$H$46*(IRTL!$L$7:$L$46<>"Complete")*(IRTL!$A$7:$A$46<>"")-ROW(IRTL!$A$7:$A$46)/100000,$A9),IRTL!$H$7:$H$46*(IRTL!$L$7:$L$46<>"Complete")*(IRTL!$A$7:$A$46<>"")-ROW(IRTL!$A$7:$A$46)/100000,0))),"") | D9: =IFERROR(IF(LARGE(IRTL!$H$7:$H$46*(IRTL!$L$7:$L$46<>"Complete")*(IRTL!$A$7:$A$46<>"")-ROW(IRTL!$A$7:$A$46)/100000,$A9)<=0,"",INDEX(IRTL!$F$7:$F$46,MATCH(LARGE(IRTL!$H$7:$H$46*(IRTL!$L$7:$L$46<>"Complete")*(IRTL!$A$7:$A$46<>"")-ROW(IRTL!$A$7:$A$46)/100000,$A9),IRTL!$H$7:$H$46*(IRTL!$L$7:$L$46<>"Complete")*(IRTL!$A$7:$A$46<>"")-ROW(IRTL!$A$7:$A$46)/100000,0))),"") | E9: =IFERROR(IF(LARGE(IRTL!$H$7:$H$46*(IRTL!$L$7:$L$46<>"Complete")*(IRTL!$A$7:$A$46<>"")-ROW(IRTL!$A$7:$A$46)/100000,$A9)<=0,"",INDEX(IRTL!$G$7:$G$46,MATCH(LARGE(IRTL!$H$7:$H$46*(IRTL!$L$7:$L$46<>"Complete")*(IRTL!$A$7:$A$46<>"")-ROW(IRTL!$A$7:$A$46)/100000,$A9),IRTL!$H$7:$H$46*(IRTL!$L$7:$L$46<>"Complete")*(IRTL!$A$7:$A$46<>"")-ROW(IRTL!$A$7:$A$46)/100000,0))),"") | F9: =IFERROR(IF(LARGE(IRTL!$H$7:$H$46*(IRTL!$L$7:$L$46<>"Complete")*(IRTL!$A$7:$A$46<>"")-ROW(IRTL!$A$7:$A$46)/100000,$A9)<=0,"",INDEX(IRTL!$H$7:$H$46,MATCH(LARGE(IRTL!$H$7:$H$46*(IRTL!$L$7:$L$46<>"Complete")*(IRTL!$A$7:$A$46<>"")-ROW(IRTL!$A$7:$A$46)/100000,$A9),IRTL!$H$7:$H$46*(IRTL!$L$7:$L$46<>"Complete")*(IRTL!$A$7:$A$46<>"")-ROW(IRTL!$A$7:$A$46)/100000,0))),"") | G9: =IFERROR(IF(LARGE(IRTL!$H$7:$H$46*(IRTL!$L$7:$L$46<>"Complete")*(IRTL!$A$7:$A$46<>"")-ROW(IRTL!$A$7:$A$46)/100000,$A9)<=0,"",INDEX(IRTL!$I$7:$I$46,MATCH(LARGE(IRTL!$H$7:$H$46*(IRTL!$L$7:$L$46<>"Complete")*(IRTL!$A$7:$A$46<>"")-ROW(IRTL!$A$7:$A$46)/100000,$A9),IRTL!$H$7:$H$46*(IRTL!$L$7:$L$46<>"Complete")*(IRTL!$A$7:$A$46<>"")-ROW(IRTL!$A$7:$A$46)/100000,0))),"") | H9: =IFERROR(IF(LARGE(IRTL!$H$7:$H$46*(IRTL!$L$7:$L$46<>"Complete")*(IRTL!$A$7:$A$46<>"")-ROW(IRTL!$A$7:$A$46)/100000,$A9)<=0,"",INDEX(IRTL!$K$7:$K$46,MATCH(LARGE(IRTL!$H$7:$H$46*(IRTL!$L$7:$L$46<>"Complete")*(IRTL!$A$7:$A$46<>"")-ROW(IRTL!$A$7:$A$46)/100000,$A9),IRTL!$H$7:$H$46*(IRTL!$L$7:$L$46<>"Complete")*(IRTL!$A$7:$A$46<>"")-ROW(IRTL!$A$7:$A$46)/100000,0))),"") | I9: =IFERROR(IF(LARGE(IRTL!$H$7:$H$46*(IRTL!$L$7:$L$46<>"Complete")*(IRTL!$A$7:$A$46<>"")-ROW(IRTL!$A$7:$A$46)/100000,$A9)<=0,"",INDEX(IRTL!$L$7:$L$46,MATCH(LARGE(IRTL!$H$7:$H$46*(IRTL!$L$7:$L$46<>"Complete")*(IRTL!$A$7:$A$46<>"")-ROW(IRTL!$A$7:$A$46)/100000,$A9),IRTL!$H$7:$H$46*(IRTL!$L$7:$L$46<>"Complete")*(IRTL!$A$7:$A$46<>"")-ROW(IRTL!$A$7:$A$46)/100000,0))),"") | J9: =IFERROR(IF(LARGE(IRTL!$H$7:$H$46*(IRTL!$L$7:$L$46<>"Complete")*(IRTL!$A$7:$A$46<>"")-ROW(IRTL!$A$7:$A$46)/100000,$A9)<=0,"",INDEX(IRTL!$J$7:$J$46,MATCH(LARGE(IRTL!$H$7:$H$46*(IRTL!$L$7:$L$46<>"Complete")*(IRTL!$A$7:$A$46<>"")-ROW(IRTL!$A$7:$A$46)/100000,$A9),IRTL!$H$7:$H$46*(IRTL!$L$7:$L$46<>"Complete")*(IRTL!$A$7:$A$46<>"")-ROW(IRTL!$A$7:$A$46)/100000,0))),"")
A10: 4 | B10: =IFERROR(IF(LARGE(IRTL!$H$7:$H$46*(IRTL!$L$7:$L$46<>"Complete")*(IRTL!$A$7:$A$46<>"")-ROW(IRTL!$A$7:$A$46)/100000,$A10)<=0,"",INDEX(IRTL!$A$7:$A$46,MATCH(LARGE(IRTL!$H$7:$H$46*(IRTL!$L$7:$L$46<>"Complete")*(IRTL!$A$7:$A$46<>"")-ROW(IRTL!$A$7:$A$46)/100000,$A10),IRTL!$H$7:$H$46*(IRTL!$L$7:$L$46<>"Complete")*(IRTL!$A$7:$A$46<>"")-ROW(IRTL!$A$7:$A$46)/100000,0))),"") | C10: =IFERROR(IF(LARGE(IRTL!$H$7:$H$46*(IRTL!$L$7:$L$46<>"Complete")*(IRTL!$A$7:$A$46<>"")-ROW(IRTL!$A$7:$A$46)/100000,$A10)<=0,"",INDEX(IRTL!$E$7:$E$46,MATCH(LARGE(IRTL!$H$7:$H$46*(IRTL!$L$7:$L$46<>"Complete")*(IRTL!$A$7:$A$46<>"")-ROW(IRTL!$A$7:$A$46)/100000,$A10),IRTL!$H$7:$H$46*(IRTL!$L$7:$L$46<>"Complete")*(IRTL!$A$7:$A$46<>"")-ROW(IRTL!$A$7:$A$46)/100000,0))),"") | D10: =IFERROR(IF(LARGE(IRTL!$H$7:$H$46*(IRTL!$L$7:$L$46<>"Complete")*(IRTL!$A$7:$A$46<>"")-ROW(IRTL!$A$7:$A$46)/100000,$A10)<=0,"",INDEX(IRTL!$F$7:$F$46,MATCH(LARGE(IRTL!$H$7:$H$46*(IRTL!$L$7:$L$46<>"Complete")*(IRTL!$A$7:$A$46<>"")-ROW(IRTL!$A$7:$A$46)/100000,$A10),IRTL!$H$7:$H$46*(IRTL!$L$7:$L$46<>"Complete")*(IRTL!$A$7:$A$46<>"")-ROW(IRTL!$A$7:$A$46)/100000,0))),"") | E10: =IFERROR(IF(LARGE(IRTL!$H$7:$H$46*(IRTL!$L$7:$L$46<>"Complete")*(IRTL!$A$7:$A$46<>"")-ROW(IRTL!$A$7:$A$46)/100000,$A10)<=0,"",INDEX(IRTL!$G$7:$G$46,MATCH(LARGE(IRTL!$H$7:$H$46*(IRTL!$L$7:$L$46<>"Complete")*(IRTL!$A$7:$A$46<>"")-ROW(IRTL!$A$7:$A$46)/100000,$A10),IRTL!$H$7:$H$46*(IRTL!$L$7:$L$46<>"Complete")*(IRTL!$A$7:$A$46<>"")-ROW(IRTL!$A$7:$A$46)/100000,0))),"") | F10: =IFERROR(IF(LARGE(IRTL!$H$7:$H$46*(IRTL!$L$7:$L$46<>"Complete")*(IRTL!$A$7:$A$46<>"")-ROW(IRTL!$A$7:$A$46)/100000,$A10)<=0,"",INDEX(IRTL!$H$7:$H$46,MATCH(LARGE(IRTL!$H$7:$H$46*(IRTL!$L$7:$L$46<>"Complete")*(IRTL!$A$7:$A$46<>"")-ROW(IRTL!$A$7:$A$46)/100000,$A10),IRTL!$H$7:$H$46*(IRTL!$L$7:$L$46<>"Complete")*(IRTL!$A$7:$A$46<>"")-ROW(IRTL!$A$7:$A$46)/100000,0))),"") | G10: =IFERROR(IF(LARGE(IRTL!$H$7:$H$46*(IRTL!$L$7:$L$46<>"Complete")*(IRTL!$A$7:$A$46<>"")-ROW(IRTL!$A$7:$A$46)/100000,$A10)<=0,"",INDEX(IRTL!$I$7:$I$46,MATCH(LARGE(IRTL!$H$7:$H$46*(IRTL!$L$7:$L$46<>"Complete")*(IRTL!$A$7:$A$46<>"")-ROW(IRTL!$A$7:$A$46)/100000,$A10),IRTL!$H$7:$H$46*(IRTL!$L$7:$L$46<>"Complete")*(IRTL!$A$7:$A$46<>"")-ROW(IRTL!$A$7:$A$46)/100000,0))),"") | H10: =IFERROR(IF(LARGE(IRTL!$H$7:$H$46*(IRTL!$L$7:$L$46<>"Complete")*(IRTL!$A$7:$A$46<>"")-ROW(IRTL!$A$7:$A$46)/100000,$A10)<=0,"",INDEX(IRTL!$K$7:$K$46,MATCH(LARGE(IRTL!$H$7:$H$46*(IRTL!$L$7:$L$46<>"Complete")*(IRTL!$A$7:$A$46<>"")-ROW(IRTL!$A$7:$A$46)/100000,$A10),IRTL!$H$7:$H$46*(IRTL!$L$7:$L$46<>"Complete")*(IRTL!$A$7:$A$46<>"")-ROW(IRTL!$A$7:$A$46)/100000,0))),"") | I10: =IFERROR(IF(LARGE(IRTL!$H$7:$H$46*(IRTL!$L$7:$L$46<>"Complete")*(IRTL!$A$7:$A$46<>"")-ROW(IRTL!$A$7:$A$46)/100000,$A10)<=0,"",INDEX(IRTL!$L$7:$L$46,MATCH(LARGE(IRTL!$H$7:$H$46*(IRTL!$L$7:$L$46<>"Complete")*(IRTL!$A$7:$A$46<>"")-ROW(IRTL!$A$7:$A$46)/100000,$A10),IRTL!$H$7:$H$46*(IRTL!$L$7:$L$46<>"Complete")*(IRTL!$A$7:$A$46<>"")-ROW(IRTL!$A$7:$A$46)/100000,0))),"") | J10: =IFERROR(IF(LARGE(IRTL!$H$7:$H$46*(IRTL!$L$7:$L$46<>"Complete")*(IRTL!$A$7:$A$46<>"")-ROW(IRTL!$A$7:$A$46)/100000,$A10)<=0,"",INDEX(IRTL!$J$7:$J$46,MATCH(LARGE(IRTL!$H$7:$H$46*(IRTL!$L$7:$L$46<>"Complete")*(IRTL!$A$7:$A$46<>"")-ROW(IRTL!$A$7:$A$46)/100000,$A10),IRTL!$H$7:$H$46*(IRTL!$L$7:$L$46<>"Complete")*(IRTL!$A$7:$A$46<>"")-ROW(IRTL!$A$7:$A$46)/100000,0))),"")
A11: 5 | B11: =IFERROR(IF(LARGE(IRTL!$H$7:$H$46*(IRTL!$L$7:$L$46<>"Complete")*(IRTL!$A$7:$A$46<>"")-ROW(IRTL!$A$7:$A$46)/100000,$A11)<=0,"",INDEX(IRTL!$A$7:$A$46,MATCH(LARGE(IRTL!$H$7:$H$46*(IRTL!$L$7:$L$46<>"Complete")*(IRTL!$A$7:$A$46<>"")-ROW(IRTL!$A$7:$A$46)/100000,$A11),IRTL!$H$7:$H$46*(IRTL!$L$7:$L$46<>"Complete")*(IRTL!$A$7:$A$46<>"")-ROW(IRTL!$A$7:$A$46)/100000,0))),"") | C11: =IFERROR(IF(LARGE(IRTL!$H$7:$H$46*(IRTL!$L$7:$L$46<>"Complete")*(IRTL!$A$7:$A$46<>"")-ROW(IRTL!$A$7:$A$46)/100000,$A11)<=0,"",INDEX(IRTL!$E$7:$E$46,MATCH(LARGE(IRTL!$H$7:$H$46*(IRTL!$L$7:$L$46<>"Complete")*(IRTL!$A$7:$A$46<>"")-ROW(IRTL!$A$7:$A$46)/100000,$A11),IRTL!$H$7:$H$46*(IRTL!$L$7:$L$46<>"Complete")*(IRTL!$A$7:$A$46<>"")-ROW(IRTL!$A$7:$A$46)/100000,0))),"") | D11: =IFERROR(IF(LARGE(IRTL!$H$7:$H$46*(IRTL!$L$7:$L$46<>"Complete")*(IRTL!$A$7:$A$46<>"")-ROW(IRTL!$A$7:$A$46)/100000,$A11)<=0,"",INDEX(IRTL!$F$7:$F$46,MATCH(LARGE(IRTL!$H$7:$H$46*(IRTL!$L$7:$L$46<>"Complete")*(IRTL!$A$7:$A$46<>"")-ROW(IRTL!$A$7:$A$46)/100000,$A11),IRTL!$H$7:$H$46*(IRTL!$L$7:$L$46<>"Complete")*(IRTL!$A$7:$A$46<>"")-ROW(IRTL!$A$7:$A$46)/100000,0))),"") | E11: =IFERROR(IF(LARGE(IRTL!$H$7:$H$46*(IRTL!$L$7:$L$46<>"Complete")*(IRTL!$A$7:$A$46<>"")-ROW(IRTL!$A$7:$A$46)/100000,$A11)<=0,"",INDEX(IRTL!$G$7:$G$46,MATCH(LARGE(IRTL!$H$7:$H$46*(IRTL!$L$7:$L$46<>"Complete")*(IRTL!$A$7:$A$46<>"")-ROW(IRTL!$A$7:$A$46)/100000,$A11),IRTL!$H$7:$H$46*(IRTL!$L$7:$L$46<>"Complete")*(IRTL!$A$7:$A$46<>"")-ROW(IRTL!$A$7:$A$46)/100000,0))),"") | F11: =IFERROR(IF(LARGE(IRTL!$H$7:$H$46*(IRTL!$L$7:$L$46<>"Complete")*(IRTL!$A$7:$A$46<>"")-ROW(IRTL!$A$7:$A$46)/100000,$A11)<=0,"",INDEX(IRTL!$H$7:$H$46,MATCH(LARGE(IRTL!$H$7:$H$46*(IRTL!$L$7:$L$46<>"Complete")*(IRTL!$A$7:$A$46<>"")-ROW(IRTL!$A$7:$A$46)/100000,$A11),IRTL!$H$7:$H$46*(IRTL!$L$7:$L$46<>"Complete")*(IRTL!$A$7:$A$46<>"")-ROW(IRTL!$A$7:$A$46)/100000,0))),"") | G11: =IFERROR(IF(LARGE(IRTL!$H$7:$H$46*(IRTL!$L$7:$L$46<>"Complete")*(IRTL!$A$7:$A$46<>"")-ROW(IRTL!$A$7:$A$46)/100000,$A11)<=0,"",INDEX(IRTL!$I$7:$I$46,MATCH(LARGE(IRTL!$H$7:$H$46*(IRTL!$L$7:$L$46<>"Complete")*(IRTL!$A$7:$A$46<>"")-ROW(IRTL!$A$7:$A$46)/100000,$A11),IRTL!$H$7:$H$46*(IRTL!$L$7:$L$46<>"Complete")*(IRTL!$A$7:$A$46<>"")-ROW(IRTL!$A$7:$A$46)/100000,0))),"") | H11: =IFERROR(IF(LARGE(IRTL!$H$7:$H$46*(IRTL!$L$7:$L$46<>"Complete")*(IRTL!$A$7:$A$46<>"")-ROW(IRTL!$A$7:$A$46)/100000,$A11)<=0,"",INDEX(IRTL!$K$7:$K$46,MATCH(LARGE(IRTL!$H$7:$H$46*(IRTL!$L$7:$L$46<>"Complete")*(IRTL!$A$7:$A$46<>"")-ROW(IRTL!$A$7:$A$46)/100000,$A11),IRTL!$H$7:$H$46*(IRTL!$L$7:$L$46<>"Complete")*(IRTL!$A$7:$A$46<>"")-ROW(IRTL!$A$7:$A$46)/100000,0))),"") | I11: =IFERROR(IF(LARGE(IRTL!$H$7:$H$46*(IRTL!$L$7:$L$46<>"Complete")*(IRTL!$A$7:$A$46<>"")-ROW(IRTL!$A$7:$A$46)/100000,$A11)<=0,"",INDEX(IRTL!$L$7:$L$46,MATCH(LARGE(IRTL!$H$7:$H$46*(IRTL!$L$7:$L$46<>"Complete")*(IRTL!$A$7:$A$46<>"")-ROW(IRTL!$A$7:$A$46)/100000,$A11),IRTL!$H$7:$H$46*(IRTL!$L$7:$L$46<>"Complete")*(IRTL!$A$7:$A$46<>"")-ROW(IRTL!$A$7:$A$46)/100000,0))),"") | J11: =IFERROR(IF(LARGE(IRTL!$H$7:$H$46*(IRTL!$L$7:$L$46<>"Complete")*(IRTL!$A$7:$A$46<>"")-ROW(IRTL!$A$7:$A$46)/100000,$A11)<=0,"",INDEX(IRTL!$J$7:$J$46,MATCH(LARGE(IRTL!$H$7:$H$46*(IRTL!$L$7:$L$46<>"Complete")*(IRTL!$A$7:$A$46<>"")-ROW(IRTL!$A$7:$A$46)/100000,$A11),IRTL!$H$7:$H$46*(IRTL!$L$7:$L$46<>"Complete")*(IRTL!$A$7:$A$46<>"")-ROW(IRTL!$A$7:$A$46)/100000,0))),"")
A12: 6 | B12: =IFERROR(IF(LARGE(IRTL!$H$7:$H$46*(IRTL!$L$7:$L$46<>"Complete")*(IRTL!$A$7:$A$46<>"")-ROW(IRTL!$A$7:$A$46)/100000,$A12)<=0,"",INDEX(IRTL!$A$7:$A$46,MATCH(LARGE(IRTL!$H$7:$H$46*(IRTL!$L$7:$L$46<>"Complete")*(IRTL!$A$7:$A$46<>"")-ROW(IRTL!$A$7:$A$46)/100000,$A12),IRTL!$H$7:$H$46*(IRTL!$L$7:$L$46<>"Complete")*(IRTL!$A$7:$A$46<>"")-ROW(IRTL!$A$7:$A$46)/100000,0))),"") | C12: =IFERROR(IF(LARGE(IRTL!$H$7:$H$46*(IRTL!$L$7:$L$46<>"Complete")*(IRTL!$A$7:$A$46<>"")-ROW(IRTL!$A$7:$A$46)/100000,$A12)<=0,"",INDEX(IRTL!$E$7:$E$46,MATCH(LARGE(IRTL!$H$7:$H$46*(IRTL!$L$7:$L$46<>"Complete")*(IRTL!$A$7:$A$46<>"")-ROW(IRTL!$A$7:$A$46)/100000,$A12),IRTL!$H$7:$H$46*(IRTL!$L$7:$L$46<>"Complete")*(IRTL!$A$7:$A$46<>"")-ROW(IRTL!$A$7:$A$46)/100000,0))),"") | D12: =IFERROR(IF(LARGE(IRTL!$H$7:$H$46*(IRTL!$L$7:$L$46<>"Complete")*(IRTL!$A$7:$A$46<>"")-ROW(IRTL!$A$7:$A$46)/100000,$A12)<=0,"",INDEX(IRTL!$F$7:$F$46,MATCH(LARGE(IRTL!$H$7:$H$46*(IRTL!$L$7:$L$46<>"Complete")*(IRTL!$A$7:$A$46<>"")-ROW(IRTL!$A$7:$A$46)/100000,$A12),IRTL!$H$7:$H$46*(IRTL!$L$7:$L$46<>"Complete")*(IRTL!$A$7:$A$46<>"")-ROW(IRTL!$A$7:$A$46)/100000,0))),"") | E12: =IFERROR(IF(LARGE(IRTL!$H$7:$H$46*(IRTL!$L$7:$L$46<>"Complete")*(IRTL!$A$7:$A$46<>"")-ROW(IRTL!$A$7:$A$46)/100000,$A12)<=0,"",INDEX(IRTL!$G$7:$G$46,MATCH(LARGE(IRTL!$H$7:$H$46*(IRTL!$L$7:$L$46<>"Complete")*(IRTL!$A$7:$A$46<>"")-ROW(IRTL!$A$7:$A$46)/100000,$A12),IRTL!$H$7:$H$46*(IRTL!$L$7:$L$46<>"Complete")*(IRTL!$A$7:$A$46<>"")-ROW(IRTL!$A$7:$A$46)/100000,0))),"") | F12: =IFERROR(IF(LARGE(IRTL!$H$7:$H$46*(IRTL!$L$7:$L$46<>"Complete")*(IRTL!$A$7:$A$46<>"")-ROW(IRTL!$A$7:$A$46)/100000,$A12)<=0,"",INDEX(IRTL!$H$7:$H$46,MATCH(LARGE(IRTL!$H$7:$H$46*(IRTL!$L$7:$L$46<>"Complete")*(IRTL!$A$7:$A$46<>"")-ROW(IRTL!$A$7:$A$46)/100000,$A12),IRTL!$H$7:$H$46*(IRTL!$L$7:$L$46<>"Complete")*(IRTL!$A$7:$A$46<>"")-ROW(IRTL!$A$7:$A$46)/100000,0))),"") | G12: =IFERROR(IF(LARGE(IRTL!$H$7:$H$46*(IRTL!$L$7:$L$46<>"Complete")*(IRTL!$A$7:$A$46<>"")-ROW(IRTL!$A$7:$A$46)/100000,$A12)<=0,"",INDEX(IRTL!$I$7:$I$46,MATCH(LARGE(IRTL!$H$7:$H$46*(IRTL!$L$7:$L$46<>"Complete")*(IRTL!$A$7:$A$46<>"")-ROW(IRTL!$A$7:$A$46)/100000,$A12),IRTL!$H$7:$H$46*(IRTL!$L$7:$L$46<>"Complete")*(IRTL!$A$7:$A$46<>"")-ROW(IRTL!$A$7:$A$46)/100000,0))),"") | H12: =IFERROR(IF(LARGE(IRTL!$H$7:$H$46*(IRTL!$L$7:$L$46<>"Complete")*(IRTL!$A$7:$A$46<>"")-ROW(IRTL!$A$7:$A$46)/100000,$A12)<=0,"",INDEX(IRTL!$K$7:$K$46,MATCH(LARGE(IRTL!$H$7:$H$46*(IRTL!$L$7:$L$46<>"Complete")*(IRTL!$A$7:$A$46<>"")-ROW(IRTL!$A$7:$A$46)/100000,$A12),IRTL!$H$7:$H$46*(IRTL!$L$7:$L$46<>"Complete")*(IRTL!$A$7:$A$46<>"")-ROW(IRTL!$A$7:$A$46)/100000,0))),"") | I12: =IFERROR(IF(LARGE(IRTL!$H$7:$H$46*(IRTL!$L$7:$L$46<>"Complete")*(IRTL!$A$7:$A$46<>"")-ROW(IRTL!$A$7:$A$46)/100000,$A12)<=0,"",INDEX(IRTL!$L$7:$L$46,MATCH(LARGE(IRTL!$H$7:$H$46*(IRTL!$L$7:$L$46<>"Complete")*(IRTL!$A$7:$A$46<>"")-ROW(IRTL!$A$7:$A$46)/100000,$A12),IRTL!$H$7:$H$46*(IRTL!$L$7:$L$46<>"Complete")*(IRTL!$A$7:$A$46<>"")-ROW(IRTL!$A$7:$A$46)/100000,0))),"") | J12: =IFERROR(IF(LARGE(IRTL!$H$7:$H$46*(IRTL!$L$7:$L$46<>"Complete")*(IRTL!$A$7:$A$46<>"")-ROW(IRTL!$A$7:$A$46)/100000,$A12)<=0,"",INDEX(IRTL!$J$7:$J$46,MATCH(LARGE(IRTL!$H$7:$H$46*(IRTL!$L$7:$L$46<>"Complete")*(IRTL!$A$7:$A$46<>"")-ROW(IRTL!$A$7:$A$46)/100000,$A12),IRTL!$H$7:$H$46*(IRTL!$L$7:$L$46<>"Complete")*(IRTL!$A$7:$A$46<>"")-ROW(IRTL!$A$7:$A$46)/100000,0))),"")
A13: 7 | B13: =IFERROR(IF(LARGE(IRTL!$H$7:$H$46*(IRTL!$L$7:$L$46<>"Complete")*(IRTL!$A$7:$A$46<>"")-ROW(IRTL!$A$7:$A$46)/100000,$A13)<=0,"",INDEX(IRTL!$A$7:$A$46,MATCH(LARGE(IRTL!$H$7:$H$46*(IRTL!$L$7:$L$46<>"Complete")*(IRTL!$A$7:$A$46<>"")-ROW(IRTL!$A$7:$A$46)/100000,$A13),IRTL!$H$7:$H$46*(IRTL!$L$7:$L$46<>"Complete")*(IRTL!$A$7:$A$46<>"")-ROW(IRTL!$A$7:$A$46)/100000,0))),"") | C13: =IFERROR(IF(LARGE(IRTL!$H$7:$H$46*(IRTL!$L$7:$L$46<>"Complete")*(IRTL!$A$7:$A$46<>"")-ROW(IRTL!$A$7:$A$46)/100000,$A13)<=0,"",INDEX(IRTL!$E$7:$E$46,MATCH(LARGE(IRTL!$H$7:$H$46*(IRTL!$L$7:$L$46<>"Complete")*(IRTL!$A$7:$A$46<>"")-ROW(IRTL!$A$7:$A$46)/100000,$A13),IRTL!$H$7:$H$46*(IRTL!$L$7:$L$46<>"Complete")*(IRTL!$A$7:$A$46<>"")-ROW(IRTL!$A$7:$A$46)/100000,0))),"") | D13: =IFERROR(IF(LARGE(IRTL!$H$7:$H$46*(IRTL!$L$7:$L$46<>"Complete")*(IRTL!$A$7:$A$46<>"")-ROW(IRTL!$A$7:$A$46)/100000,$A13)<=0,"",INDEX(IRTL!$F$7:$F$46,MATCH(LARGE(IRTL!$H$7:$H$46*(IRTL!$L$7:$L$46<>"Complete")*(IRTL!$A$7:$A$46<>"")-ROW(IRTL!$A$7:$A$46)/100000,$A13),IRTL!$H$7:$H$46*(IRTL!$L$7:$L$46<>"Complete")*(IRTL!$A$7:$A$46<>"")-ROW(IRTL!$A$7:$A$46)/100000,0))),"") | E13: =IFERROR(IF(LARGE(IRTL!$H$7:$H$46*(IRTL!$L$7:$L$46<>"Complete")*(IRTL!$A$7:$A$46<>"")-ROW(IRTL!$A$7:$A$46)/100000,$A13)<=0,"",INDEX(IRTL!$G$7:$G$46,MATCH(LARGE(IRTL!$H$7:$H$46*(IRTL!$L$7:$L$46<>"Complete")*(IRTL!$A$7:$A$46<>"")-ROW(IRTL!$A$7:$A$46)/100000,$A13),IRTL!$H$7:$H$46*(IRTL!$L$7:$L$46<>"Complete")*(IRTL!$A$7:$A$46<>"")-ROW(IRTL!$A$7:$A$46)/100000,0))),"") | F13: =IFERROR(IF(LARGE(IRTL!$H$7:$H$46*(IRTL!$L$7:$L$46<>"Complete")*(IRTL!$A$7:$A$46<>"")-ROW(IRTL!$A$7:$A$46)/100000,$A13)<=0,"",INDEX(IRTL!$H$7:$H$46,MATCH(LARGE(IRTL!$H$7:$H$46*(IRTL!$L$7:$L$46<>"Complete")*(IRTL!$A$7:$A$46<>"")-ROW(IRTL!$A$7:$A$46)/100000,$A13),IRTL!$H$7:$H$46*(IRTL!$L$7:$L$46<>"Complete")*(IRTL!$A$7:$A$46<>"")-ROW(IRTL!$A$7:$A$46)/100000,0))),"") | G13: =IFERROR(IF(LARGE(IRTL!$H$7:$H$46*(IRTL!$L$7:$L$46<>"Complete")*(IRTL!$A$7:$A$46<>"")-ROW(IRTL!$A$7:$A$46)/100000,$A13)<=0,"",INDEX(IRTL!$I$7:$I$46,MATCH(LARGE(IRTL!$H$7:$H$46*(IRTL!$L$7:$L$46<>"Complete")*(IRTL!$A$7:$A$46<>"")-ROW(IRTL!$A$7:$A$46)/100000,$A13),IRTL!$H$7:$H$46*(IRTL!$L$7:$L$46<>"Complete")*(IRTL!$A$7:$A$46<>"")-ROW(IRTL!$A$7:$A$46)/100000,0))),"") | H13: =IFERROR(IF(LARGE(IRTL!$H$7:$H$46*(IRTL!$L$7:$L$46<>"Complete")*(IRTL!$A$7:$A$46<>"")-ROW(IRTL!$A$7:$A$46)/100000,$A13)<=0,"",INDEX(IRTL!$K$7:$K$46,MATCH(LARGE(IRTL!$H$7:$H$46*(IRTL!$L$7:$L$46<>"Complete")*(IRTL!$A$7:$A$46<>"")-ROW(IRTL!$A$7:$A$46)/100000,$A13),IRTL!$H$7:$H$46*(IRTL!$L$7:$L$46<>"Complete")*(IRTL!$A$7:$A$46<>"")-ROW(IRTL!$A$7:$A$46)/100000,0))),"") | I13: =IFERROR(IF(LARGE(IRTL!$H$7:$H$46*(IRTL!$L$7:$L$46<>"Complete")*(IRTL!$A$7:$A$46<>"")-ROW(IRTL!$A$7:$A$46)/100000,$A13)<=0,"",INDEX(IRTL!$L$7:$L$46,MATCH(LARGE(IRTL!$H$7:$H$46*(IRTL!$L$7:$L$46<>"Complete")*(IRTL!$A$7:$A$46<>"")-ROW(IRTL!$A$7:$A$46)/100000,$A13),IRTL!$H$7:$H$46*(IRTL!$L$7:$L$46<>"Complete")*(IRTL!$A$7:$A$46<>"")-ROW(IRTL!$A$7:$A$46)/100000,0))),"") | J13: =IFERROR(IF(LARGE(IRTL!$H$7:$H$46*(IRTL!$L$7:$L$46<>"Complete")*(IRTL!$A$7:$A$46<>"")-ROW(IRTL!$A$7:$A$46)/100000,$A13)<=0,"",INDEX(IRTL!$J$7:$J$46,MATCH(LARGE(IRTL!$H$7:$H$46*(IRTL!$L$7:$L$46<>"Complete")*(IRTL!$A$7:$A$46<>"")-ROW(IRTL!$A$7:$A$46)/100000,$A13),IRTL!$H$7:$H$46*(IRTL!$L$7:$L$46<>"Complete")*(IRTL!$A$7:$A$46<>"")-ROW(IRTL!$A$7:$A$46)/100000,0))),"")
A14: 8 | B14: =IFERROR(IF(LARGE(IRTL!$H$7:$H$46*(IRTL!$L$7:$L$46<>"Complete")*(IRTL!$A$7:$A$46<>"")-ROW(IRTL!$A$7:$A$46)/100000,$A14)<=0,"",INDEX(IRTL!$A$7:$A$46,MATCH(LARGE(IRTL!$H$7:$H$46*(IRTL!$L$7:$L$46<>"Complete")*(IRTL!$A$7:$A$46<>"")-ROW(IRTL!$A$7:$A$46)/100000,$A14),IRTL!$H$7:$H$46*(IRTL!$L$7:$L$46<>"Complete")*(IRTL!$A$7:$A$46<>"")-ROW(IRTL!$A$7:$A$46)/100000,0))),"") | C14: =IFERROR(IF(LARGE(IRTL!$H$7:$H$46*(IRTL!$L$7:$L$46<>"Complete")*(IRTL!$A$7:$A$46<>"")-ROW(IRTL!$A$7:$A$46)/100000,$A14)<=0,"",INDEX(IRTL!$E$7:$E$46,MATCH(LARGE(IRTL!$H$7:$H$46*(IRTL!$L$7:$L$46<>"Complete")*(IRTL!$A$7:$A$46<>"")-ROW(IRTL!$A$7:$A$46)/100000,$A14),IRTL!$H$7:$H$46*(IRTL!$L$7:$L$46<>"Complete")*(IRTL!$A$7:$A$46<>"")-ROW(IRTL!$A$7:$A$46)/100000,0))),"") | D14: =IFERROR(IF(LARGE(IRTL!$H$7:$H$46*(IRTL!$L$7:$L$46<>"Complete")*(IRTL!$A$7:$A$46<>"")-ROW(IRTL!$A$7:$A$46)/100000,$A14)<=0,"",INDEX(IRTL!$F$7:$F$46,MATCH(LARGE(IRTL!$H$7:$H$46*(IRTL!$L$7:$L$46<>"Complete")*(IRTL!$A$7:$A$46<>"")-ROW(IRTL!$A$7:$A$46)/100000,$A14),IRTL!$H$7:$H$46*(IRTL!$L$7:$L$46<>"Complete")*(IRTL!$A$7:$A$46<>"")-ROW(IRTL!$A$7:$A$46)/100000,0))),"") | E14: =IFERROR(IF(LARGE(IRTL!$H$7:$H$46*(IRTL!$L$7:$L$46<>"Complete")*(IRTL!$A$7:$A$46<>"")-ROW(IRTL!$A$7:$A$46)/100000,$A14)<=0,"",INDEX(IRTL!$G$7:$G$46,MATCH(LARGE(IRTL!$H$7:$H$46*(IRTL!$L$7:$L$46<>"Complete")*(IRTL!$A$7:$A$46<>"")-ROW(IRTL!$A$7:$A$46)/100000,$A14),IRTL!$H$7:$H$46*(IRTL!$L$7:$L$46<>"Complete")*(IRTL!$A$7:$A$46<>"")-ROW(IRTL!$A$7:$A$46)/100000,0))),"") | F14: =IFERROR(IF(LARGE(IRTL!$H$7:$H$46*(IRTL!$L$7:$L$46<>"Complete")*(IRTL!$A$7:$A$46<>"")-ROW(IRTL!$A$7:$A$46)/100000,$A14)<=0,"",INDEX(IRTL!$H$7:$H$46,MATCH(LARGE(IRTL!$H$7:$H$46*(IRTL!$L$7:$L$46<>"Complete")*(IRTL!$A$7:$A$46<>"")-ROW(IRTL!$A$7:$A$46)/100000,$A14),IRTL!$H$7:$H$46*(IRTL!$L$7:$L$46<>"Complete")*(IRTL!$A$7:$A$46<>"")-ROW(IRTL!$A$7:$A$46)/100000,0))),"") | G14: =IFERROR(IF(LARGE(IRTL!$H$7:$H$46*(IRTL!$L$7:$L$46<>"Complete")*(IRTL!$A$7:$A$46<>"")-ROW(IRTL!$A$7:$A$46)/100000,$A14)<=0,"",INDEX(IRTL!$I$7:$I$46,MATCH(LARGE(IRTL!$H$7:$H$46*(IRTL!$L$7:$L$46<>"Complete")*(IRTL!$A$7:$A$46<>"")-ROW(IRTL!$A$7:$A$46)/100000,$A14),IRTL!$H$7:$H$46*(IRTL!$L$7:$L$46<>"Complete")*(IRTL!$A$7:$A$46<>"")-ROW(IRTL!$A$7:$A$46)/100000,0))),"") | H14: =IFERROR(IF(LARGE(IRTL!$H$7:$H$46*(IRTL!$L$7:$L$46<>"Complete")*(IRTL!$A$7:$A$46<>"")-ROW(IRTL!$A$7:$A$46)/100000,$A14)<=0,"",INDEX(IRTL!$K$7:$K$46,MATCH(LARGE(IRTL!$H$7:$H$46*(IRTL!$L$7:$L$46<>"Complete")*(IRTL!$A$7:$A$46<>"")-ROW(IRTL!$A$7:$A$46)/100000,$A14),IRTL!$H$7:$H$46*(IRTL!$L$7:$L$46<>"Complete")*(IRTL!$A$7:$A$46<>"")-ROW(IRTL!$A$7:$A$46)/100000,0))),"") | I14: =IFERROR(IF(LARGE(IRTL!$H$7:$H$46*(IRTL!$L$7:$L$46<>"Complete")*(IRTL!$A$7:$A$46<>"")-ROW(IRTL!$A$7:$A$46)/100000,$A14)<=0,"",INDEX(IRTL!$L$7:$L$46,MATCH(LARGE(IRTL!$H$7:$H$46*(IRTL!$L$7:$L$46<>"Complete")*(IRTL!$A$7:$A$46<>"")-ROW(IRTL!$A$7:$A$46)/100000,$A14),IRTL!$H$7:$H$46*(IRTL!$L$7:$L$46<>"Complete")*(IRTL!$A$7:$A$46<>"")-ROW(IRTL!$A$7:$A$46)/100000,0))),"") | J14: =IFERROR(IF(LARGE(IRTL!$H$7:$H$46*(IRTL!$L$7:$L$46<>"Complete")*(IRTL!$A$7:$A$46<>"")-ROW(IRTL!$A$7:$A$46)/100000,$A14)<=0,"",INDEX(IRTL!$J$7:$J$46,MATCH(LARGE(IRTL!$H$7:$H$46*(IRTL!$L$7:$L$46<>"Complete")*(IRTL!$A$7:$A$46<>"")-ROW(IRTL!$A$7:$A$46)/100000,$A14),IRTL!$H$7:$H$46*(IRTL!$L$7:$L$46<>"Complete")*(IRTL!$A$7:$A$46<>"")-ROW(IRTL!$A$7:$A$46)/100000,0))),"")
A15: 9 | B15: =IFERROR(IF(LARGE(IRTL!$H$7:$H$46*(IRTL!$L$7:$L$46<>"Complete")*(IRTL!$A$7:$A$46<>"")-ROW(IRTL!$A$7:$A$46)/100000,$A15)<=0,"",INDEX(IRTL!$A$7:$A$46,MATCH(LARGE(IRTL!$H$7:$H$46*(IRTL!$L$7:$L$46<>"Complete")*(IRTL!$A$7:$A$46<>"")-ROW(IRTL!$A$7:$A$46)/100000,$A15),IRTL!$H$7:$H$46*(IRTL!$L$7:$L$46<>"Complete")*(IRTL!$A$7:$A$46<>"")-ROW(IRTL!$A$7:$A$46)/100000,0))),"") | C15: =IFERROR(IF(LARGE(IRTL!$H$7:$H$46*(IRTL!$L$7:$L$46<>"Complete")*(IRTL!$A$7:$A$46<>"")-ROW(IRTL!$A$7:$A$46)/100000,$A15)<=0,"",INDEX(IRTL!$E$7:$E$46,MATCH(LARGE(IRTL!$H$7:$H$46*(IRTL!$L$7:$L$46<>"Complete")*(IRTL!$A$7:$A$46<>"")-ROW(IRTL!$A$7:$A$46)/100000,$A15),IRTL!$H$7:$H$46*(IRTL!$L$7:$L$46<>"Complete")*(IRTL!$A$7:$A$46<>"")-ROW(IRTL!$A$7:$A$46)/100000,0))),"") | D15: =IFERROR(IF(LARGE(IRTL!$H$7:$H$46*(IRTL!$L$7:$L$46<>"Complete")*(IRTL!$A$7:$A$46<>"")-ROW(IRTL!$A$7:$A$46)/100000,$A15)<=0,"",INDEX(IRTL!$F$7:$F$46,MATCH(LARGE(IRTL!$H$7:$H$46*(IRTL!$L$7:$L$46<>"Complete")*(IRTL!$A$7:$A$46<>"")-ROW(IRTL!$A$7:$A$46)/100000,$A15),IRTL!$H$7:$H$46*(IRTL!$L$7:$L$46<>"Complete")*(IRTL!$A$7:$A$46<>"")-ROW(IRTL!$A$7:$A$46)/100000,0))),"") | E15: =IFERROR(IF(LARGE(IRTL!$H$7:$H$46*(IRTL!$L$7:$L$46<>"Complete")*(IRTL!$A$7:$A$46<>"")-ROW(IRTL!$A$7:$A$46)/100000,$A15)<=0,"",INDEX(IRTL!$G$7:$G$46,MATCH(LARGE(IRTL!$H$7:$H$46*(IRTL!$L$7:$L$46<>"Complete")*(IRTL!$A$7:$A$46<>"")-ROW(IRTL!$A$7:$A$46)/100000,$A15),IRTL!$H$7:$H$46*(IRTL!$L$7:$L$46<>"Complete")*(IRTL!$A$7:$A$46<>"")-ROW(IRTL!$A$7:$A$46)/100000,0))),"") | F15: =IFERROR(IF(LARGE(IRTL!$H$7:$H$46*(IRTL!$L$7:$L$46<>"Complete")*(IRTL!$A$7:$A$46<>"")-ROW(IRTL!$A$7:$A$46)/100000,$A15)<=0,"",INDEX(IRTL!$H$7:$H$46,MATCH(LARGE(IRTL!$H$7:$H$46*(IRTL!$L$7:$L$46<>"Complete")*(IRTL!$A$7:$A$46<>"")-ROW(IRTL!$A$7:$A$46)/100000,$A15),IRTL!$H$7:$H$46*(IRTL!$L$7:$L$46<>"Complete")*(IRTL!$A$7:$A$46<>"")-ROW(IRTL!$A$7:$A$46)/100000,0))),"") | G15: =IFERROR(IF(LARGE(IRTL!$H$7:$H$46*(IRTL!$L$7:$L$46<>"Complete")*(IRTL!$A$7:$A$46<>"")-ROW(IRTL!$A$7:$A$46)/100000,$A15)<=0,"",INDEX(IRTL!$I$7:$I$46,MATCH(LARGE(IRTL!$H$7:$H$46*(IRTL!$L$7:$L$46<>"Complete")*(IRTL!$A$7:$A$46<>"")-ROW(IRTL!$A$7:$A$46)/100000,$A15),IRTL!$H$7:$H$46*(IRTL!$L$7:$L$46<>"Complete")*(IRTL!$A$7:$A$46<>"")-ROW(IRTL!$A$7:$A$46)/100000,0))),"") | H15: =IFERROR(IF(LARGE(IRTL!$H$7:$H$46*(IRTL!$L$7:$L$46<>"Complete")*(IRTL!$A$7:$A$46<>"")-ROW(IRTL!$A$7:$A$46)/100000,$A15)<=0,"",INDEX(IRTL!$K$7:$K$46,MATCH(LARGE(IRTL!$H$7:$H$46*(IRTL!$L$7:$L$46<>"Complete")*(IRTL!$A$7:$A$46<>"")-ROW(IRTL!$A$7:$A$46)/100000,$A15),IRTL!$H$7:$H$46*(IRTL!$L$7:$L$46<>"Complete")*(IRTL!$A$7:$A$46<>"")-ROW(IRTL!$A$7:$A$46)/100000,0))),"") | I15: =IFERROR(IF(LARGE(IRTL!$H$7:$H$46*(IRTL!$L$7:$L$46<>"Complete")*(IRTL!$A$7:$A$46<>"")-ROW(IRTL!$A$7:$A$46)/100000,$A15)<=0,"",INDEX(IRTL!$L$7:$L$46,MATCH(LARGE(IRTL!$H$7:$H$46*(IRTL!$L$7:$L$46<>"Complete")*(IRTL!$A$7:$A$46<>"")-ROW(IRTL!$A$7:$A$46)/100000,$A15),IRTL!$H$7:$H$46*(IRTL!$L$7:$L$46<>"Complete")*(IRTL!$A$7:$A$46<>"")-ROW(IRTL!$A$7:$A$46)/100000,0))),"") | J15: =IFERROR(IF(LARGE(IRTL!$H$7:$H$46*(IRTL!$L$7:$L$46<>"Complete")*(IRTL!$A$7:$A$46<>"")-ROW(IRTL!$A$7:$A$46)/100000,$A15)<=0,"",INDEX(IRTL!$J$7:$J$46,MATCH(LARGE(IRTL!$H$7:$H$46*(IRTL!$L$7:$L$46<>"Complete")*(IRTL!$A$7:$A$46<>"")-ROW(IRTL!$A$7:$A$46)/100000,$A15),IRTL!$H$7:$H$46*(IRTL!$L$7:$L$46<>"Complete")*(IRTL!$A$7:$A$46<>"")-ROW(IRTL!$A$7:$A$46)/100000,0))),"")
A16: 10 | B16: =IFERROR(IF(LARGE(IRTL!$H$7:$H$46*(IRTL!$L$7:$L$46<>"Complete")*(IRTL!$A$7:$A$46<>"")-ROW(IRTL!$A$7:$A$46)/100000,$A16)<=0,"",INDEX(IRTL!$A$7:$A$46,MATCH(LARGE(IRTL!$H$7:$H$46*(IRTL!$L$7:$L$46<>"Complete")*(IRTL!$A$7:$A$46<>"")-ROW(IRTL!$A$7:$A$46)/100000,$A16),IRTL!$H$7:$H$46*(IRTL!$L$7:$L$46<>"Complete")*(IRTL!$A$7:$A$46<>"")-ROW(IRTL!$A$7:$A$46)/100000,0))),"") | C16: =IFERROR(IF(LARGE(IRTL!$H$7:$H$46*(IRTL!$L$7:$L$46<>"Complete")*(IRTL!$A$7:$A$46<>"")-ROW(IRTL!$A$7:$A$46)/100000,$A16)<=0,"",INDEX(IRTL!$E$7:$E$46,MATCH(LARGE(IRTL!$H$7:$H$46*(IRTL!$L$7:$L$46<>"Complete")*(IRTL!$A$7:$A$46<>"")-ROW(IRTL!$A$7:$A$46)/100000,$A16),IRTL!$H$7:$H$46*(IRTL!$L$7:$L$46<>"Complete")*(IRTL!$A$7:$A$46<>"")-ROW(IRTL!$A$7:$A$46)/100000,0))),"") | D16: =IFERROR(IF(LARGE(IRTL!$H$7:$H$46*(IRTL!$L$7:$L$46<>"Complete")*(IRTL!$A$7:$A$46<>"")-ROW(IRTL!$A$7:$A$46)/100000,$A16)<=0,"",INDEX(IRTL!$F$7:$F$46,MATCH(LARGE(IRTL!$H$7:$H$46*(IRTL!$L$7:$L$46<>"Complete")*(IRTL!$A$7:$A$46<>"")-ROW(IRTL!$A$7:$A$46)/100000,$A16),IRTL!$H$7:$H$46*(IRTL!$L$7:$L$46<>"Complete")*(IRTL!$A$7:$A$46<>"")-ROW(IRTL!$A$7:$A$46)/100000,0))),"") | E16: =IFERROR(IF(LARGE(IRTL!$H$7:$H$46*(IRTL!$L$7:$L$46<>"Complete")*(IRTL!$A$7:$A$46<>"")-ROW(IRTL!$A$7:$A$46)/100000,$A16)<=0,"",INDEX(IRTL!$G$7:$G$46,MATCH(LARGE(IRTL!$H$7:$H$46*(IRTL!$L$7:$L$46<>"Complete")*(IRTL!$A$7:$A$46<>"")-ROW(IRTL!$A$7:$A$46)/100000,$A16),IRTL!$H$7:$H$46*(IRTL!$L$7:$L$46<>"Complete")*(IRTL!$A$7:$A$46<>"")-ROW(IRTL!$A$7:$A$46)/100000,0))),"") | F16: =IFERROR(IF(LARGE(IRTL!$H$7:$H$46*(IRTL!$L$7:$L$46<>"Complete")*(IRTL!$A$7:$A$46<>"")-ROW(IRTL!$A$7:$A$46)/100000,$A16)<=0,"",INDEX(IRTL!$H$7:$H$46,MATCH(LARGE(IRTL!$H$7:$H$46*(IRTL!$L$7:$L$46<>"Complete")*(IRTL!$A$7:$A$46<>"")-ROW(IRTL!$A$7:$A$46)/100000,$A16),IRTL!$H$7:$H$46*(IRTL!$L$7:$L$46<>"Complete")*(IRTL!$A$7:$A$46<>"")-ROW(IRTL!$A$7:$A$46)/100000,0))),"") | G16: =IFERROR(IF(LARGE(IRTL!$H$7:$H$46*(IRTL!$L$7:$L$46<>"Complete")*(IRTL!$A$7:$A$46<>"")-ROW(IRTL!$A$7:$A$46)/100000,$A16)<=0,"",INDEX(IRTL!$I$7:$I$46,MATCH(LARGE(IRTL!$H$7:$H$46*(IRTL!$L$7:$L$46<>"Complete")*(IRTL!$A$7:$A$46<>"")-ROW(IRTL!$A$7:$A$46)/100000,$A16),IRTL!$H$7:$H$46*(IRTL!$L$7:$L$46<>"Complete")*(IRTL!$A$7:$A$46<>"")-ROW(IRTL!$A$7:$A$46)/100000,0))),"") | H16: =IFERROR(IF(LARGE(IRTL!$H$7:$H$46*(IRTL!$L$7:$L$46<>"Complete")*(IRTL!$A$7:$A$46<>"")-ROW(IRTL!$A$7:$A$46)/100000,$A16)<=0,"",INDEX(IRTL!$K$7:$K$46,MATCH(LARGE(IRTL!$H$7:$H$46*(IRTL!$L$7:$L$46<>"Complete")*(IRTL!$A$7:$A$46<>"")-ROW(IRTL!$A$7:$A$46)/100000,$A16),IRTL!$H$7:$H$46*(IRTL!$L$7:$L$46<>"Complete")*(IRTL!$A$7:$A$46<>"")-ROW(IRTL!$A$7:$A$46)/100000,0))),"") | I16: =IFERROR(IF(LARGE(IRTL!$H$7:$H$46*(IRTL!$L$7:$L$46<>"Complete")*(IRTL!$A$7:$A$46<>"")-ROW(IRTL!$A$7:$A$46)/100000,$A16)<=0,"",INDEX(IRTL!$L$7:$L$46,MATCH(LARGE(IRTL!$H$7:$H$46*(IRTL!$L$7:$L$46<>"Complete")*(IRTL!$A$7:$A$46<>"")-ROW(IRTL!$A$7:$A$46)/100000,$A16),IRTL!$H$7:$H$46*(IRTL!$L$7:$L$46<>"Complete")*(IRTL!$A$7:$A$46<>"")-ROW(IRTL!$A$7:$A$46)/100000,0))),"") | J16: =IFERROR(IF(LARGE(IRTL!$H$7:$H$46*(IRTL!$L$7:$L$46<>"Complete")*(IRTL!$A$7:$A$46<>"")-ROW(IRTL!$A$7:$A$46)/100000,$A16)<=0,"",INDEX(IRTL!$J$7:$J$46,MATCH(LARGE(IRTL!$H$7:$H$46*(IRTL!$L$7:$L$46<>"Complete")*(IRTL!$A$7:$A$46<>"")-ROW(IRTL!$A$7:$A$46)/100000,$A16),IRTL!$H$7:$H$46*(IRTL!$L$7:$L$46<>"Complete")*(IRTL!$A$7:$A$46<>"")-ROW(IRTL!$A$7:$A$46)/100000,0))),"")
A17: 11 | B17: =IFERROR(IF(LARGE(IRTL!$H$7:$H$46*(IRTL!$L$7:$L$46<>"Complete")*(IRTL!$A$7:$A$46<>"")-ROW(IRTL!$A$7:$A$46)/100000,$A17)<=0,"",INDEX(IRTL!$A$7:$A$46,MATCH(LARGE(IRTL!$H$7:$H$46*(IRTL!$L$7:$L$46<>"Complete")*(IRTL!$A$7:$A$46<>"")-ROW(IRTL!$A$7:$A$46)/100000,$A17),IRTL!$H$7:$H$46*(IRTL!$L$7:$L$46<>"Complete")*(IRTL!$A$7:$A$46<>"")-ROW(IRTL!$A$7:$A$46)/100000,0))),"") | C17: =IFERROR(IF(LARGE(IRTL!$H$7:$H$46*(IRTL!$L$7:$L$46<>"Complete")*(IRTL!$A$7:$A$46<>"")-ROW(IRTL!$A$7:$A$46)/100000,$A17)<=0,"",INDEX(IRTL!$E$7:$E$46,MATCH(LARGE(IRTL!$H$7:$H$46*(IRTL!$L$7:$L$46<>"Complete")*(IRTL!$A$7:$A$46<>"")-ROW(IRTL!$A$7:$A$46)/100000,$A17),IRTL!$H$7:$H$46*(IRTL!$L$7:$L$46<>"Complete")*(IRTL!$A$7:$A$46<>"")-ROW(IRTL!$A$7:$A$46)/100000,0))),"") | D17: =IFERROR(IF(LARGE(IRTL!$H$7:$H$46*(IRTL!$L$7:$L$46<>"Complete")*(IRTL!$A$7:$A$46<>"")-ROW(IRTL!$A$7:$A$46)/100000,$A17)<=0,"",INDEX(IRTL!$F$7:$F$46,MATCH(LARGE(IRTL!$H$7:$H$46*(IRTL!$L$7:$L$46<>"Complete")*(IRTL!$A$7:$A$46<>"")-ROW(IRTL!$A$7:$A$46)/100000,$A17),IRTL!$H$7:$H$46*(IRTL!$L$7:$L$46<>"Complete")*(IRTL!$A$7:$A$46<>"")-ROW(IRTL!$A$7:$A$46)/100000,0))),"") | E17: =IFERROR(IF(LARGE(IRTL!$H$7:$H$46*(IRTL!$L$7:$L$46<>"Complete")*(IRTL!$A$7:$A$46<>"")-ROW(IRTL!$A$7:$A$46)/100000,$A17)<=0,"",INDEX(IRTL!$G$7:$G$46,MATCH(LARGE(IRTL!$H$7:$H$46*(IRTL!$L$7:$L$46<>"Complete")*(IRTL!$A$7:$A$46<>"")-ROW(IRTL!$A$7:$A$46)/100000,$A17),IRTL!$H$7:$H$46*(IRTL!$L$7:$L$46<>"Complete")*(IRTL!$A$7:$A$46<>"")-ROW(IRTL!$A$7:$A$46)/100000,0))),"") | F17: =IFERROR(IF(LARGE(IRTL!$H$7:$H$46*(IRTL!$L$7:$L$46<>"Complete")*(IRTL!$A$7:$A$46<>"")-ROW(IRTL!$A$7:$A$46)/100000,$A17)<=0,"",INDEX(IRTL!$H$7:$H$46,MATCH(LARGE(IRTL!$H$7:$H$46*(IRTL!$L$7:$L$46<>"Complete")*(IRTL!$A$7:$A$46<>"")-ROW(IRTL!$A$7:$A$46)/100000,$A17),IRTL!$H$7:$H$46*(IRTL!$L$7:$L$46<>"Complete")*(IRTL!$A$7:$A$46<>"")-ROW(IRTL!$A$7:$A$46)/100000,0))),"") | G17: =IFERROR(IF(LARGE(IRTL!$H$7:$H$46*(IRTL!$L$7:$L$46<>"Complete")*(IRTL!$A$7:$A$46<>"")-ROW(IRTL!$A$7:$A$46)/100000,$A17)<=0,"",INDEX(IRTL!$I$7:$I$46,MATCH(LARGE(IRTL!$H$7:$H$46*(IRTL!$L$7:$L$46<>"Complete")*(IRTL!$A$7:$A$46<>"")-ROW(IRTL!$A$7:$A$46)/100000,$A17),IRTL!$H$7:$H$46*(IRTL!$L$7:$L$46<>"Complete")*(IRTL!$A$7:$A$46<>"")-ROW(IRTL!$A$7:$A$46)/100000,0))),"") | H17: =IFERROR(IF(LARGE(IRTL!$H$7:$H$46*(IRTL!$L$7:$L$46<>"Complete")*(IRTL!$A$7:$A$46<>"")-ROW(IRTL!$A$7:$A$46)/100000,$A17)<=0,"",INDEX(IRTL!$K$7:$K$46,MATCH(LARGE(IRTL!$H$7:$H$46*(IRTL!$L$7:$L$46<>"Complete")*(IRTL!$A$7:$A$46<>"")-ROW(IRTL!$A$7:$A$46)/100000,$A17),IRTL!$H$7:$H$46*(IRTL!$L$7:$L$46<>"Complete")*(IRTL!$A$7:$A$46<>"")-ROW(IRTL!$A$7:$A$46)/100000,0))),"") | I17: =IFERROR(IF(LARGE(IRTL!$H$7:$H$46*(IRTL!$L$7:$L$46<>"Complete")*(IRTL!$A$7:$A$46<>"")-ROW(IRTL!$A$7:$A$46)/100000,$A17)<=0,"",INDEX(IRTL!$L$7:$L$46,MATCH(LARGE(IRTL!$H$7:$H$46*(IRTL!$L$7:$L$46<>"Complete")*(IRTL!$A$7:$A$46<>"")-ROW(IRTL!$A$7:$A$46)/100000,$A17),IRTL!$H$7:$H$46*(IRTL!$L$7:$L$46<>"Complete")*(IRTL!$A$7:$A$46<>"")-ROW(IRTL!$A$7:$A$46)/100000,0))),"") | J17: =IFERROR(IF(LARGE(IRTL!$H$7:$H$46*(IRTL!$L$7:$L$46<>"Complete")*(IRTL!$A$7:$A$46<>"")-ROW(IRTL!$A$7:$A$46)/100000,$A17)<=0,"",INDEX(IRTL!$J$7:$J$46,MATCH(LARGE(IRTL!$H$7:$H$46*(IRTL!$L$7:$L$46<>"Complete")*(IRTL!$A$7:$A$46<>"")-ROW(IRTL!$A$7:$A$46)/100000,$A17),IRTL!$H$7:$H$46*(IRTL!$L$7:$L$46<>"Complete")*(IRTL!$A$7:$A$46<>"")-ROW(IRTL!$A$7:$A$46)/100000,0))),"")
A18: 12 | B18: =IFERROR(IF(LARGE(IRTL!$H$7:$H$46*(IRTL!$L$7:$L$46<>"Complete")*(IRTL!$A$7:$A$46<>"")-ROW(IRTL!$A$7:$A$46)/100000,$A18)<=0,"",INDEX(IRTL!$A$7:$A$46,MATCH(LARGE(IRTL!$H$7:$H$46*(IRTL!$L$7:$L$46<>"Complete")*(IRTL!$A$7:$A$46<>"")-ROW(IRTL!$A$7:$A$46)/100000,$A18),IRTL!$H$7:$H$46*(IRTL!$L$7:$L$46<>"Complete")*(IRTL!$A$7:$A$46<>"")-ROW(IRTL!$A$7:$A$46)/100000,0))),"") | C18: =IFERROR(IF(LARGE(IRTL!$H$7:$H$46*(IRTL!$L$7:$L$46<>"Complete")*(IRTL!$A$7:$A$46<>"")-ROW(IRTL!$A$7:$A$46)/100000,$A18)<=0,"",INDEX(IRTL!$E$7:$E$46,MATCH(LARGE(IRTL!$H$7:$H$46*(IRTL!$L$7:$L$46<>"Complete")*(IRTL!$A$7:$A$46<>"")-ROW(IRTL!$A$7:$A$46)/100000,$A18),IRTL!$H$7:$H$46*(IRTL!$L$7:$L$46<>"Complete")*(IRTL!$A$7:$A$46<>"")-ROW(IRTL!$A$7:$A$46)/100000,0))),"") | D18: =IFERROR(IF(LARGE(IRTL!$H$7:$H$46*(IRTL!$L$7:$L$46<>"Complete")*(IRTL!$A$7:$A$46<>"")-ROW(IRTL!$A$7:$A$46)/100000,$A18)<=0,"",INDEX(IRTL!$F$7:$F$46,MATCH(LARGE(IRTL!$H$7:$H$46*(IRTL!$L$7:$L$46<>"Complete")*(IRTL!$A$7:$A$46<>"")-ROW(IRTL!$A$7:$A$46)/100000,$A18),IRTL!$H$7:$H$46*(IRTL!$L$7:$L$46<>"Complete")*(IRTL!$A$7:$A$46<>"")-ROW(IRTL!$A$7:$A$46)/100000,0))),"") | E18: =IFERROR(IF(LARGE(IRTL!$H$7:$H$46*(IRTL!$L$7:$L$46<>"Complete")*(IRTL!$A$7:$A$46<>"")-ROW(IRTL!$A$7:$A$46)/100000,$A18)<=0,"",INDEX(IRTL!$G$7:$G$46,MATCH(LARGE(IRTL!$H$7:$H$46*(IRTL!$L$7:$L$46<>"Complete")*(IRTL!$A$7:$A$46<>"")-ROW(IRTL!$A$7:$A$46)/100000,$A18),IRTL!$H$7:$H$46*(IRTL!$L$7:$L$46<>"Complete")*(IRTL!$A$7:$A$46<>"")-ROW(IRTL!$A$7:$A$46)/100000,0))),"") | F18: =IFERROR(IF(LARGE(IRTL!$H$7:$H$46*(IRTL!$L$7:$L$46<>"Complete")*(IRTL!$A$7:$A$46<>"")-ROW(IRTL!$A$7:$A$46)/100000,$A18)<=0,"",INDEX(IRTL!$H$7:$H$46,MATCH(LARGE(IRTL!$H$7:$H$46*(IRTL!$L$7:$L$46<>"Complete")*(IRTL!$A$7:$A$46<>"")-ROW(IRTL!$A$7:$A$46)/100000,$A18),IRTL!$H$7:$H$46*(IRTL!$L$7:$L$46<>"Complete")*(IRTL!$A$7:$A$46<>"")-ROW(IRTL!$A$7:$A$46)/100000,0))),"") | G18: =IFERROR(IF(LARGE(IRTL!$H$7:$H$46*(IRTL!$L$7:$L$46<>"Complete")*(IRTL!$A$7:$A$46<>"")-ROW(IRTL!$A$7:$A$46)/100000,$A18)<=0,"",INDEX(IRTL!$I$7:$I$46,MATCH(LARGE(IRTL!$H$7:$H$46*(IRTL!$L$7:$L$46<>"Complete")*(IRTL!$A$7:$A$46<>"")-ROW(IRTL!$A$7:$A$46)/100000,$A18),IRTL!$H$7:$H$46*(IRTL!$L$7:$L$46<>"Complete")*(IRTL!$A$7:$A$46<>"")-ROW(IRTL!$A$7:$A$46)/100000,0))),"") | H18: =IFERROR(IF(LARGE(IRTL!$H$7:$H$46*(IRTL!$L$7:$L$46<>"Complete")*(IRTL!$A$7:$A$46<>"")-ROW(IRTL!$A$7:$A$46)/100000,$A18)<=0,"",INDEX(IRTL!$K$7:$K$46,MATCH(LARGE(IRTL!$H$7:$H$46*(IRTL!$L$7:$L$46<>"Complete")*(IRTL!$A$7:$A$46<>"")-ROW(IRTL!$A$7:$A$46)/100000,$A18),IRTL!$H$7:$H$46*(IRTL!$L$7:$L$46<>"Complete")*(IRTL!$A$7:$A$46<>"")-ROW(IRTL!$A$7:$A$46)/100000,0))),"") | I18: =IFERROR(IF(LARGE(IRTL!$H$7:$H$46*(IRTL!$L$7:$L$46<>"Complete")*(IRTL!$A$7:$A$46<>"")-ROW(IRTL!$A$7:$A$46)/100000,$A18)<=0,"",INDEX(IRTL!$L$7:$L$46,MATCH(LARGE(IRTL!$H$7:$H$46*(IRTL!$L$7:$L$46<>"Complete")*(IRTL!$A$7:$A$46<>"")-ROW(IRTL!$A$7:$A$46)/100000,$A18),IRTL!$H$7:$H$46*(IRTL!$L$7:$L$46<>"Complete")*(IRTL!$A$7:$A$46<>"")-ROW(IRTL!$A$7:$A$46)/100000,0))),"") | J18: =IFERROR(IF(LARGE(IRTL!$H$7:$H$46*(IRTL!$L$7:$L$46<>"Complete")*(IRTL!$A$7:$A$46<>"")-ROW(IRTL!$A$7:$A$46)/100000,$A18)<=0,"",INDEX(IRTL!$J$7:$J$46,MATCH(LARGE(IRTL!$H$7:$H$46*(IRTL!$L$7:$L$46<>"Complete")*(IRTL!$A$7:$A$46<>"")-ROW(IRTL!$A$7:$A$46)/100000,$A18),IRTL!$H$7:$H$46*(IRTL!$L$7:$L$46<>"Complete")*(IRTL!$A$7:$A$46<>"")-ROW(IRTL!$A$7:$A$46)/100000,0))),"")
A20: Priority is likelihood times impact
A21: High = 3, Medium = 2, Low = 1, so priority runs from 1 to 9. Six or more needs an owner and a date this week. A risk with no owner is not being managed, it is being hoped about.

Sheet CCR
A1: Form CCR - Configuration Change Request
A2: Once a baseline is agreed with the client, changes go through here - not through a quiet commit.
A4: Team | B4: =SETUP!$C$10 | E4: Requests | F4: =COUNTA(A7:A46) | G4: Approved | H4: =COUNTIF(K7:K46,"Approved") | I4: Added hours | J4: =SUMIF(K7:K46,"Approved",H7:H46)
A6: CCR ID | B6: Date | C6: Raised by | D6: Change type | E6: Component | F6: What changes | G6: Why - whose need does this serve | H6: Est. hrs | I6: M/stone | J6: Reviewer | K6: Decision | L6: Decided on | M6: Notes
A7: CCR-01 | B7: 46322 | C7: Harith Bin Ismail | D7: Requirement | E7: Order entry | F7: Add a free-text note to each order line | G7: Counter staff already write notes on the paper book; without it they will not use the app | H7: 6 | I7: M2 | J7: Aisyah Binti Rahman | K7: Approved | L7: 46324 | M7: Absorbed into the M2 plan
A8: CCR-02 | B8: 46329 | C8: Daniel Wong Jun Hao | D8: Design | E8: Order & catalogue service | F8: Replace the single price field with dated price records | G8: Supplier prices change weekly; an invoice must use the price at order time | H8: 14 | I8: M2 | J8: Aisyah Binti Rahman | K8: Approved | L8: 46331 | M8: Pushed the catalogue work one week; schedule updated
A9: CCR-03 | B9: 46343 | C9: Priya Nair | D9: Requirement | E9: Order entry | F9: Add a Gemini parser for free-text order notes | G9: Staff type faster than they browse; raised after the week 9 demo | H9: 18 | I9: M3 | J9: Aisyah Binti Rahman | K9: Approved | L9: 46345 | M9: Made optional with a manual fallback after the latency test
A10: CCR-04 | B10: 46357 | C10: Harith Bin Ismail | D10: Requirement | E10: Order history | F10: Show all orders rather than the last 30 days | G10: Requested by the client at the week 11 meeting | H10: 10 | I10: M3 | J10: Aisyah Binti Rahman | K10: Deferred | L10: 46359 | M10: Deferred to post-handover; the client agreed 30 days is enough for the pilot
A11: CCR-05 | B11: 46364 | C11: Priya Nair | D11: Code | E11: UI / screens | F11: Increase the base font size at the till | G11: Counter staff could not read the catalogue at arm's length during the acceptance test | H11: 2 | I11: M4 | J11: Aisyah Binti Rahman | K11: Approved | L11: 46366 | M11: Shipped before handover
A12: CCR-06 | B12: 46371 | C12: Mei Ling Chong | D12: Build / CI | E12: SYSTEM | F12: Add a signed release job to the workflow | G12: M4 requires a v1.0.0 release artefact | H12: 4 | I12: M4 | J12: Aisyah Binti Rahman | K12: Approved | L12: 46373 | M12: Done in week 14

Sheet SUMS
A1: Form SUMS - Size Summary
A2: Screens, widgets, services and their size. Without size there is no density, no rate, no learning.
A4: Team | B4: =SETUP!$C$10
G6: PLANNED SIZE | N6: ACTUAL SIZE
A7: ID | B7: Assembly / part name | C7: Type | D7: Parent assembly | E7: Owner | F7: Size measure | G7: Base | H7: Deleted | I7: Modified | J7: Added | K7: Reused | L7: New & changed | M7: Total | N7: Base | O7: Deleted | P7: Modified | Q7: Added | R7: Reused | S7: New & changed | T7: Total
A8: 1 | B8: UI / screens | C8: Part | D8: SYSTEM | E8: Priya Nair | F8: Dart LOC | G8: 0 | H8: 0 | I8: 200 | J8: 1800 | K8: 300 | L8: =IF(COUNT($G8:$K8)=0,"",N($I8)+N($J8)) | M8: =IF(COUNT($G8:$K8)=0,"",N($G8)-N($H8)+N($J8)+N($K8)) | N8: 0 | O8: 0 | P8: 260 | Q8: 1950 | R8: 300 | S8: =IF(COUNT($N8:$R8)=0,"",N($P8)+N($Q8)) | T8: =IF(COUNT($N8:$R8)=0,"",N($N8)-N($O8)+N($Q8)+N($R8))
A9: 2 | B9: Order & catalogue service | C9: Part | D9: SYSTEM | E9: Daniel Wong Jun Hao | F9: Dart LOC | G9: 0 | H9: 0 | I9: 100 | J9: 900 | K9: 150 | L9: =IF(COUNT($G9:$K9)=0,"",N($I9)+N($J9)) | M9: =IF(COUNT($G9:$K9)=0,"",N($G9)-N($H9)+N($J9)+N($K9)) | N9: 0 | O9: 0 | P9: 140 | Q9: 980 | R9: 150 | S9: =IF(COUNT($N9:$R9)=0,"",N($P9)+N($Q9)) | T9: =IF(COUNT($N9:$R9)=0,"",N($N9)-N($O9)+N($Q9)+N($R9))
A10: 3 | B10: Local store & sync | C10: Part | D10: SYSTEM | E10: Mei Ling Chong | F10: Dart LOC | G10: 0 | H10: 0 | I10: 60 | J10: 500 | K10: 80 | L10: =IF(COUNT($G10:$K10)=0,"",N($I10)+N($J10)) | M10: =IF(COUNT($G10:$K10)=0,"",N($G10)-N($H10)+N($J10)+N($K10)) | N10: 0 | O10: 0 | P10: 90 | Q10: 540 | R10: 80 | S10: =IF(COUNT($N10:$R10)=0,"",N($P10)+N($Q10)) | T10: =IF(COUNT($N10:$R10)=0,"",N($N10)-N($O10)+N($Q10)+N($R10))
A11: 4 | B11: Shared widgets & theme | C11: Part | D11: SYSTEM | E11: Mei Ling Chong | F11: Dart LOC | G11: 0 | H11: 0 | I11: 0 | J11: 350 | K11: 0 | L11: =IF(COUNT($G11:$K11)=0,"",N($I11)+N($J11)) | M11: =IF(COUNT($G11:$K11)=0,"",N($G11)-N($H11)+N($J11)+N($K11)) | N11: 0 | O11: 0 | P11: 30 | Q11: 410 | R11: 0 | S11: =IF(COUNT($N11:$R11)=0,"",N($P11)+N($Q11)) | T11: =IF(COUNT($N11:$R11)=0,"",N($N11)-N($O11)+N($Q11)+N($R11))
A12: 5 | B12: Order entry screen | C12: Part | D12: UI / screens | E12: Priya Nair | F12: Screens | G12: 0 | H12: 0 | I12: 0 | J12: 6 | K12: 0 | L12: =IF(COUNT($G12:$K12)=0,"",N($I12)+N($J12)) | M12: =IF(COUNT($G12:$K12)=0,"",N($G12)-N($H12)+N($J12)+N($K12)) | N12: 0 | O12: 0 | P12: 0 | Q12: 7 | R12: 0 | S12: =IF(COUNT($N12:$R12)=0,"",N($P12)+N($Q12)) | T12: =IF(COUNT($N12:$R12)=0,"",N($N12)-N($O12)+N($Q12)+N($R12))
A13: 6 | B13: Catalogue screen | C13: Part | D13: UI / screens | E13: Priya Nair | F13: Screens | G13: 0 | H13: 0 | I13: 0 | J13: 4 | K13: 0 | L13: =IF(COUNT($G13:$K13)=0,"",N($I13)+N($J13)) | M13: =IF(COUNT($G13:$K13)=0,"",N($G13)-N($H13)+N($J13)+N($K13)) | N13: 0 | O13: 0 | P13: 0 | Q13: 5 | R13: 0 | S13: =IF(COUNT($N13:$R13)=0,"",N($P13)+N($Q13)) | T13: =IF(COUNT($N13:$R13)=0,"",N($N13)-N($O13)+N($Q13)+N($R13))
A14: 7 | B14: Invoice & history | C14: Part | D14: UI / screens | E14: Harith Bin Ismail | F14: Screens | G14: 0 | H14: 0 | I14: 0 | J14: 4 | K14: 0 | L14: =IF(COUNT($G14:$K14)=0,"",N($I14)+N($J14)) | M14: =IF(COUNT($G14:$K14)=0,"",N($G14)-N($H14)+N($J14)+N($K14)) | N14: 0 | O14: 0 | P14: 0 | Q14: 4 | R14: 0 | S14: =IF(COUNT($N14:$R14)=0,"",N($P14)+N($Q14)) | T14: =IF(COUNT($N14:$R14)=0,"",N($N14)-N($O14)+N($Q14)+N($R14))
A15: 8 | L15: =IF(COUNT($G15:$K15)=0,"",N($I15)+N($J15)) | M15: =IF(COUNT($G15:$K15)=0,"",N($G15)-N($H15)+N($J15)+N($K15)) | S15: =IF(COUNT($N15:$R15)=0,"",N($P15)+N($Q15)) | T15: =IF(COUNT($N15:$R15)=0,"",N($N15)-N($O15)+N($Q15)+N($R15))
A16: 9 | L16: =IF(COUNT($G16:$K16)=0,"",N($I16)+N($J16)) | M16: =IF(COUNT($G16:$K16)=0,"",N($G16)-N($H16)+N($J16)+N($K16)) | S16: =IF(COUNT($N16:$R16)=0,"",N($P16)+N($Q16)) | T16: =IF(COUNT($N16:$R16)=0,"",N($N16)-N($O16)+N($Q16)+N($R16))
A17: 10 | L17: =IF(COUNT($G17:$K17)=0,"",N($I17)+N($J17)) | M17: =IF(COUNT($G17:$K17)=0,"",N($G17)-N($H17)+N($J17)+N($K17)) | S17: =IF(COUNT($N17:$R17)=0,"",N($P17)+N($Q17)) | T17: =IF(COUNT($N17:$R17)=0,"",N($N17)-N($O17)+N($Q17)+N($R17))
A18: 11 | L18: =IF(COUNT($G18:$K18)=0,"",N($I18)+N($J18)) | M18: =IF(COUNT($G18:$K18)=0,"",N($G18)-N($H18)+N($J18)+N($K18)) | S18: =IF(COUNT($N18:$R18)=0,"",N($P18)+N($Q18)) | T18: =IF(COUNT($N18:$R18)=0,"",N($N18)-N($O18)+N($Q18)+N($R18))
A19: 12 | L19: =IF(COUNT($G19:$K19)=0,"",N($I19)+N($J19)) | M19: =IF(COUNT($G19:$K19)=0,"",N($G19)-N($H19)+N($J19)+N($K19)) | S19: =IF(COUNT($N19:$R19)=0,"",N($P19)+N($Q19)) | T19: =IF(COUNT($N19:$R19)=0,"",N($N19)-N($O19)+N($Q19)+N($R19))
A20: 13 | L20: =IF(COUNT($G20:$K20)=0,"",N($I20)+N($J20)) | M20: =IF(COUNT($G20:$K20)=0,"",N($G20)-N($H20)+N($J20)+N($K20)) | S20: =IF(COUNT($N20:$R20)=0,"",N($P20)+N($Q20)) | T20: =IF(COUNT($N20:$R20)=0,"",N($N20)-N($O20)+N($Q20)+N($R20))
A21: 14 | L21: =IF(COUNT($G21:$K21)=0,"",N($I21)+N($J21)) | M21: =IF(COUNT($G21:$K21)=0,"",N($G21)-N($H21)+N($J21)+N($K21)) | S21: =IF(COUNT($N21:$R21)=0,"",N($P21)+N($Q21)) | T21: =IF(COUNT($N21:$R21)=0,"",N($N21)-N($O21)+N($Q21)+N($R21))
A22: 15 | L22: =IF(COUNT($G22:$K22)=0,"",N($I22)+N($J22)) | M22: =IF(COUNT($G22:$K22)=0,"",N($G22)-N($H22)+N($J22)+N($K22)) | S22: =IF(COUNT($N22:$R22)=0,"",N($P22)+N($Q22)) | T22: =IF(COUNT($N22:$R22)=0,"",N($N22)-N($O22)+N($Q22)+N($R22))
A23: 16 | L23: =IF(COUNT($G23:$K23)=0,"",N($I23)+N($J23)) | M23: =IF(COUNT($G23:$K23)=0,"",N($G23)-N($H23)+N($J23)+N($K23)) | S23: =IF(COUNT($N23:$R23)=0,"",N($P23)+N($Q23)) | T23: =IF(COUNT($N23:$R23)=0,"",N($N23)-N($O23)+N($Q23)+N($R23))
A24: 17 | L24: =IF(COUNT($G24:$K24)=0,"",N($I24)+N($J24)) | M24: =IF(COUNT($G24:$K24)=0,"",N($G24)-N($H24)+N($J24)+N($K24)) | S24: =IF(COUNT($N24:$R24)=0,"",N($P24)+N($Q24)) | T24: =IF(COUNT($N24:$R24)=0,"",N($N24)-N($O24)+N($Q24)+N($R24))
A25: 18 | L25: =IF(COUNT($G25:$K25)=0,"",N($I25)+N($J25)) | M25: =IF(COUNT($G25:$K25)=0,"",N($G25)-N($H25)+N($J25)+N($K25)) | S25: =IF(COUNT($N25:$R25)=0,"",N($P25)+N($Q25)) | T25: =IF(COUNT($N25:$R25)=0,"",N($N25)-N($O25)+N($Q25)+N($R25))
A26: 19 | L26: =IF(COUNT($G26:$K26)=0,"",N($I26)+N($J26)) | M26: =IF(COUNT($G26:$K26)=0,"",N($G26)-N($H26)+N($J26)+N($K26)) | S26: =IF(COUNT($N26:$R26)=0,"",N($P26)+N($Q26)) | T26: =IF(COUNT($N26:$R26)=0,"",N($N26)-N($O26)+N($Q26)+N($R26))
... A37: 30 | L37: =IF(COUNT($G37:$K37)=0,"",N($I37)+N($J37)) | M37: =IF(COUNT($G37:$K37)=0,"",N($G37)-N($H37)+N($J37)+N($K37)) | S37: =IF(COUNT($N37:$R37)=0,"",N($P37)+N($Q37)) | T37: =IF(COUNT($N37:$R37)=0,"",N($N37)-N($O37)+N($Q37)+N($R37))
B38: TOTAL (Dart LOC rows only) | G38: =SUMIF($F$8:$F$37,"Dart LOC",G$8:G$37) | H38: =SUMIF($F$8:$F$37,"Dart LOC",H$8:H$37) | I38: =SUMIF($F$8:$F$37,"Dart LOC",I$8:I$37) | J38: =SUMIF($F$8:$F$37,"Dart LOC",J$8:J$37) | K38: =SUMIF($F$8:$F$37,"Dart LOC",K$8:K$37) | L38: =SUMIF($F$8:$F$37,"Dart LOC",L$8:L$37) | M38: =SUMIF($F$8:$F$37,"Dart LOC",M$8:M$37) | N38: =SUMIF($F$8:$F$37,"Dart LOC",N$8:N$37) | ... T38: =SUMIF($F$8:$F$37,"Dart LOC",T$8:T$37)
A40: Document & Artefact Size
B41: Artefact | F41: Measure | G41: Plan | M41: Actual
B42: Software Requirements Specification (SRS) | F42: SRS Pages | G42: 60 | M42: 64
B43: Software Design Document (SDD) | F43: SDD Pages | G43: 50 | M43: 58
B44: User Manual | F44: Documents | G44: 1 | M44: 1
B45: Test Plan | F45: Documents | G45: 1 | M45: 1
B46: Final Report | F46: Documents | G46: 1 | M46: 1
B47: Screens delivered | F47: Screens | G47: 14 | M47: 16
B48: Reusable widgets built | F48: Widgets | G48: 20 | M48: 24
B49: API endpoints consumed | F49: API Endpoints | G49: 8 | M49: 9

Sheet SUMP
A1: Form SUMP - Plan Summary
A2: Plan columns are yours to fill at the launch. Actual columns read themselves out of the logs.
A4: Team | B4: =SETUP!$C$10 | D4: Cycle / milestone
A6: Program Size
B7: Plan | C7: Actual | D7: Actual % | F7: Source
A8: Total requirements pages (SRS) | B8: =SUMS!$G$42 | C8: =SUMS!$M$42 | F8: SUMS document block
A9: Total design pages (SDD) | B9: =SUMS!$G$43 | C9: =SUMS!$M$43 | F9: SUMS document block
A10: New & changed Dart LOC (N) | B10: =SUMS!$L$38 | C10: =SUMS!$S$38 | F10: SUMS component totals
A11: Total Dart LOC (T) | B11: =SUMS!$M$38 | C11: =SUMS!$T$38 | F11: SUMS component totals
A12: Reused Dart LOC (R) | B12: =SUMS!$K$38 | C12: =SUMS!$R$38 | F12: SUMS component totals
A13: Screens delivered | B13: =SUMS!$G$47 | C13: =SUMS!$M$47 | F13: SUMS document block
A14: Reusable widgets built | B14: =SUMS!$G$48 | C14: =SUMS!$M$48 | F14: SUMS document block
A16: Time in Phase (hours)
A17: Phase | B17: Plan | C17: Actual | D17: Actual % | E17: Plan % | F17: Description
A18: MGMT | B18: 7 | C18: =SUMIFS(LOGT!$K$7:$K$406,LOGT!$E$7:$E$406,"MGMT")/60 | D18: =IF($C$44=0,"",$C18/$C$44) | E18: =IF($B$44=0,"",$B18/$B$44) | F18: Management & Miscellaneous
A19: STRAT | B19: 11 | C19: =SUMIFS(LOGT!$K$7:$K$406,LOGT!$E$7:$E$406,"STRAT")/60 | D19: =IF($C$44=0,"",$C19/$C$44) | E19: =IF($B$44=0,"",$B19/$B$44) | F19: Launch & Strategy
A20: PLAN | B20: 10.5 | C20: =SUMIFS(LOGT!$K$7:$K$406,LOGT!$E$7:$E$406,"PLAN")/60 | D20: =IF($C$44=0,"",$C20/$C$44) | E20: =IF($B$44=0,"",$B20/$B$44) | F20: Planning
A21: REQ | B21: 7 | C21: =SUMIFS(LOGT!$K$7:$K$406,LOGT!$E$7:$E$406,"REQ")/60 | D21: =IF($C$44=0,"",$C21/$C$44) | E21: =IF($B$44=0,"",$B21/$B$44) | F21: Requirements / SRS
A22: STP | B22: 6 | C22: =SUMIFS(LOGT!$K$7:$K$406,LOGT!$E$7:$E$406,"STP")/60 | D22: =IF($C$44=0,"",$C22/$C$44) | E22: =IF($B$44=0,"",$B22/$B$44) | F22: System Test Plan
A23: REQINSP | B23: 11 | C23: =SUMIFS(LOGT!$K$7:$K$406,LOGT!$E$7:$E$406,"REQINSP")/60 | D23: =IF($C$44=0,"",$C23/$C$44) | E23: =IF($B$44=0,"",$B23/$B$44) | F23: Requirements Inspection
A24: HLD | B24: 9.5 | C24: =SUMIFS(LOGT!$K$7:$K$406,LOGT!$E$7:$E$406,"HLD")/60 | D24: =IF($C$44=0,"",$C24/$C$44) | E24: =IF($B$44=0,"",$B24/$B$44) | F24: High-Level Design / Architecture (SDD)
A25: ITP | B25: 6 | C25: =SUMIFS(LOGT!$K$7:$K$406,LOGT!$E$7:$E$406,"ITP")/60 | D25: =IF($C$44=0,"",$C25/$C$44) | E25: =IF($B$44=0,"",$B25/$B$44) | F25: Integration Test Plan
A26: HLDINSP | B26: 6 | C26: =SUMIFS(LOGT!$K$7:$K$406,LOGT!$E$7:$E$406,"HLDINSP")/60 | D26: =IF($C$44=0,"",$C26/$C$44) | E26: =IF($B$44=0,"",$B26/$B$44) | F26: HLD Inspection
A27: DLD | B27: 27.5 | C27: =SUMIFS(LOGT!$K$7:$K$406,LOGT!$E$7:$E$406,"DLD")/60 | D27: =IF($C$44=0,"",$C27/$C$44) | E27: =IF($B$44=0,"",$B27/$B$44) | F27: Detailed Design (screens, widgets, models)
A28: DLDR | B28: 40.5 | C28: =SUMIFS(LOGT!$K$7:$K$406,LOGT!$E$7:$E$406,"DLDR")/60 | D28: =IF($C$44=0,"",$C28/$C$44) | E28: =IF($B$44=0,"",$B28/$B$44) | F28: Detailed Design Review
A29: TD | B29: 37 | C29: =SUMIFS(LOGT!$K$7:$K$406,LOGT!$E$7:$E$406,"TD")/60 | D29: =IF($C$44=0,"",$C29/$C$44) | E29: =IF($B$44=0,"",$B29/$B$44) | F29: Test Development
A30: DLDINSP | B30: 25.5 | C30: =SUMIFS(LOGT!$K$7:$K$406,LOGT!$E$7:$E$406,"DLDINSP")/60 | D30: =IF($C$44=0,"",$C30/$C$44) | E30: =IF($B$44=0,"",$B30/$B$44) | F30: Detailed Design Inspection
A31: CODE | B31: 66 | C31: =SUMIFS(LOGT!$K$7:$K$406,LOGT!$E$7:$E$406,"CODE")/60 | D31: =IF($C$44=0,"",$C31/$C$44) | E31: =IF($B$44=0,"",$B31/$B$44) | F31: Code - hand-written Dart/Flutter
A32: AIGEN | B32: 30 | C32: =SUMIFS(LOGT!$K$7:$K$406,LOGT!$E$7:$E$406,"AIGEN")/60 | D32: =IF($C$44=0,"",$C32/$C$44) | E32: =IF($B$44=0,"",$B32/$B$44) | F32: Code - AI-assisted generation (Vibe)
A33: CR | B33: 37 | C33: =SUMIFS(LOGT!$K$7:$K$406,LOGT!$E$7:$E$406,"CR")/60 | D33: =IF($C$44=0,"",$C33/$C$44) | E33: =IF($B$44=0,"",$B33/$B$44) | F33: Code Review / Pull-Request Review
A34: BUILD | B34: 34.5 | C34: =SUMIFS(LOGT!$K$7:$K$406,LOGT!$E$7:$E$406,"BUILD")/60 | D34: =IF($C$44=0,"",$C34/$C$44) | E34: =IF($B$44=0,"",$B34/$B$44) | F34: Build & Static Analysis (flutter analyze)
A35: CODEINSP | B35: 36 | C35: =SUMIFS(LOGT!$K$7:$K$406,LOGT!$E$7:$E$406,"CODEINSP")/60 | D35: =IF($C$44=0,"",$C35/$C$44) | E35: =IF($B$44=0,"",$B35/$B$44) | F35: Code Inspection
A36: UT | B36: 35 | C36: =SUMIFS(LOGT!$K$7:$K$406,LOGT!$E$7:$E$406,"UT")/60 | D36: =IF($C$44=0,"",$C36/$C$44) | E36: =IF($B$44=0,"",$B36/$B$44) | F36: Unit Test
A37: WT | B37: 14 | C37: =SUMIFS(LOGT!$K$7:$K$406,LOGT!$E$7:$E$406,"WT")/60 | D37: =IF($C$44=0,"",$C37/$C$44) | E37: =IF($B$44=0,"",$B37/$B$44) | F37: Widget Test
A38: IT | B38: 17 | C38: =SUMIFS(LOGT!$K$7:$K$406,LOGT!$E$7:$E$406,"IT")/60 | D38: =IF($C$44=0,"",$C38/$C$44) | E38: =IF($B$44=0,"",$B38/$B$44) | F38: Build & Integration Test
A39: CICD | B39: 10 | C39: =SUMIFS(LOGT!$K$7:$K$406,LOGT!$E$7:$E$406,"CICD")/60 | D39: =IF($C$44=0,"",$C39/$C$44) | E39: =IF($B$44=0,"",$B39/$B$44) | F39: CI/CD Pipeline (GitHub Actions)
A40: ST | B40: 20 | C40: =SUMIFS(LOGT!$K$7:$K$406,LOGT!$E$7:$E$406,"ST")/60 | D40: =IF($C$44=0,"",$C40/$C$44) | E40: =IF($B$44=0,"",$B40/$B$44) | F40: System Test
A41: UAT | B41: 8 | C41: =SUMIFS(LOGT!$K$7:$K$406,LOGT!$E$7:$E$406,"UAT")/60 | D41: =IF($C$44=0,"",$C41/$C$44) | E41: =IF($B$44=0,"",$B41/$B$44) | F41: Client Acceptance Test
A42: DOC | B42: 16 | C42: =SUMIFS(LOGT!$K$7:$K$406,LOGT!$E$7:$E$406,"DOC")/60 | D42: =IF($C$44=0,"",$C42/$C$44) | E42: =IF($B$44=0,"",$B42/$B$44) | F42: Documentation & User Manual
A43: PM | B43: 12 | C43: =SUMIFS(LOGT!$K$7:$K$406,LOGT!$E$7:$E$406,"PM")/60 | D43: =IF($C$44=0,"",$C43/$C$44) | E43: =IF($B$44=0,"",$B43/$B$44) | F43: Postmortem
A44: TOTAL | B44: =SUM(B18:B43) | C44: =SUM(C18:C43) | D44: =IF($C$44=0,"",1) | E44: =IF($B$44=0,"",1)
A46: Defects Injected
A47: Phase | B47: Plan | C47: Actual | D47: Actual % | F47: Description
A48: PLAN | C48: =COUNTIFS(LOGD!$G$7:$G$306,"PLAN") | D48: =IF($C$69=0,"",$C48/$C$69) | F48: Planning
A49: REQ | B49: 8 | C49: =COUNTIFS(LOGD!$G$7:$G$306,"REQ") | D49: =IF($C$69=0,"",$C49/$C$69) | F49: Requirements / SRS
A50: STP | C50: =COUNTIFS(LOGD!$G$7:$G$306,"STP") | D50: =IF($C$69=0,"",$C50/$C$69) | F50: System Test Plan
A51: REQINSP | C51: =COUNTIFS(LOGD!$G$7:$G$306,"REQINSP") | D51: =IF($C$69=0,"",$C51/$C$69) | F51: Requirements Inspection
